Workbook

Sheet Main Page
A1: SL | B1: Category (FG) | D1: Item Description | E1: Production Plan | F1: ERP Production Done | G1: Physical Production Done | H1: ERP Pending | I1: Production Due | K1: Daily Target
A2: Exhaust Fan
A3: 1 | B3: EF0801OW/EF0801OW | C3: Ex-08 Copper | D3: 08 Inch Fresh Air Exhaust Fan Off White | E3: 2700 | F3: {=_xlfn.XLOOKUP(B3:B6,'ERP Entry FG'!E:E,'ERP Entry FG'!L:L,0)} -> 2690 | G3: 2522 | H3: =G3-F3 -> -168 | I3: =E3-G3 -> 178 | K3: 200
A4: 2 | B4: EF1001OW/EF1001OW | C4: Ex-10 Copper | D4: 10 Inch Fresh Air Exhaust Fan Off White | E4: 2200 | F4: 1554 | G4: 870 | H4: =G4-F4 -> -684 | I4: =E4-G4 -> 1330 | K4: 1000
A5: 3 | B5: EF1001AF | C5: Ex-10 Aluminium | D5: Aero Flow 10`` Exhaust Fan | E5: 8300 | F5: 3078 | G5: 3048 | H5: =G5-F5 -> -30 | I5: =E5-G5 -> 5252 | K5: 1000
A6: 4 | B6: EF0801AF | C6: Ex-08 Aluminium | D6: Aero Flow 8`` Exhaust Fan | E6: 2600 | F6: 2626 | G6: 2626 | H6: =G6-F6 -> 0 | I6: =E6-G6 -> -26 | K6: 1000
A8: Capacitor
A9: 1 | B9: CFCP001 | C9: Capacitor 2.5 | D9: Ceiling Fan Capacitor 2.5 uf | E9: 75000 | F9: {=_xlfn.XLOOKUP(B9:B10,'ERP Entry FG'!E:E,'ERP Entry FG'!L:L,0)} -> 70128 | G9: 54000 | H9: =G9-F9 -> -16128 | I9: =E9-G9 -> 21000 | K9: 7000
A10: 2 | B10: CFCP002 | C10: Capacitor 3.5 | D10: Ceiling Fan Capacitor 3.5 uf | E10: 50000 | F10: 79872 | G10: 27360 | H10: =G10-F10 -> -52512 | I10: =E10-G10 -> 22640 | K10: 7000
A12: Ceiling Fan | E12: =SUM(E13:E20) -> 45000
A13: 1 | B13: CF5601/CF5601IV | C13: CF 5601 | D13: 56 Inch Premium Ceiling Fan - Ivory | E13: 30000 | F13: {=_xlfn.XLOOKUP(B13:B20,'ERP Entry FG'!E:E,'ERP Entry FG'!L:L,0)} -> 30786 | I13: =E13-G13 -> 30000 | K13: 1000
A14: 2 | B14: CF5602/CF5602IV | C14: CF 5602 | D14: 56 Inch Speed King Ceiling Fan - Ivory | F14: 0 | I14: =E14-G14 -> 0
A15: 3 | B15: CF5603/CF5603IV | C15: CF 5603 | D15: 56 Inch Premium Gold Ceiling Fan - Ivory | F15: 0 | I15: =E15-G15 -> 0 | K15: 1000 | Q15: =128+39+170 -> 337
A16: 4 | B16: CF5606/CF5606IV | C16: CF 5606 | D16: 56 Inch Premium Plus Ceiling Fan - Ivory | F16: 60 | I16: =E16-G16 -> 0 | Q16: =Q15*4*12 -> 16176 | V16: CF5601/CF5601IV | X16: 56 Inch Premium Ceiling Fan - Ivory
A17: 5 | B17: CF5607/CF5607IV | C17: CF 5607 | D17: 56 Inch Crown Ceiling Fan - Ivory | F17: 335 | I17: =E17-G17 -> 0 | K17: 50 | V17: CF5602/CF5602IV | X17: 56 Inch Speed King Ceiling Fan - Ivory
A18: 6 | B18: CF4801/CF4801IV | C18: CF 4801 | D18: 48 Inch Popular Ceiling Fan - Ivory | E18: 5000 | F18: 1100 | I18: =E18-G18 -> 5000 | V18: CF5603/CF5603IV | X18: Inch Premium Gold Ceiling Fan - Ivory
A19: 7 | B19: CF3601/CF3601IV | C19: CF 3601 | D19: 36 Inch Hero Ceiling Fan - Ivory | E19: 5000 | F19: 8000 | I19: =E19-G19 -> 5000 | V19: CF5606/CF5606IV | X19: 56 Inch Premium Plus Ceiling Fan - Ivory
A20: 8 | B20: CF2401/CF2401IV | C20: CF 2401 | D20: 24 Inch Super Ceiling Fan - Ivory | E20: 5000 | F20: 1091 | I20: =E20-G20 -> 5000 | V20: CF5607/CF5607IV | X20: 56 Inch Crown Ceiling Fan - Ivory
B22: CFB2401/FB2401IV | D22: {=_xlfn.XLOOKUP(B22:B31,'ERP Entry FG'!E:E,'ERP Entry FG'!F:F)} -> 24 Inch Super Ceiling Fan Blade - Ivory | F22: {=_xlfn.XLOOKUP(B22:B31,'ERP Entry FG'!E:E,'ERP Entry FG'!L:L,0)} -> 0 | V22: CF3601/CF3601IV | X22: 36 Inch Hero Ceiling Fan - Ivory
B23: CR3601IV | D23: 36 Inch Hero Ceiling Fan- Ivory (Without Regulator) | F23: 0 | V23: CF2401/CF2401IV | X23: 24 Inch Super Ceiling Fan - Ivory
B24: CFB3601/FB3601IV | D24: 36 Inch Hero Celling Fan Blade - Ivory | F24: 1
B25: CFB4801/FB4801IV | D25: 48 Inch Popular Celling Fan Blade- Ivory | F25: 0
B26: CF5601WH/CF5601WH | D26: 56 Inch Premium Ceiling Fan - White | F26: 49 | P26: =170*4*12 -> 8160
B27: CFB5601/FB5601IV | D27: 56 Inch Premium Ceiling Fan Blade - Ivory | F27: 0
B28: CR5601IV | D28: 56 Inch Premium Ceiling Fan- Ivory (Without Regulator) | F28: 2015
B29: CR5601WH | D29: 56 Inch Premium Ceiling Fan- White (Without Regulator) | F29: 56
B30: CG5606/CG5606IV | D30: 56 Inch Premium Plus Ceiling Fan With Gang Regulator - Ivory | F30: 0
B31: CR5606IV | D31: 56 Inch Premium Plus Ceiling Fan- Ivory (Without Regulator) | F31: 0

Sheet Stock
A1: MEP FAN LTD | Q1: Item Name | R1: Pending | S1: ERP Pending | T1: Daily Production | U1: Total
Q2: Ex-10 Aluminium | R2: =_xlfn.XLOOKUP(Q2,'Main Page'!C3:C20,'Main Page'!I3:I20,0) -> 5252 | T2: 5000 | U2: =SUM(S2:T2) -> 5000
A3: SL | B3: Category | C3: Item Code | D3: Item Description | E3: Unit | F3: BOM | G3: Total RM Consumption | H3: Store Stock | I3: Floor Stock | J3: Total RM Requirement | L3: Daily RM Consumption | M3: Store Stock | N3: Floor Stock | O3: Daily RM Requirement
A4: {=_xlfn._xlws.FILTER(BOM!A2:F1174,BOM!G2:G1174=Stock!Q2)} -> 1 | B4: Ceiling Raw | C4: 3101010023 | D4: FAN Ampere Tube-04 no | E4: Mtr | F4: 0.129 | G4: =IF(F4*$R$2=0,"",F4*$R$2) -> 677.508 | H4: {=_xlfn.XLOOKUP(C4:C44,'ERP Entry Stock'!G:G,'ERP Entry Stock'!J:J,0)} -> 3200.004 | I4: {=_xlfn.XLOOKUP(C4:C44,'ERP Entry Stock'!G:G,'ERP Entry Stock'!K:K,0)} -> 3475.627 | J4: =MAX(0,G4-H4-I4) -> 0 | L4: =F4*$U$2 -> 645 | M4: {=_xlfn.XLOOKUP(C4:C44,'ERP Entry Stock'!G:G,'ERP Entry Stock'!J:J,0)} -> 3200.004 | N4: {=_xlfn.XLOOKUP(C4:C44,'ERP Entry Stock'!G:G,'ERP Entry Stock'!K:K,0)} -> 3475.627 | O4: =MAX(0,L4-H4-I4) -> 0
A5: 2 | B5: Ceiling Raw | C5: 3101010094 | D5: Soldering Wire | E5: KG | F5: 0.001 | G5: =F5*$R$2 -> 5.252 | H5: 27.997 | I5: 5.991 | J5: =MAX(0,G5-H5-I5) -> 0 | L5: =F5*$U$2 -> 5 | M5: 27.997 | N5: 5.991 | O5: =MAX(0,L5-H5-I5) -> 0
A6: 3 | B6: Exhaust Raw | C6: 3102010013 | D6: 5/32 Inch, 9mm Screw | E6: KG | F6: 0.009 | G6: =F6*$R$2 -> 47.268 | H6: 0.004 | I6: 28.453 | J6: =MAX(0,G6-H6-I6) -> 18.811 | L6: =F6*$U$2 -> 45 | M6: 0.004 | N6: 28.453 | O6: =MAX(0,L6-H6-I6) -> 16.543
A7: 4 | B7: Exhaust Raw | C7: 3102010012 | D7: Cable 2x23/0.0076 | E7: Mtr | F7: 0.62 | G7: =F7*$R$2 -> 3256.24 | H7: 5000 | I7: 774.54 | J7: =MAX(0,G7-H7-I7) -> 0 | L7: =F7*$U$2 -> 3100 | M7: 5000 | N7: 774.54 | O7: =MAX(0,L7-H7-I7) -> 0
A8: 5 | B8: Exhaust Raw | C8: 3202010010 | D8: Exhaust Fan Base (10``) | E8: Pcs | F8: 1 | G8: =F8*$R$2 -> 5252 | H8: 3901 | I8: 5343 | J8: =MAX(0,G8-H8-I8) -> 0 | L8: =F8*$U$2 -> 5000 | M8: 3901 | N8: 5343 | O8: =MAX(0,L8-H8-I8) -> 0
A9: 6 | B9: Exhaust Raw | C9: 3202010017 | D9: Exhaust Fan Blade (10``) | E9: Pcs | F9: 1 | G9: =F9*$R$2 -> 5252 | H9: 3463 | I9: 816 | J9: =MAX(0,G9-H9-I9) -> 973 | L9: =F9*$U$2 -> 5000 | M9: 3463 | N9: 816 | O9: =MAX(0,L9-H9-I9) -> 721
A10: 7 | B10: Exhaust Raw | C10: 3102010022 | D10: Exhaust Fan Capacitor 1.5 µF | E10: Pcs | F10: 1 | G10: =F10*$R$2 -> 5252 | H10: 0 | I10: 5263 | J10: =MAX(0,G10-H10-I10) -> 0 | L10: =F10*$U$2 -> 5000 | M10: 0 | N10: 5263 | O10: =MAX(0,L10-H10-I10) -> 0 | X10: Ex-08 Copper
A11: 8 | B11: Exhaust Raw | C11: 3102010007 | D11: Exhaust Fan Capacitor Box | E11: Pcs | F11: 1 | G11: =F11*$R$2 -> 5252 | H11: 4572 | I11: 1646 | J11: =MAX(0,G11-H11-I11) -> 0 | L11: =F11*$U$2 -> 5000 | M11: 4572 | N11: 1646 | O11: =MAX(0,L11-H11-I11) -> 0 | X11: Ex-10 Copper
A12: 9 | B12: Exhaust Raw | C12: 3102010009 | D12: Exhaust Fan Clam | E12: Pcs | F12: 1 | G12: =F12*$R$2 -> 5252 | H12: 0 | I12: 18417 | J12: =MAX(0,G12-H12-I12) -> 0 | L12: =F12*$U$2 -> 5000 | M12: 0 | N12: 18417 | O12: =MAX(0,L12-H12-I12) -> 0 | X12: Ex-10 Aluminium
A13: 10 | B13: Exhaust Raw | C13: 3202010011 | D13: Exhaust Fan Cover (10``) | E13: Pcs | F13: 1 | G13: =F13*$R$2 -> 5252 | H13: 2460 | I13: 754 | J13: =MAX(0,G13-H13-I13) -> 2038 | L13: =F13*$U$2 -> 5000 | M13: 2460 | N13: 754 | O13: =MAX(0,L13-H13-I13) -> 1786 | X13: Ex-08 Aluminium
A14: 11 | B14: Exhaust Raw | C14: 3102010021 | D14: Exhaust Fan Motor (10``)-Alu | E14: Pcs | F14: 1 | G14: =F14*$R$2 -> 5252 | H14: 0 | I14: 2549 | J14: =MAX(0,G14-H14-I14) -> 2703 | L14: =F14*$U$2 -> 5000 | M14: 0 | N14: 2549 | O14: =MAX(0,L14-H14-I14) -> 2451 | X14: Capacitor 2.5
A15: 12 | B15: Exhaust Raw | C15: 3102010006 | D15: Exhaust Fan Show Cap With Pitol Bush | E15: Pcs | F15: 1 | G15: =F15*$R$2 -> 5252 | H15: 0 | I15: 3320 | J15: =MAX(0,G15-H15-I15) -> 1932 | L15: =F15*$U$2 -> 5000 | M15: 0 | N15: 3320 | O15: =MAX(0,L15-H15-I15) -> 1680 | X15: Capacitor 3.5
A16: 13 | B16: Exhaust Raw | C16: 3202010013 | D16: Exhaust Fan Shutter (10``) | E16: Pcs | F16: 3 | G16: =F16*$R$2 -> 15756 | H16: 465 | I16: 2434 | J16: =MAX(0,G16-H16-I16) -> 12857 | L16: =F16*$U$2 -> 15000 | M16: 465 | N16: 2434 | O16: =MAX(0,L16-H16-I16) -> 12101 | X16: CF 5601
A17: 14 | B17: Exhaust Raw | C17: 3202010012 | D17: Exhaust Fan Side Stand (10``) | E17: Pcs | F17: 1 | G17: =F17*$R$2 -> 5252 | H17: 7481 | I17: 4968 | J17: =MAX(0,G17-H17-I17) -> 0 | L17: =F17*$U$2 -> 5000 | M17: 7481 | N17: 4968 | O17: =MAX(0,L17-H17-I17) -> 0 | X17: CF 5602
A18: 15 | B18: Exhaust Raw | C18: 3102010010 | D18: Exhaust Fan Spring (FAN) | E18: KG | F18: 0.0028 | G18: =F18*$R$2 -> 14.7056 | H18: 0.0036 | I18: 0.0012 | J18: =MAX(0,G18-H18-I18) -> 14.7008 | L18: =F18*$U$2 -> 14 | M18: 0.0036 | N18: 0.0012 | O18: =MAX(0,L18-H18-I18) -> 13.9952 | X18: CF 5603
A19: 16 | B19: Exhaust Raw | C19: 3102010011 | D19: Exhaust Fan Spring Lock | E19: Pcs | F19: 1 | G19: =F19*$R$2 -> 5252 | H19: 3500 | I19: 7365 | J19: =MAX(0,G19-H19-I19) -> 0 | L19: =F19*$U$2 -> 5000 | M19: 3500 | N19: 7365 | O19: =MAX(0,L19-H19-I19) -> 0 | X19: CF 5606
A20: 17 | B20: Exhaust Raw | C20: 3202010014 | D20: Exhaust Fan Stick (10``) | E20: Pcs | F20: 1 | G20: =F20*$R$2 -> 5252 | H20: 8929 | I20: 1766 | J20: =MAX(0,G20-H20-I20) -> 0 | L20: =F20*$U$2 -> 5000 | M20: 8929 | N20: 1766 | O20: =MAX(0,L20-H20-I20) -> 0 | X20: CF 5607
A21: 18 | B21: Exhaust Raw | C21: 3102010010 | D21: Exhaust Fan Spring (FAN) | E21: Pcs | F21: 1 | G21: =F21*$R$2 -> 5252 | H21: 0.0036 | I21: 0.0012 | J21: =MAX(0,G21-H21-I21) -> 5251.9952 | L21: =F21*$U$2 -> 5000 | M21: 0.0036 | N21: 0.0012 | O21: =MAX(0,L21-H21-I21) -> 4999.9952 | X21: CF 4801
... A23: 20 | B23: Exhaust Raw | C23: 3202010008 | D23: HDPE Poly 20x24``-(Std.W.-0.015016 kg) | E23: KG | F23: 0.017 | G23: =F23*$R$2 -> 89.284 | H23: 505.002 | I23: 54.056 | J23: =MAX(0,G23-H23-I23) -> 0 | L23: =F23*$U$2 -> 85 | M23: 505.002 | N23: 54.056 | O23: =MAX(0,L23-H23-I23) -> 0 | X23: CF 2401
A24: 21 | B24: Exhaust Raw | C24: 3102010019 | D24: MEP Cable Tie -3.5x150mm | E24: Pcs | F24: 1 | G24: =F24*$R$2 -> 5252 | H24: 16000 | I24: 1187 | J24: =MAX(0,G24-H24-I24) -> 0 | L24: =F24*$U$2 -> 5000 | M24: 16000 | N24: 1187 | O24: =MAX(0,L24-H24-I24) -> 0
A25: 22 | B25: Exhaust Raw | C25: 3202010007 | D25: PP Band Fita | E25: KG | F25: 0.007 | G25: =F25*$R$2 -> 36.764 | H25: 94.87 | I25: 33.7123 | J25: =MAX(0,G25-H25-I25) -> 0 | L25: =F25*$U$2 -> 35 | M25: 94.87 | N25: 33.7123 | O25: =MAX(0,L25-H25-I25) -> 0
A26: 23 | B26: Packing Materials - FAN | C26: 3201010080 | D26: 10 Inch Exhaust Fan Body Carton (Alu) | E26: Pcs | F26: 1 | G26: =F26*$R$2 -> 5252 | H26: 516 | I26: 74 | J26: =MAX(0,G26-H26-I26) -> 4662 | L26: =F26*$U$2 -> 5000 | M26: 516 | N26: 74 | O26: =MAX(0,L26-H26-I26) -> 4410
A27: 24 | B27: Packing Materials - FAN | C27: 3201010081 | D27: Aero Flow Sticker | E27: Pcs | F27: 1 | G27: =F27*$R$2 -> 5252 | H27: 17750 | I27: 3263 | J27: =MAX(0,G27-H27-I27) -> 0 | L27: =F27*$U$2 -> 5000 | M27: 17750 | N27: 3263 | O27: =MAX(0,L27-H27-I27) -> 0
A28: 25 | B28: Packing Materials - FAN | C28: 3201010046 | D28: Carton Tape - (W=60mm,L=200m, MEP Print) | E28: Mtr | F28: 1.14 | G28: =F28*$R$2 -> 5987.28 | H28: 18952 | I28: 31826.915 | J28: =MAX(0,G28-H28-I28) -> 0 | L28: =F28*$U$2 -> 5700 | M28: 18952 | N28: 31826.915 | O28: =MAX(0,L28-H28-I28) -> 0
A29: 26 | B29: Packing Materials - FAN | C29: 3201010014 | D29: Fan QC Sticker | E29: Pcs | F29: 1 | G29: =F29*$R$2 -> 5252 | H29: 50500 | I29: 39511 | J29: =MAX(0,G29-H29-I29) -> 0 | L29: =F29*$U$2 -> 5000 | M29: 50500 | N29: 39511 | O29: =MAX(0,L29-H29-I29) -> 0
A30: 27 | B30: Packing Materials - FAN | C30: 3201010062 | D30: MEP Hologram Sticker | E30: Pcs | F30: 1 | G30: =F30*$R$2 -> 5252 | H30: 98100 | I30: 28412 | J30: =MAX(0,G30-H30-I30) -> 0 | L30: =F30*$U$2 -> 5000 | M30: 98100 | N30: 28412 | O30: =MAX(0,L30-H30-I30) -> 0
G31: =F31*$R$2 -> 0 | H31: 0 | I31: 0 | J31: =MAX(0,G31-H31-I31) -> 0 | L31: =F31*$U$2 -> 0 | M31: 0 | N31: 0 | O31: =MAX(0,L31-H31-I31) -> 0
G32: =F32*$R$2 -> 0 | H32: 0 | I32: 0 | J32: =MAX(0,G32-H32-I32) -> 0 | L32: =F32*$U$2 -> 0 | M32: 0 | N32: 0 | O32: =MAX(0,L32-H32-I32) -> 0
G33: =F33*$R$2 -> 0 | H33: 0 | I33: 0 | J33: =MAX(0,G33-H33-I33) -> 0 | L33: =F33*$U$2 -> 0 | M33: 0 | N33: 0 | O33: =MAX(0,L33-H33-I33) -> 0
G34: =F34*$R$2 -> 0 | H34: 0 | I34: 0 | J34: =MAX(0,G34-H34-I34) -> 0 | L34: =F34*$U$2 -> 0 | M34: 0 | N34: 0 | O34: =MAX(0,L34-H34-I34) -> 0
G35: =F35*$R$2 -> 0 | H35: 0 | I35: 0 | J35: =MAX(0,G35-H35-I35) -> 0 | L35: =F35*$U$2 -> 0 | M35: 0 | N35: 0 | O35: =MAX(0,L35-H35-I35) -> 0
G36: =F36*$R$2 -> 0 | H36: 0 | I36: 0 | J36: =MAX(0,G36-H36-I36) -> 0 | L36: =F36*$U$2 -> 0 | M36: 0 | N36: 0 | O36: =MAX(0,L36-H36-I36) -> 0
G37: =F37*$R$2 -> 0 | H37: 0 | I37: 0 | J37: =MAX(0,G37-H37-I37) -> 0 | L37: =F37*$U$2 -> 0 | M37: 0 | N37: 0 | O37: =MAX(0,L37-H37-I37) -> 0
G38: =F38*$R$2 -> 0 | H38: 0 | I38: 0 | J38: =MAX(0,G38-H38-I38) -> 0 | L38: =F38*$U$2 -> 0 | M38: 0 | N38: 0 | O38: =MAX(0,L38-H38-I38) -> 0
G39: =F39*$R$2 -> 0 | H39: 0 | I39: 0 | J39: =MAX(0,G39-H39-I39) -> 0 | L39: =F39*$U$2 -> 0 | M39: 0 | N39: 0 | O39: =MAX(0,L39-H39-I39) -> 0
G40: =F40*$R$2 -> 0 | H40: 0 | I40: 0 | J40: =MAX(0,G40-H40-I40) -> 0 | L40: =F40*$U$2 -> 0 | M40: 0 | N40: 0 | O40: =MAX(0,L40-H40-I40) -> 0
G41: =F41*$R$2 -> 0 | H41: 0 | I41: 0 | J41: =MAX(0,G41-H41-I41) -> 0 | L41: =F41*$U$2 -> 0 | M41: 0 | N41: 0 | O41: =MAX(0,L41-H41-I41) -> 0
G42: =F42*$R$2 -> 0 | H42: 0 | I42: 0 | J42: =MAX(0,G42-H42-I42) -> 0 | L42: =F42*$U$2 -> 0 | M42: 0 | N42: 0 | O42: =MAX(0,L42-H42-I42) -> 0
... G44: =F44*$R$2 -> 0 | H44: 0 | I44: 0 | J44: =MAX(0,G44-H44-I44) -> 0 | L44: =F44*$U$2 -> 0 | M44: 0 | N44: 0 | O44: =MAX(0,L44-H44-I44) -> 0

Sheet ERP Entry Stock
A1: Warehouse Stock Position Report Detail(Closing)
A3: Closing Stock of Date-2026-08-29
A5: Reporting Time: 02:43 PM 29-08-2026
A6: S/L | B6: Company | C6: Group | D6: Category | E6: SubCategory | F6: Item Code | G6: FG | H6: Item Name | I6: Unit | J6: Store Qty | K6: Section Qty
A7: 1 | B7: FAN | E7: Fan Scrap | F7: 1500100001 | G7: 1500100001 | H7: Aluminium Bar Scrap | I7: KG | J7: 0 | K7: 7528.403
A8: 2 | B8: FAN | E8: Fan Scrap | F8: 1500100003 | G8: 1500100003 | H8: Silicon Sheet 25 Gage Scrap | I8: KG | J8: 0 | K8: 33798.194
A9: 3 | B9: FAN | E9: Fan Scrap | F9: 1500100014 | G9: 1500100014 | H9: Super Enamel Copper Scrap (Fan) | I9: KG | J9: 0 | K9: 0
A10: 4 | B10: FAN | E10: Ceiling Raw | F10: 200100002 | G10: 3101010001 | H10: Aluminum Ingot | I10: KG | J10: 34000 | K10: 2427.879
A11: 5 | B11: FAN | E11: Ceiling Raw | F11: 200100003 | G11: 3101010002 | H11: Aluminium Bar | I11: KG | J11: 0 | K11: 0
A12: 6 | B12: FAN | E12: Ceiling Raw | F12: 200100005 | G12: 3101010004 | H12: Aluminum Blade Sheet-1.22mm(18G) | I12: KG | J12: 9348 | K12: 14712.012
A13: 7 | B13: FAN | E13: Ceiling Raw | F13: 200100006 | G13: 3101010005 | H13: Silicon Sheet-0.51mm(25G) (Hard) | I13: KG | J13: 95315
A14: 8 | B14: FAN | E14: Ceiling Raw | F14: 200100007 | G14: 3101010006 | H14: Silicon Sheet 0.51mm (25G) Hard 7`` (179.9mm) | I14: KG | J14: 0 | K14: 84037.204
A15: 9 | B15: FAN | E15: Ceiling Raw | F15: 200100008 | G15: 3101010007 | H15: Silicon Sheet 0.51mm (25G) Hard 6`` (155.9mm) | I15: KG | J15: 0 | K15: 3313.749
A16: 10 | B16: FAN | E16: Ceiling Raw | F16: 200100009 | G16: 3101010008 | H16: Silicon Sheet 0.51mm (25G) Hard 5.5`` (142.8mm) | I16: KG | J16: 0 | K16: 12357.351
A17: 11 | B17: FAN | E17: Ceiling Raw | F17: 200100012 | G17: 3101010011 | H17: MS Shank Sheet 2.03mm(14G) (M Hard) | I17: KG | J17: 0 | K17: 10130.713
A18: 12 | B18: FAN | E18: Ceiling Raw | F18: 200100013 | G18: 3101010012 | H18: MS Shank/Clamp Sheet 1.83mm(15G) | I18: KG | J18: 0 | K18: 5751.224
A19: 13 | B19: FAN | E19: Ceiling Raw | F19: 200100014 | G19: 3101010013 | H19: MS Blade Sheet 0.61mm(23G) (Hard) | I19: KG | J19: 0 | K19: 7438.022
A20: 14 | B20: FAN | E20: Ceiling Raw | F20: 200100015 | G20: 3101010014 | H20: MS Blade Sheet 0.61mm(23G) (M Hard) | I20: KG | J20: 8205 | K20: 969.392
A21: 15 | B21: FAN | E21: Ceiling Raw | F21: 200100016 | G21: 3101010015 | H21: MS Pipe - OD=22mm, ID=18mm, T=2mm, L=20feet | I21: Feet | J21: 40000 | K21: 1560.85
A22: 16 | B22: FAN | E22: Ceiling Raw | F22: 200100017 | G22: 3101010016 | H22: Super Wire (SWG 33) / 0.253mm | I22: KG | J22: 6718.7 | K22: 17.29
A23: 17 | B23: FAN | E23: Ceiling Raw | F23: 200100018 | G23: 3101010017 | H23: Super Wire (SWG 34) / 0.233mm | I23: KG | J23: 10.38 | K23: 14.376
A24: 18 | B24: FAN | E24: Ceiling Raw | F24: 200100019 | G24: 3101010018 | H24: Super Wire (SWG 35) / 0.213mm | I24: KG | J24: 65.65 | K24: 39.22
A25: 19 | B25: FAN | E25: Ceiling Raw | F25: 200100020 | G25: 3101010019 | H25: Insulation Fiber 20 mm x 0.35mm | I25: KG | J25: 1728.733 | K25: 74.119
... A99: 93 | B99: FAN | E99: Ceiling Raw | F99: 200100116 | G99: 3101010117 | H99: Canopy White | I99: Pcs | J99: 10 | K99: 25
A100: 94 | B100: FAN | E100: Ceiling Raw | F100: 200100118 | G100: 3101010118 | H100: FAN Copper Rod 8mm | I100: KG | J100: 15900.29
A101: 95 | B101: FAN | E101: Ceiling Raw | F101: 200100119 | G101: 3101010119 | H101: Promotional Gang Regulator White (P512) | I101: Pcs | J101: 785 | K101: 0
A102: 96 | B102: FAN | E102: Ceiling Raw | F102: 200100120 | G102: 3101010120 | H102: XL/Shaft -178mm | I102: Pcs | J102: 742 | K102: 742
A103: 97 | B103: FAN | E103: Ceiling Raw | F103: 200100121 | G103: 3101010121 | H103: Down Pipe - 5607 | I103: Pcs | J103: 1100 | K103: 343
A104: 98 | B104: FAN | E104: Ceiling Raw | F104: 200100122 | G104: 3101010122 | H104: Neck - 5607 | I104: Pcs | J104: 700 | K104: 687
A105: 99 | B105: FAN | E105: Ceiling Raw | F105: 200100123 | G105: 3101010123 | H105: Canopy with Ring - 5607 | I105: Pcs | J105: 638 | K105: 198
A106: 100 | B106: FAN | E106: Ceiling Raw | F106: 200100124 | G106: 3101010124 | H106: Body Show Cap - 5607 | I106: Pcs | J106: 184 | K106: 192
A107: 101 | B107: FAN | E107: Ceiling Raw | F107: 200100125 | G107: 3101010125 | H107: Blade Show Cap - 5607 | I107: Pcs | J107: 0 | K107: 585
A108: 102 | B108: FAN | E108: Ceiling Raw | F108: 200100126 | G108: 3101010126 | H108: Capacitor Support- 5607 | I108: Pcs | J108: 0 | K108: 1164
A109: 103 | B109: FAN | E109: Ceiling Raw | F109: 200100127 | G109: 3101010127 | H109: Down Pipe Sira Pin (Big) | I109: Pcs | J109: 360 | K109: 191
A110: 104 | B110: FAN | E110: Ceiling Raw | F110: 200100128 | G110: 3101010128 | H110: Down Pipe Jam Nut - 5607 | I110: Pcs | J110: 200
A111: 105 | B111: FAN | E111: Ceiling Raw | F111: 200100129 | G111: 3101010129 | H111: Decorative Nut Bolt - 5607 | I111: Set | J111: 0 | K111: 2181
A112: 106 | B112: FAN | E112: Ceiling Raw | F112: 200100130 | G112: 3101010130 | H112: Body screw- 3/16`` x 35mm | I112: KG | J112: 10.001 | K112: 10.151
A113: 107 | B113: FAN | E113: Ceiling Raw | F113: 200100131 | G113: 3101010131 | H113: ADC12 Aluminium Ingot | I113: KG | J113: 0 | K113: 0
A114: 108 | B114: FAN | E114: Ceiling Raw | F114: 200100132 | G114: 3101010132 | H114: Aluminium Bar Scrap Local - FAN | I114: KG | J114: 0.002 | K114: 0.16994
A115: 109 | B115: FAN | E115: Ceiling Raw | F115: 200100133 | G115: 3101010133 | H115: Super Enamel Copper Scrap Local - FAN | I115: KG | J115: 42.63
A116: 110 | B116: FAN | E116: Ceiling Raw | F116: 200100134 | G116: 3101010134 | H116: MS Sheet 2.03mm(14G)-L/C | I116: KG | J116: 21810
A117: 111 | B117: FAN | E117: Ceiling Raw | F117: 200100135 | G117: 3101010135 | H117: Ball Bearing 6202 -(CnU) | I117: Pcs | J117: 43200 | K117: 9916
A118: 112 | B118: FAN | E118: Ceiling Raw | F118: 200100136 | G118: 3101010136 | H118: Ball Bearing 6203 (CnU) | I118: Pcs | J118: 44100 | K118: 9797
A119: 113 | B119: FAN | E119: Ceiling Raw | F119: 200100137 | G119: 3101010137 | H119: MEP Cable Tie -2.5 x100mm | I119: Pcs | J119: 0 | K119: 96409
A120: 114 | B120: FAN | E120: Ceiling Raw | F120: 200100138 | G120: 3101010138 | H120: MEP Capacitor 2.5 µF (450VAC) | I120: Pcs | J120: 231858 | K120: 58028
A121: 115 | B121: FAN | E121: Ceiling Raw | F121: 200100139 | G121: 3101010139 | H121: MEP Capacitor 3.5 µF (450VAC) | I121: Pcs | J121: 77752 | K121: 176
A122: 116 | B122: FAN | E122: Ceiling Raw | F122: 200100140 | G122: 3101010140 | H122: Ball Bearing 6202 (KBK) | I122: Pcs | J122: 0 | K122: 0
A123: 117 | B123: FAN | E123: Ceiling Raw | F123: 200100141 | G123: 3101010141 | H123: Ball Bearing 6203 (KBK) | I123: Pcs | J123: 0 | K123: 0
A124: 118 | B124: FAN | E124: Exhaust Raw | F124: 200200001 | G124: 3102010001 | H124: Exhaust Fan Base (8``) | I124: Pcs | J124: 0 | K124: 2
A125: 119 | B125: FAN | E125: Exhaust Raw | F125: 200200002 | G125: 3102010002 | H125: Exhaust Fan Cover (8``) | I125: Pcs | J125: 1131 | K125: 506
A126: 120 | B126: FAN | E126: Exhaust Raw | F126: 200200003 | G126: 3102010003 | H126: Exhaust Fan Shutter (8``) | I126: Pcs | J126: 336 | K126: 3213
A127: 121 | B127: FAN | E127: Exhaust Raw | F127: 200200004 | G127: 3102010004 | H127: Exhaust Fan Blade (8``) | I127: Pcs | J127: 2690 | K127: 985
A128: 122 | B128: FAN | E128: Exhaust Raw | F128: 200200005 | G128: 3102010005 | H128: Exhaust Fan Side Stand (8``) | I128: Pcs | J128: 2595 | K128: 1528
... A309: 303 | B309: FAN | E309: Exhaust Raw | F309: 200200043 | G309: 3202010017 | H309: Exhaust Fan Blade (10``) | I309: Pcs | J309: 3463 | K309: 816
A310: 304 | B310: FAN | E310: Mechanical Parts | F310: 400200057 | G310: 60058 | H310: 12 | I310: Pcs | J310: 10
A311: 305 | B311: FAN | E311: Production Consumables - FAN | F311: 700100001 | G311: 700000001 | H311: Solvent - Drucker | I311: Ltr | J311: 42 | K311: 8
A312: 306 | B312: FAN | E312: Production Consumables - FAN | F312: 700100002 | G312: 700000002 | H312: Printing INK Black | I312: Pcs | J312: 2 | K312: 0
A313: 307 | B313: FAN | E313: Production Consumables - FAN | F313: 700100003 | G313: 700000003 | H313: Hands Gloves - Cotton | I313: Pcs | J313: 2046 | K313: 2480
A314: 308 | B314: FAN | E314: Production Consumables - FAN | F314: 700100004 | G314: 700000004 | H314: Hands Gloves - Rubber | I314: Pcs | J314: 0 | K314: 0
A315: 309 | B315: FAN | E315: Production Consumables - FAN | F315: 700100005 | G315: 700000005 | H315: Bengin | I315: Ltr | J315: 0 | K315: 0
A316: 310 | B316: FAN | E316: Production Consumables - FAN | F316: 700100006 | G316: 700000006 | H316: Reduccer | I316: Ltr | J316: 3 | K316: 0
A317: 311 | B317: FAN | E317: Production Consumables - FAN | F317: 700100007 | G317: 700000007 | H317: Wash (3500) | I317: Ltr | J317: 3 | K317: 0
A318: 312 | B318: FAN | E318: Production Consumables - FAN | F318: 700100008 | G318: 700000008 | H318: Makeup (8535) | I318: Ltr | J318: 9 | K318: 0
A319: 313 | B319: FAN | E319: Production Consumables - FAN | F319: 700100009 | G319: 700000009 | H319: Printing Ink Black(8530) | I319: Ltr | J319: 0 | K319: 0
A320: 314 | B320: FAN | E320: Production Consumables - FAN | F320: 700100010 | G320: 700000010 | H320: Sanding Paper 80 No | I320: Pcs | J320: 3400 | K320: 0
A321: 315 | B321: FAN | E321: Production Consumables - FAN | F321: 700100011 | G321: 700000011 | H321: Sanding Paper 120 No | I321: Pcs | J321: 1380 | K321: 0
A322: 316 | B322: FAN | E322: Production Consumables - FAN | F322: 700100012 | G322: 700000012 | H322: Sanding Pad 5`` | I322: Pcs | J322: 20 | K322: 0
... A345: 339 | B345: FAN | E345: Production Consumables - FAN | F345: 700100036 | G345: 700100037 | H345: GI Insulation wire | I345: Mtr | J345: 0 | K345: 0
A346: 340 | B346: FAN | E346: Production Consumables - FAN | F346: 700100037 | G346: 700100038 | H346: Replace Card-Fan | I346: Pcs | J346: 0
A347: 341 | B347: FAN | E347: Production Consumables - FAN | F347: 700100038 | G347: 700100039 | H347: Carton Tape Transparent- (W=57mm,L=200m, Non Print) | I347: Mtr | J347: 5400 | K347: 3600
A348: 342 | B348: FAN | E348: Exhaust Raw | F348: 200200010 | G348: Erro-2 | H348: Not Use-2 | I348: Pcs | J348: 0 | K348: 0
A349: 343 | B349: FAN | E349: Production Consumables - FAN | F349: 700100016 | G349: Error-1 | H349: NOT Use | I349: Pcs | J349: 0 | K349: 0
A350: 344 | B350: FAN | E350: FAN SFG | F350: 1300100005 | G350: SFG1010005 | H350: Painting Top Cover-2401 (184mm)- Ivory | I350: Pcs | J350: 0 | K350: 3523
A351: 345 | B351: FAN | E351: FAN SFG | F351: 1300100006 | G351: SFG1010006 | H351: Painting Top Cover-3601 (184mm) - Ivory | I351: Pcs | J351: 0 | K351: 7616
A352: 346 | B352: FAN | E352: FAN SFG | F352: 1300100007 | G352: SFG1010007 | H352: Painting Top Cover-4801 (220mm) - Ivory | I352: Pcs | J352: 0 | K352: 2687
A353: 347 | B353: FAN | E353: FAN SFG | F353: 1300100008 | G353: SFG1010008 | H353: Painting Top Cover-5601 (232mm) - Ivory | I353: Pcs | J353: 0 | K353: 3405
A354: 348 | B354: FAN | E354: FAN SFG | F354: 1300100009 | G354: SFG1010009 | H354: Painting Top Cover-5602 (217mm) - Ivory | I354: Pcs | J354: 0 | K354: 3920
A355: 349 | B355: FAN | E355: FAN SFG | F355: 1300100014 | G355: SFG1010014 | H355: Painting Bottom Cover-2401 (184mm) - Ivory | I355: Pcs | J355: 0 | K355: 4296
A356: 350 | B356: FAN | E356: FAN SFG | F356: 1300100015 | G356: SFG1010015 | H356: Painting Bottom Cover-3601 (184mm) - Ivory | I356: Pcs | J356: 0 | K356: 7340
A357: 351 | B357: FAN | E357: FAN SFG | F357: 1300100016 | G357: SFG1010016 | H357: Painting Bottom Cover-4801 (220mm) - Ivory | I357: Pcs | J357: 0 | K357: 2641
A358: 352 | B358: FAN | E358: FAN SFG | F358: 1300100017 | G358: SFG1010017 | H358: Painting Bottom Cover-5601 (232mm) - Ivory | I358: Pcs | J358: 0 | K358: 8064
A359: 353 | B359: FAN | E359: FAN SFG | F359: 1300100018 | G359: SFG1010018 | H359: Painting Bottom Cover-5602 (217mm) - Ivory | I359: Pcs | J359: 0 | K359: 4091
... A404: 398 | B404: FAN | E404: FAN SFG | F404: 1300100139 | G404: SFG1010142 | H404: Completed Clamp with Accessories - 5607 | I404: Set | J404: 0 | K404: 1
A405: 399 | B405: FAN | D405: CEILING FAN | E405: Finished Goods | F405: 100103562 | G405: CF5601/CF5601IV | H405: 56 Inch Premium Ceiling Fan - Ivory | I405: Pcs | J405: 14 | K405: 1
A406: 400 | B406: FAN | D406: CEILING FAN | E406: Finished Goods | F406: 100103563 | G406: CF5602/CF5602IV | H406: 56 Inch Speed King Ceiling Fan - Ivory | I406: Pcs | J406: 34 | K406: 0
A407: 401 | B407: FAN | D407: CEILING FAN | E407: Finished Goods | F407: 100103564 | G407: CF5603/CF5603IV | H407: 56 Inch Premium Gold Ceiling Fan - Ivory | I407: Pcs | J407: 25 | K407: 8
A408: 402 | B408: FAN | D408: CEILING FAN | E408: Finished Goods | F408: 100104717 | G408: CF5607/CF5607IV | H408: 56 Inch Crown Ceiling Fan - Ivory | I408: Pcs | J408: 1 | K408: 0
A409: 403 | B409: FAN | D409: CEILING FAN | E409: Finished Goods | F409: 100104722 | G409: CR5601IV | H409: 56 Inch Premium Ceiling Fan- Ivory (Without Regulator) | I409: Pcs | J409: 65 | K409: 0
A410: 404 | B410: FAN | D410: CEILING FAN | E410: Finished Goods | F410: 100103570 | G410: CF4801/CF4801IV | H410: 48 Inch Popular Ceiling Fan - Ivory | I410: Pcs | J410: 22 | K410: 0
A411: 405 | B411: FAN | D411: CEILING FAN | E411: Finished Goods | F411: 100103571 | G411: CF3601/CF3601IV | H411: 36 Inch Hero Ceiling Fan - Ivory | I411: Pcs | J411: 39 | K411: 0
A412: 406 | B412: FAN | D412: CEILING FAN | E412: Finished Goods | F412: 100103572 | G412: CF2401/CF2401IV | H412: 24 Inch Super Ceiling Fan - Ivory | I412: Pcs | J412: 123 | K412: 0
A413: 407 | B413: FAN | D413: EXHAUST FAN | E413: Finished Goods | F413: 100103576 | G413: EF0801OW/EF0801OW | H413: 08 Inch Fresh Air Exhaust Fan Off White | I413: Pcs | J413: 87 | K413: 0
A414: 408 | B414: FAN | D414: EXHAUST FAN | E414: Finished Goods | F414: 100103575 | G414: EF1001OW/EF1001OW | H414: 10 Inch Fresh Air Exhaust Fan Off White | I414: Pcs | J414: 60 | K414: 118
A415: 409 | B415: FAN | D415: TABLE FAN | E415: Finished Goods | F415: 100103577 | G415: MRTF1201 | H415: 12 Inch Swasti Rechargeable Table Fan | I415: Pcs | J415: 4 | K415: 0
A416: 410 | B416: FAN | D416: TABLE FAN | E416: Finished Goods | F416: 100106794 | G416: MRTF1601 | H416: 16 Inch Swasti Rechargeable Table Fan | I416: Pcs | J416: 0 | K416: 0
A417: 411 | B417: FAN | D417: TABLE FAN | E417: Finished Goods | F417: 100103581 | G417: TF16316/GTF00100 | H417: 16 Inch Table Fan AC Type-01 | I417: Pcs | J417: 0
A418: 412 | B418: FAN | D418: TABLE FAN | E418: Finished Goods | F418: 100103582 | G418: TF16320/GTF00200 | H418: 16 Inch Table Fan AC Type-02 | I418: Pcs | J418: 0
A419: 413 | B419: FAN | D419: FAN ACCESSORIES | E419: Finished Goods | F419: 100103599 | G419: CFB3601/FB3601IV | H419: 36 Inch Hero Celling Fan Blade - Ivory | I419: PKT | J419: 0 | K419: 0
A420: 414 | B420: FAN | D420: FAN ACCESSORIES | E420: Finished Goods | F420: 100103597 | G420: CFB4801/FB4801IV | H420: 48 Inch Popular Celling Fan Blade- Ivory | I420: PKT | J420: 1 | K420: 7
A421: 415 | B421: FAN | D421: FAN ACCESSORIES | E421: Finished Goods | F421: 100103587 | G421: CFB5601/FB5601IV | H421: 56 Inch Premium Ceiling Fan Blade - Ivory | I421: PKT | J421: 9 | K421: 13
...

Sheet ERP Entry FG
A1: S/L | B1: Company | C1: Category | D1: ERP CODE | E1: Code | F1: Item Name | G1: Unit | H1: Opening | I1: Opening Adjust | J1: Store Receive | K1: Section Receive | L1: Production Receive | M1: Damage Receive | N1: Others Receive | O1: Total Receive | P1: Consumption | Q1: WIP Issue | R1: Opening Adjust | S1: Issue To Reapir | T1: Issue To Damage | U1: In Transit | V1: Total Issue | W1: Closing | X1: Bin Closing | Y1: Diff | Z1: Remarks
A2: 1 | B2: FAN | C2: Finished Goods | D2: 100103576 | E2: EF0801OW/EF0801OW | F2: 08 Inch Fresh Air Exhaust Fan Off White | G2: Pcs | H2: 22 | J2: 0 | K2: 2690 | L2: 2690 | N2: 0 | O2: 5402 | Q2: 5402 | V2: 5402 | W2: 0 | X2: 0 | Y2: 0
A3: 2 | B3: FAN | C3: Finished Goods | D3: 100103575 | E3: EF1001OW/EF1001OW | F3: 10 Inch Fresh Air Exhaust Fan Off White | G3: Pcs | H3: 0 | J3: 0 | K3: 1554 | L3: 1554 | N3: 0 | O3: 3108 | Q3: 2990 | V3: 2990 | W3: 118 | X3: 118 | Y3: 0
A4: 3 | B4: FAN | C4: Finished Goods | D4: 100103577 | E4: MRTF1201 | F4: 12 Inch Swasti Rechargeable Table Fan | G4: Pcs | H4: 264 | J4: 0 | K4: 30 | L4: 30 | N4: 0 | O4: 324 | Q4: 324 | V4: 324 | W4: 0 | X4: 0 | Y4: 0
A5: 4 | B5: FAN | C5: Finished Goods | D5: 100103572 | E5: CF2401/CF2401IV | F5: 24 Inch Super Ceiling Fan - Ivory | G5: Pcs | H5: 0 | J5: 0 | K5: 1091 | L5: 1091 | N5: 0 | O5: 2182 | Q5: 2182 | V5: 2182 | W5: 0 | X5: 0 | Y5: 0
A6: 5 | B6: FAN | C6: Finished Goods | D6: 100103601 | E6: CFB2401/FB2401IV | F6: 24 Inch Super Ceiling Fan Blade - Ivory | G6: PKT | H6: 6 | J6: 0 | O6: 6 | V6: 0 | W6: 6 | X6: 6 | Y6: 0
A7: 6 | B7: FAN | C7: Finished Goods | D7: 100103571 | E7: CF3601/CF3601IV | F7: 36 Inch Hero Ceiling Fan - Ivory | G7: Pcs | H7: 13 | J7: 0 | K7: 8000 | L7: 8000 | N7: 0 | O7: 16013 | Q7: 14320 | U7: 1693 | V7: 16013 | W7: 0 | X7: 0 | Y7: 0
A8: 7 | B8: FAN | C8: Finished Goods | D8: 100104725 | E8: CR3601IV | F8: 36 Inch Hero Ceiling Fan- Ivory (Without Regulator) | G8: Pcs | H8: 15 | J8: 0 | O8: 15 | V8: 0 | W8: 15 | X8: 15 | Y8: 0
A9: 8 | B9: FAN | C9: Finished Goods | D9: 100103599 | E9: CFB3601/FB3601IV | F9: 36 Inch Hero Celling Fan Blade - Ivory | G9: PKT | H9: 9 | J9: 0 | K9: 1 | L9: 1 | N9: 0 | O9: 11 | Q9: 11 | V9: 11 | W9: 0 | X9: 0 | Y9: 0
A10: 9 | B10: FAN | C10: Finished Goods | D10: 100103570 | E10: CF4801/CF4801IV | F10: 48 Inch Popular Ceiling Fan - Ivory | G10: Pcs | H10: 0 | J10: 0 | K10: 1100 | L10: 1100 | N10: 0 | O10: 2200 | Q10: 2200 | V10: 2200 | W10: 0 | X10: 0 | Y10: 0
A11: 10 | B11: FAN | C11: Finished Goods | D11: 100103597 | E11: CFB4801/FB4801IV | F11: 48 Inch Popular Celling Fan Blade- Ivory | G11: PKT | H11: 7 | J11: 0 | O11: 7 | V11: 0 | W11: 7 | X11: 7 | Y11: 0
A12: 11 | B12: FAN | C12: Finished Goods | D12: 100104717 | E12: CF5607/CF5607IV | F12: 56 Inch Crown Ceiling Fan - Ivory | G12: Pcs | H12: 1 | J12: 0 | K12: 335 | L12: 335 | N12: 0 | O12: 671 | Q12: 671 | V12: 671 | W12: 0 | X12: 0 | Y12: 0
A13: 12 | B13: FAN | C13: Finished Goods | D13: 100103562 | E13: CF5601/CF5601IV | F13: 56 Inch Premium Ceiling Fan - Ivory | G13: Pcs | H13: 1 | J13: 1 | K13: 30786 | L13: 30786 | N13: 0 | O13: 61574 | Q13: 61573 | V13: 61573 | W13: 1 | X13: 1 | Y13: 0
A14: 13 | B14: FAN | C14: Finished Goods | D14: 100104179 | E14: CF5601WH/CF5601WH | F14: 56 Inch Premium Ceiling Fan - White | G14: Pcs | H14: 23 | J14: 0 | K14: 49 | L14: 49 | N14: 0 | O14: 121 | Q14: 49 | U14: 49 | V14: 98 | W14: 23 | X14: 23 | Y14: 0
A15: 14 | B15: FAN | C15: Finished Goods | D15: 100103587 | E15: CFB5601/FB5601IV | F15: 56 Inch Premium Ceiling Fan Blade - Ivory | G15: PKT | H15: 33 | J15: 0 | O15: 33 | Q15: 20 | V15: 20 | W15: 13 | X15: 13 | Y15: 0
A16: 15 | B16: FAN | C16: Finished Goods | D16: 100104745 | E16: CG5601/CG5601IV | F16: 56 Inch Premium Ceiling Fan With Gang Regulator - Ivory | G16: Pcs | H16: 0 | J16: 0 | K16: 48 | L16: 48 | N16: 0 | O16: 96 | Q16: 96 | V16: 96 | W16: 0 | X16: 0 | Y16: 0
A17: 16 | B17: FAN | C17: Finished Goods | D17: 100104722 | E17: CR5601IV | F17: 56 Inch Premium Ceiling Fan- Ivory (Without Regulator) | G17: Pcs | H17: 93 | J17: 0 | K17: 2015 | L17: 2015 | N17: 0 | O17: 4123 | Q17: 4123 | V17: 4123 | W17: 0 | X17: 0 | Y17: 0
A18: 17 | B18: FAN | C18: Finished Goods | D18: 100104726 | E18: CR5601WH | F18: 56 Inch Premium Ceiling Fan- White (Without Regulator) | G18: Pcs | H18: 0 | J18: 0 | K18: 56 | L18: 56 | N18: 0 | O18: 112 | Q18: 112 | V18: 112 | W18: 0 | X18: 0 | Y18: 0
A19: 18 | B19: FAN | C19: Finished Goods | D19: 100103564 | E19: CF5603/CF5603IV | F19: 56 Inch Premium Gold Ceiling Fan - Ivory | G19: Pcs | H19: 8 | J19: 0 | O19: 8 | V19: 0 | W19: 8 | X19: 8 | Y19: 0
A20: 19 | B20: FAN | C20: Finished Goods | D20: 100103567 | E20: CF5606/CF5606IV | F20: 56 Inch Premium Plus Ceiling Fan - Ivory | G20: Pcs | H20: 0 | J20: 0 | K20: 60 | L20: 60 | N20: 0 | O20: 120 | Q20: 112 | V20: 112 | W20: 8 | X20: 8 | Y20: 0
A21: 20 | B21: FAN | C21: Finished Goods | D21: 100105514 | E21: CG5606/CG5606IV | F21: 56 Inch Premium Plus Ceiling Fan With Gang Regulator - Ivory | G21: Pcs | H21: 4 | J21: 0 | O21: 4 | V21: 0 | W21: 4 | X21: 4 | Y21: 0
A22: 21 | B22: FAN | C22: Finished Goods | D22: 100105513 | E22: CR5606IV | F22: 56 Inch Premium Plus Ceiling Fan- Ivory (Without Regulator) | G22: Pcs | H22: 2 | J22: 0 | O22: 2 | V22: 0 | W22: 2 | X22: 2 | Y22: 0
A23: 22 | B23: FAN | C23: Finished Goods | D23: 100103563 | E23: CF5602/CF5602IV | F23: 56 Inch Speed King Ceiling Fan - Ivory | G23: Pcs | H23: 296 | J23: 0 | O23: 296 | Q23: 296 | V23: 296 | W23: 0 | X23: 0 | Y23: 0
A24: 23 | B24: FAN | C24: Finished Goods | D24: 100107316 | E24: EF1001AF | F24: Aero Flow 10`` Exhaust Fan | G24: Pcs | H24: 301 | J24: 0 | K24: 3078 | L24: 3078 | N24: 0 | O24: 6457 | Q24: 6456 | V24: 6456 | W24: 1 | X24: 1 | Y24: 0
A25: 24 | B25: FAN | C25: Finished Goods | D25: 100107315 | E25: EF0801AF | F25: Aero Flow 8`` Exhaust Fan | G25: Pcs | H25: 20 | J25: 0 | K25: 2626 | L25: 2626 | N25: 0 | O25: 5272 | Q25: 5272 | V25: 5272 | W25: 0 | X25: 0 | Y25: 0
A26: 25 | B26: FAN | C26: Finished Goods | D26: 100107035 | E26: CFCP001 | F26: Ceiling Fan Capacitor 2.5 uf | G26: Pcs | H26: 0 | J26: 0 | K26: 70128 | L26: 70128 | N26: 0 | O26: 140256 | Q26: 138576 | V26: 138576 | W26: 1680 | X26: 1680 | Y26: 0
A27: 26 | B27: FAN | C27: Finished Goods | D27: 100107036 | E27: CFCP002 | F27: Ceiling Fan Capacitor 3.5 uf | G27: Pcs | H27: 0 | J27: 0 | K27: 79872 | L27: 79872 | N27: 0 | O27: 159744 | Q27: 159744 | V27: 159744 | W27: 0 | X27: 0 | Y27: 0
A28: 27 | B28: FAN | C28: Finished Goods | D28: 1300100099 | E28: CFDP01/FDP001IV | F28: Celling Fan Down Pipe 1 Inch -Ivory | G28: Inch | H28: 2831 | J28: 0 | K28: 22000 | L28: 22000 | N28: 0 | O28: 46831 | Q28: 43332 | U28: 686 | V28: 44018 | W28: 2813 | X28: 2813 | Y28: 0
A29: 28 | B29: FAN | C29: Finished Goods | D29: 100103662 | E29: CFDP14/FDP014IV | F29: Celling Fan Down Pipe 14 Inch - Ivory | G29: Pcs | H29: 2 | J29: 0 | O29: 2 | V29: 0 | W29: 2 | X29: 2 | Y29: 0
A30: 29 | B30: FAN | C30: Finished Goods | D30: 100103647 | E30: CFDP60/FDP060IV | F30: Celling Fan Down Pipe 60 Inch Ivory | G30: Pcs | H30: 1 | J30: 0 | O30: 1 | V30: 0 | W30: 1 | X30: 1 | Y30: 0
A31: 30 | B31: FAN | C31: Finished Goods | D31: 100103726 | E31: 60477/FOA00500 | F31: MS Iron | G31: KG | H31: 254 | J31: 0 | O31: 254 | V31: 0 | W31: 254 | X31: 254 | Y31: 0
F32: Total | H32: 4206 | I32: 0 | J32: 1 | K32: 225519 | L32: 225519 | M32: 0 | N32: 0 | O32: 455245 | P32: 0 | Q32: 447861 | R32: 0 | S32: 0 | T32: 0 | U32: 2428 | V32: 450289 | W32: 4956 | X32: 4956 | Y32: 0

Sheet BSIC Entry
A1: MEP FAN LIMITED. | AA1: =IFERROR( IF(ISNUMBER(C1),C1,DATE(VALUE(RIGHT(C1,4)),VALUE(MID(SUBSTITUTE(C1,"/","-"),FIND("-",SUBSTITUTE(C1,"/","-"))+1,FIND("-",SUBSTITUTE(C1,"/","-"),FIND("-",SUBSTITUTE(C1,"/","-"))+1)-FIND("-",SUBSTITUTE(C1,"/","-"))-1)),VALUE(LEFT(SUBSTITUTE(C1,"/","-"),FIND("-",SUBSTITUTE(C1,"/","-"))-1)))), DATE(1995,1,1) ) -> 34700
AA2: =IFERROR( IF(ISNUMBER(C2),C2,DATE(VALUE(RIGHT(C2,4)),VALUE(MID(SUBSTITUTE(C2,"/","-"),FIND("-",SUBSTITUTE(C2,"/","-"))+1,FIND("-",SUBSTITUTE(C2,"/","-"),FIND("-",SUBSTITUTE(C2,"/","-"))+1)-FIND("-",SUBSTITUTE(C2,"/","-"))-1)),VALUE(LEFT(SUBSTITUTE(C2,"/","-"),FIND("-",SUBSTITUTE(C2,"/","-"))-1)))), DATE(1995,1,1) ) -> 34700
A3: Inter Sales Requisition Details Report | AA3: =IFERROR( IF(ISNUMBER(C3),C3,DATE(VALUE(RIGHT(C3,4)),VALUE(MID(SUBSTITUTE(C3,"/","-"),FIND("-",SUBSTITUTE(C3,"/","-"))+1,FIND("-",SUBSTITUTE(C3,"/","-"),FIND("-",SUBSTITUTE(C3,"/","-"))+1)-FIND("-",SUBSTITUTE(C3,"/","-"))-1)),VALUE(LEFT(SUBSTITUTE(C3,"/","-"),FIND("-",SUBSTITUTE(C3,"/","-"))-1)))), DATE(1995,1,1) ) -> 34700
AA4: =IFERROR( IF(ISNUMBER(C4),C4,DATE(VALUE(RIGHT(C4,4)),VALUE(MID(SUBSTITUTE(C4,"/","-"),FIND("-",SUBSTITUTE(C4,"/","-"))+1,FIND("-",SUBSTITUTE(C4,"/","-"),FIND("-",SUBSTITUTE(C4,"/","-"))+1)-FIND("-",SUBSTITUTE(C4,"/","-"))-1)),VALUE(LEFT(SUBSTITUTE(C4,"/","-"),FIND("-",SUBSTITUTE(C4,"/","-"))-1)))), DATE(1995,1,1) ) -> 34700
A5: 20-06-2026 To 29-08-2026 | AA5: =IFERROR( IF(ISNUMBER(C5),C5,DATE(VALUE(RIGHT(C5,4)),VALUE(MID(SUBSTITUTE(C5,"/","-"),FIND("-",SUBSTITUTE(C5,"/","-"))+1,FIND("-",SUBSTITUTE(C5,"/","-"),FIND("-",SUBSTITUTE(C5,"/","-"))+1)-FIND("-",SUBSTITUTE(C5,"/","-"))-1)),VALUE(LEFT(SUBSTITUTE(C5,"/","-"),FIND("-",SUBSTITUTE(C5,"/","-"))-1)))), DATE(1995,1,1) ) -> 34700
AA6: =IFERROR( IF(ISNUMBER(C6),C6,DATE(VALUE(RIGHT(C6,4)),VALUE(MID(SUBSTITUTE(C6,"/","-"),FIND("-",SUBSTITUTE(C6,"/","-"))+1,FIND("-",SUBSTITUTE(C6,"/","-"),FIND("-",SUBSTITUTE(C6,"/","-"))+1)-FIND("-",SUBSTITUTE(C6,"/","-"))-1)),VALUE(LEFT(SUBSTITUTE(C6,"/","-"),FIND("-",SUBSTITUTE(C6,"/","-"))-1)))), DATE(1995,1,1) ) -> 34700
A7: Reporting Time: 02:43 PM 29-08-2026 | AA7: =IFERROR( IF(ISNUMBER(C7),C7,DATE(VALUE(RIGHT(C7,4)),VALUE(MID(SUBSTITUTE(C7,"/","-"),FIND("-",SUBSTITUTE(C7,"/","-"))+1,FIND("-",SUBSTITUTE(C7,"/","-"),FIND("-",SUBSTITUTE(C7,"/","-"))+1)-FIND("-",SUBSTITUTE(C7,"/","-"))-1)),VALUE(LEFT(SUBSTITUTE(C7,"/","-"),FIND("-",SUBSTITUTE(C7,"/","-"))-1)))), DATE(1995,1,1) ) -> 34700
A8: S/L | B8: Req No | C8: Req Date | D8: Issue NO | E8: Company (Purchase) | F8: Company (Sales) | G8: Item Code | H8: Item Name | I8: Unit Name | J8: Req Qty | K8: Req Value | L8: Issue Qty | M8: Issue Value | N8: Pending Qty | O8: Pending Value | P8: Status | Q8: Entry By | R8: Entry At | AA8: =IFERROR( IF(ISNUMBER(C8),C8,DATE(VALUE(RIGHT(C8,4)),VALUE(MID(SUBSTITUTE(C8,"/","-"),FIND("-",SUBSTITUTE(C8,"/","-"))+1,FIND("-",SUBSTITUTE(C8,"/","-"),FIND("-",SUBSTITUTE(C8,"/","-"))+1)-FIND("-",SUBSTITUTE(C8,"/","-"))-1)),VALUE(LEFT(SUBSTITUTE(C8,"/","-"),FIND("-",SUBSTITUTE(C8,"/","-"))-1)))), DATE(1995,1,1) ) -> 34700
A9: 1 | B9: 2108 | C9: 20-06-2026 | E9: FAN | F9: Printing and Packaging | G9: 3202010001 | H9: HDPE Poly (L=22``, W=18``, T=0.025mm) | I9: KG | J9: 50 | K9: 14494.54 | M9: 0 | N9: 50 | O9: 14494.54 | P9: PENDING | Q9: 144 | R9: 46193.793 | AA9: =IFERROR( IF(ISNUMBER(C9),C9,DATE(VALUE(RIGHT(C9,4)),VALUE(MID(SUBSTITUTE(C9,"/","-"),FIND("-",SUBSTITUTE(C9,"/","-"))+1,FIND("-",SUBSTITUTE(C9,"/","-"),FIND("-",SUBSTITUTE(C9,"/","-"))+1)-FIND("-",SUBSTITUTE(C9,"/","-"))-1)),VALUE(LEFT(SUBSTITUTE(C9,"/","-"),FIND("-",SUBSTITUTE(C9,"/","-"))-1)))), DATE(1995,1,1) ) -> 46193
A10: 2 | B10: 2111 | C10: 21-06-2026 | D10: 1517415243 | E10: FAN | F10: Printing and Packaging | G10: 3202010001 | H10: HDPE Poly (L=22``, W=18``, T=0.025mm) | I10: KG | J10: 100 | K10: 28989.08 | L10: 42 | M10: 12175.41 | N10: 58 | O10: 16813.67 | P10: PENDING | Q10: 144 | R10: 46196.358 | AA10: =IFERROR( IF(ISNUMBER(C10),C10,DATE(VALUE(RIGHT(C10,4)),VALUE(MID(SUBSTITUTE(C10,"/","-"),FIND("-",SUBSTITUTE(C10,"/","-"))+1,FIND("-",SUBSTITUTE(C10,"/","-"),FIND("-",SUBSTITUTE(C10,"/","-"))+1)-FIND("-",SUBSTITUTE(C10,"/","-"))-1)),VALUE(LEFT(SUBSTITUTE(C10,"/","-"),FIND("-",SUBSTITUTE(C10,"/","-"))-1)))), DATE(1995,1,1) ) -> 46194
A11: 3 | B11: 2219 | C11: 26-07-2026 | D11: 1584715871 | E11: FAN | F11: Printing and Packaging | G11: 3202010001 | H11: HDPE Poly (L=22``, W=18``, T=0.025mm) | I11: KG | J11: 100 | K11: 28989.08 | L11: 100 | M11: 28989.08 | N11: 0 | O11: 0 | P11: PENDING | Q11: 144 | R11: 46229.685 | AA11: =IFERROR( IF(ISNUMBER(C11),C11,DATE(VALUE(RIGHT(C11,4)),VALUE(MID(SUBSTITUTE(C11,"/","-"),FIND("-",SUBSTITUTE(C11,"/","-"))+1,FIND("-",SUBSTITUTE(C11,"/","-"),FIND("-",SUBSTITUTE(C11,"/","-"))+1)-FIND("-",SUBSTITUTE(C11,"/","-"))-1)),VALUE(LEFT(SUBSTITUTE(C11,"/","-"),FIND("-",SUBSTITUTE(C11,"/","-"))-1)))), DATE(1995,1,1) ) -> 46229
A12: 4 | B12: 2282 | C12: 20-08-2026 | E12: FAN | F12: Printing and Packaging | G12: 3202010001 | H12: HDPE Poly (L=22``, W=18``, T=0.025mm) | I12: KG | J12: 0 | K12: 0 | M12: 0 | N12: 0 | O12: 0 | P12: CHECKED | Q12: 144 | R12: 46260.682 | AA12: =IFERROR( IF(ISNUMBER(C12),C12,DATE(VALUE(RIGHT(C12,4)),VALUE(MID(SUBSTITUTE(C12,"/","-"),FIND("-",SUBSTITUTE(C12,"/","-"))+1,FIND("-",SUBSTITUTE(C12,"/","-"),FIND("-",SUBSTITUTE(C12,"/","-"))+1)-FIND("-",SUBSTITUTE(C12,"/","-"))-1)),VALUE(LEFT(SUBSTITUTE(C12,"/","-"),FIND("-",SUBSTITUTE(C12,"/","-"))-1)))), DATE(1995,1,1) ) -> 46254
A13: 5 | B13: 2108 | C13: 20-06-2026 | E13: FAN | F13: Printing and Packaging | G13: 3202010002 | H13: 8 Inch Exhasust Fan Body Carton | I13: Pcs | J13: 2300 | K13: 98189.87 | M13: 0 | N13: 2300 | O13: 98189.87 | P13: PENDING | Q13: 144 | R13: 46193.793 | AA13: =IFERROR( IF(ISNUMBER(C13),C13,DATE(VALUE(RIGHT(C13,4)),VALUE(MID(SUBSTITUTE(C13,"/","-"),FIND("-",SUBSTITUTE(C13,"/","-"))+1,FIND("-",SUBSTITUTE(C13,"/","-"),FIND("-",SUBSTITUTE(C13,"/","-"))+1)-FIND("-",SUBSTITUTE(C13,"/","-"))-1)),VALUE(LEFT(SUBSTITUTE(C13,"/","-"),FIND("-",SUBSTITUTE(C13,"/","-"))-1)))), DATE(1995,1,1) ) -> 46193
A14: 6 | B14: 2111 | C14: 21-06-2026 | D14: 14747 | E14: FAN | F14: Printing and Packaging | G14: 3202010002 | H14: 8 Inch Exhasust Fan Body Carton | I14: Pcs | J14: 6100 | K14: 260416.61 | L14: 165 | M14: 7044.06 | N14: 5935 | O14: 253372.56 | P14: PENDING | Q14: 144 | R14: 46196.358 | AA14: =IFERROR( IF(ISNUMBER(C14),C14,DATE(VALUE(RIGHT(C14,4)),VALUE(MID(SUBSTITUTE(C14,"/","-"),FIND("-",SUBSTITUTE(C14,"/","-"))+1,FIND("-",SUBSTITUTE(C14,"/","-"),FIND("-",SUBSTITUTE(C14,"/","-"))+1)-FIND("-",SUBSTITUTE(C14,"/","-"))-1)),VALUE(LEFT(SUBSTITUTE(C14,"/","-"),FIND("-",SUBSTITUTE(C14,"/","-"))-1)))), DATE(1995,1,1) ) -> 46194
A15: 7 | B15: 2230 | C15: 46030 | D15: 1.5798158e+24 | E15: FAN | F15: Printing and Packaging | G15: 3202010002 | H15: 8 Inch Exhasust Fan Body Carton | I15: Pcs | J15: 3150 | K15: 134477.43 | L15: 2918 | M15: 124573.06 | N15: 232 | O15: 9904.37 | P15: PENDING | Q15: 144 | R15: 46236.692 | AA15: =IFERROR( IF(ISNUMBER(C15),C15,DATE(VALUE(RIGHT(C15,4)),VALUE(MID(SUBSTITUTE(C15,"/","-"),FIND("-",SUBSTITUTE(C15,"/","-"))+1,FIND("-",SUBSTITUTE(C15,"/","-"),FIND("-",SUBSTITUTE(C15,"/","-"))+1)-FIND("-",SUBSTITUTE(C15,"/","-"))-1)),VALUE(LEFT(SUBSTITUTE(C15,"/","-"),FIND("-",SUBSTITUTE(C15,"/","-"))-1)))), DATE(1995,1,1) ) -> 46030
A16: 8 | B16: 2108 | C16: 20-06-2026 | D16: 1509415175 | E16: FAN | F16: Printing and Packaging | G16: 3202010008 | H16: HDPE Poly (L=24``, W=20``, T=0.025mm) | I16: KG | J16: 55 | K16: 15875.2 | L16: 40.5 | M16: 11689.92 | N16: 14.5 | O16: 4185.28 | P16: PENDING | Q16: 144 | R16: 46193.793 | AA16: =IFERROR( IF(ISNUMBER(C16),C16,DATE(VALUE(RIGHT(C16,4)),VALUE(MID(SUBSTITUTE(C16,"/","-"),FIND("-",SUBSTITUTE(C16,"/","-"))+1,FIND("-",SUBSTITUTE(C16,"/","-"),FIND("-",SUBSTITUTE(C16,"/","-"))+1)-FIND("-",SUBSTITUTE(C16,"/","-"))-1)),VALUE(LEFT(SUBSTITUTE(C16,"/","-"),FIND("-",SUBSTITUTE(C16,"/","-"))-1)))), DATE(1995,1,1) ) -> 46193
A17: 9 | B17: 2111 | C17: 21-06-2026 | D17: 1.4766149e+59 | E17: FAN | F17: Printing and Packaging | G17: 3202010008 | H17: HDPE Poly (L=24``, W=20``, T=0.025mm) | I17: KG | J17: 275 | K17: 79376.02 | L17: 275 | M17: 79376.02 | N17: 0 | O17: 0 | P17: PENDING | Q17: 144 | R17: 46196.358 | AA17: =IFERROR( IF(ISNUMBER(C17),C17,DATE(VALUE(RIGHT(C17,4)),VALUE(MID(SUBSTITUTE(C17,"/","-"),FIND("-",SUBSTITUTE(C17,"/","-"))+1,FIND("-",SUBSTITUTE(C17,"/","-"),FIND("-",SUBSTITUTE(C17,"/","-"))+1)-FIND("-",SUBSTITUTE(C17,"/","-"))-1)),VALUE(LEFT(SUBSTITUTE(C17,"/","-"),FIND("-",SUBSTITUTE(C17,"/","-"))-1)))), DATE(1995,1,1) ) -> 46194
A18: 10 | B18: 2219 | C18: 26-07-2026 | D18: 1584715655 | E18: FAN | F18: Printing and Packaging | G18: 3202010008 | H18: HDPE Poly (L=24``, W=20``, T=0.025mm) | I18: KG | J18: 200 | K18: 57728.01 | L18: 200 | M18: 57728.01 | N18: 0 | O18: 0 | P18: PENDING | Q18: 144 | R18: 46229.685 | AA18: =IFERROR( IF(ISNUMBER(C18),C18,DATE(VALUE(RIGHT(C18,4)),VALUE(MID(SUBSTITUTE(C18,"/","-"),FIND("-",SUBSTITUTE(C18,"/","-"))+1,FIND("-",SUBSTITUTE(C18,"/","-"),FIND("-",SUBSTITUTE(C18,"/","-"))+1)-FIND("-",SUBSTITUTE(C18,"/","-"))-1)),VALUE(LEFT(SUBSTITUTE(C18,"/","-"),FIND("-",SUBSTITUTE(C18,"/","-"))-1)))), DATE(1995,1,1) ) -> 46229
A19: 11 | B19: 2282 | C19: 20-08-2026 | E19: FAN | F19: Printing and Packaging | G19: 3202010008 | H19: HDPE Poly (L=24``, W=20``, T=0.025mm) | I19: KG | J19: 150 | K19: 43296.01 | M19: 0 | N19: 150 | O19: 43296.01 | P19: CHECKED | Q19: 144 | R19: 46260.682 | AA19: =IFERROR( IF(ISNUMBER(C19),C19,DATE(VALUE(RIGHT(C19,4)),VALUE(MID(SUBSTITUTE(C19,"/","-"),FIND("-",SUBSTITUTE(C19,"/","-"))+1,FIND("-",SUBSTITUTE(C19,"/","-"),FIND("-",SUBSTITUTE(C19,"/","-"))+1)-FIND("-",SUBSTITUTE(C19,"/","-"))-1)),VALUE(LEFT(SUBSTITUTE(C19,"/","-"),FIND("-",SUBSTITUTE(C19,"/","-"))-1)))), DATE(1995,1,1) ) -> 46254
A20: 12 | B20: 2108 | C20: 20-06-2026 | E20: FAN | F20: Printing and Packaging | G20: 3202010009 | H20: 10 Inch Exhasust Fan Body Carton | I20: Pcs | J20: 1500 | K20: 78861.46 | M20: 0 | N20: 1500 | O20: 78861.46 | P20: PENDING | Q20: 144 | R20: 46193.793 | AA20: =IFERROR( IF(ISNUMBER(C20),C20,DATE(VALUE(RIGHT(C20,4)),VALUE(MID(SUBSTITUTE(C20,"/","-"),FIND("-",SUBSTITUTE(C20,"/","-"))+1,FIND("-",SUBSTITUTE(C20,"/","-"),FIND("-",SUBSTITUTE(C20,"/","-"))+1)-FIND("-",SUBSTITUTE(C20,"/","-"))-1)),VALUE(LEFT(SUBSTITUTE(C20,"/","-"),FIND("-",SUBSTITUTE(C20,"/","-"))-1)))), DATE(1995,1,1) ) -> 46193
A21: 13 | B21: 2111 | C21: 21-06-2026 | D21: 14747 | E21: FAN | F21: Printing and Packaging | G21: 3202010009 | H21: 10 Inch Exhasust Fan Body Carton | I21: Pcs | J21: 9200 | K21: 483683.62 | L21: 675 | M21: 35487.66 | N21: 8525 | O21: 448195.96 | P21: PENDING | Q21: 144 | R21: 46196.358 | AA21: =IFERROR( IF(ISNUMBER(C21),C21,DATE(VALUE(RIGHT(C21,4)),VALUE(MID(SUBSTITUTE(C21,"/","-"),FIND("-",SUBSTITUTE(C21,"/","-"))+1,FIND("-",SUBSTITUTE(C21,"/","-"),FIND("-",SUBSTITUTE(C21,"/","-"))+1)-FIND("-",SUBSTITUTE(C21,"/","-"))-1)),VALUE(LEFT(SUBSTITUTE(C21,"/","-"),FIND("-",SUBSTITUTE(C21,"/","-"))-1)))), DATE(1995,1,1) ) -> 46194
A22: 14 | B22: 2230 | C22: 46030 | D22: 1.5886159e+29 | E22: FAN | F22: Printing and Packaging | G22: 3202010009 | H22: 10 Inch Exhasust Fan Body Carton | I22: Pcs | J22: 2650 | K22: 139321.91 | L22: 2575 | M22: 135378.84 | N22: 75 | O22: 3943.07 | P22: PENDING | Q22: 144 | R22: 46236.692 | AA22: =IFERROR( IF(ISNUMBER(C22),C22,DATE(VALUE(RIGHT(C22,4)),VALUE(MID(SUBSTITUTE(C22,"/","-"),FIND("-",SUBSTITUTE(C22,"/","-"))+1,FIND("-",SUBSTITUTE(C22,"/","-"),FIND("-",SUBSTITUTE(C22,"/","-"))+1)-FIND("-",SUBSTITUTE(C22,"/","-"))-1)),VALUE(LEFT(SUBSTITUTE(C22,"/","-"),FIND("-",SUBSTITUTE(C22,"/","-"))-1)))), DATE(1995,1,1) ) -> 46030
A23: 15 | B23: 2108 | C23: 20-06-2026 | E23: FAN | F23: Printing and Packaging | G23: 3202010015 | H23: Guarantee Card (Exhaust Fan) | I23: Pcs | J23: 6200 | K23: 1807.27 | M23: 0 | N23: 6200 | O23: 1807.27 | P23: PENDING | Q23: 144 | R23: 46193.793 | AA23: =IFERROR( IF(ISNUMBER(C23),C23,DATE(VALUE(RIGHT(C23,4)),VALUE(MID(SUBSTITUTE(C23,"/","-"),FIND("-",SUBSTITUTE(C23,"/","-"))+1,FIND("-",SUBSTITUTE(C23,"/","-"),FIND("-",SUBSTITUTE(C23,"/","-"))+1)-FIND("-",SUBSTITUTE(C23,"/","-"))-1)),VALUE(LEFT(SUBSTITUTE(C23,"/","-"),FIND("-",SUBSTITUTE(C23,"/","-"))-1)))), DATE(1995,1,1) ) -> 46193
A24: 16 | B24: 2111 | C24: 21-06-2026 | D24: 14720 | E24: FAN | F24: Printing and Packaging | G24: 3202010015 | H24: Guarantee Card (Exhaust Fan) | I24: Pcs | J24: 15500 | K24: 4518.18 | L24: 1000 | M24: 291.5 | N24: 14500 | O24: 4226.68 | P24: PENDING | Q24: 144 | R24: 46196.358 | AA24: =IFERROR( IF(ISNUMBER(C24),C24,DATE(VALUE(RIGHT(C24,4)),VALUE(MID(SUBSTITUTE(C24,"/","-"),FIND("-",SUBSTITUTE(C24,"/","-"))+1,FIND("-",SUBSTITUTE(C24,"/","-"),FIND("-",SUBSTITUTE(C24,"/","-"))+1)-FIND("-",SUBSTITUTE(C24,"/","-"))-1)),VALUE(LEFT(SUBSTITUTE(C24,"/","-"),FIND("-",SUBSTITUTE(C24,"/","-"))-1)))), DATE(1995,1,1) ) -> 46194
A25: 17 | B25: 2230 | C25: 46030 | D25: 15428 | E25: FAN | F25: Printing and Packaging | G25: 3202010015 | H25: Guarantee Card (Exhaust Fan) | I25: Pcs | J25: 6000 | K25: 1748.97 | L25: 6000 | M25: 1748.97 | N25: 0 | O25: 0 | P25: PENDING | Q25: 144 | R25: 46236.692 | AA25: =IFERROR( IF(ISNUMBER(C25),C25,DATE(VALUE(RIGHT(C25,4)),VALUE(MID(SUBSTITUTE(C25,"/","-"),FIND("-",SUBSTITUTE(C25,"/","-"))+1,FIND("-",SUBSTITUTE(C25,"/","-"),FIND("-",SUBSTITUTE(C25,"/","-"))+1)-FIND("-",SUBSTITUTE(C25,"/","-"))-1)),VALUE(LEFT(SUBSTITUTE(C25,"/","-"),FIND("-",SUBSTITUTE(C25,"/","-"))-1)))), DATE(1995,1,1) ) -> 46030
A26: 18 | B26: 2108 | C26: 20-06-2026 | E26: FAN | F26: Printing and Packaging | G26: 3202010016 | H26: Air Fresher Sticker | I26: Pcs | J26: 6300 | K26: 1150.64 | M26: 0 | N26: 6300 | O26: 1150.64 | P26: PENDING | Q26: 144 | R26: 46193.793 | AA26: =IFERROR( IF(ISNUMBER(C26),C26,DATE(VALUE(RIGHT(C26,4)),VALUE(MID(SUBSTITUTE(C26,"/","-"),FIND("-",SUBSTITUTE(C26,"/","-"))+1,FIND("-",SUBSTITUTE(C26,"/","-"),FIND("-",SUBSTITUTE(C26,"/","-"))+1)-FIND("-",SUBSTITUTE(C26,"/","-"))-1)),VALUE(LEFT(SUBSTITUTE(C26,"/","-"),FIND("-",SUBSTITUTE(C26,"/","-"))-1)))), DATE(1995,1,1) ) -> 46193
A27: 19 | B27: 2111 | C27: 21-06-2026 | D27: 1523214948 | E27: FAN | F27: Printing and Packaging | G27: 3202010016 | H27: Air Fresher Sticker | I27: Pcs | J27: 15500 | K27: 2830.94 | L27: 300 | M27: 54.79 | N27: 15200 | O27: 2776.15 | P27: PENDING | Q27: 144 | R27: 46196.358 | AA27: =IFERROR( IF(ISNUMBER(C27),C27,DATE(VALUE(RIGHT(C27,4)),VALUE(MID(SUBSTITUTE(C27,"/","-"),FIND("-",SUBSTITUTE(C27,"/","-"))+1,FIND("-",SUBSTITUTE(C27,"/","-"),FIND("-",SUBSTITUTE(C27,"/","-"))+1)-FIND("-",SUBSTITUTE(C27,"/","-"))-1)),VALUE(LEFT(SUBSTITUTE(C27,"/","-"),FIND("-",SUBSTITUTE(C27,"/","-"))-1)))), DATE(1995,1,1) ) -> 46194
A28: 20 | B28: 2230 | C28: 46030 | D28: 1542815554 | E28: FAN | F28: Printing and Packaging | G28: 3202010016 | H28: Air Fresher Sticker | I28: Pcs | J28: 6000 | K28: 1095.85 | L28: 6000 | M28: 1095.85 | N28: 0 | O28: 0 | P28: PENDING | Q28: 144 | R28: 46236.692 | AA28: =IFERROR( IF(ISNUMBER(C28),C28,DATE(VALUE(RIGHT(C28,4)),VALUE(MID(SUBSTITUTE(C28,"/","-"),FIND("-",SUBSTITUTE(C28,"/","-"))+1,FIND("-",SUBSTITUTE(C28,"/","-"),FIND("-",SUBSTITUTE(C28,"/","-"))+1)-FIND("-",SUBSTITUTE(C28,"/","-"))-1)),VALUE(LEFT(SUBSTITUTE(C28,"/","-"),FIND("-",SUBSTITUTE(C28,"/","-"))-1)))), DATE(1995,1,1) ) -> 46030
A29: 21 | B29: 2117 | C29: 21-06-2026 | D29: 148521485114471 | E29: FAN | F29: Printing and Packaging | G29: 3201010002 | H29: FAN Shank Paper | I29: Pcs | J29: 136500 | K29: 209358.94 | L29: 136500 | M29: 209358.94 | N29: 0 | O29: 0 | P29: PENDING | Q29: 144 | R29: 46196.36 | AA29: =IFERROR( IF(ISNUMBER(C29),C29,DATE(VALUE(RIGHT(C29,4)),VALUE(MID(SUBSTITUTE(C29,"/","-"),FIND("-",SUBSTITUTE(C29,"/","-"))+1,FIND("-",SUBSTITUTE(C29,"/","-"),FIND("-",SUBSTITUTE(C29,"/","-"))+1)-FIND("-",SUBSTITUTE(C29,"/","-"))-1)),VALUE(LEFT(SUBSTITUTE(C29,"/","-"),FIND("-",SUBSTITUTE(C29,"/","-"))-1)))), DATE(1995,1,1) ) -> 46194
A30: 22 | B30: 2206 | C30: 22-07-2026 | D30: 15333 | E30: FAN | F30: Printing and Packaging | G30: 3201010002 | H30: FAN Shank Paper | I30: Pcs | J30: 136500 | K30: 209358.94 | L30: 136500 | M30: 209358.94 | N30: 0 | O30: 0 | P30: PENDING | Q30: 144 | R30: 46228.398 | AA30: =IFERROR( IF(ISNUMBER(C30),C30,DATE(VALUE(RIGHT(C30,4)),VALUE(MID(SUBSTITUTE(C30,"/","-"),FIND("-",SUBSTITUTE(C30,"/","-"))+1,FIND("-",SUBSTITUTE(C30,"/","-"),FIND("-",SUBSTITUTE(C30,"/","-"))+1)-FIND("-",SUBSTITUTE(C30,"/","-"))-1)),VALUE(LEFT(SUBSTITUTE(C30,"/","-"),FIND("-",SUBSTITUTE(C30,"/","-"))-1)))), DATE(1995,1,1) ) -> 46225
A31: 23 | B31: 2283 | C31: 20-08-2026 | E31: FAN | F31: Printing and Packaging | G31: 3201010002 | H31: FAN Shank Paper | I31: Pcs | J31: 129780 | K31: 199052.04 | M31: 0 | N31: 129780 | O31: 199052.04 | P31: CHECKED | Q31: 144 | R31: 46260.691 | AA31: =IFERROR( IF(ISNUMBER(C31),C31,DATE(VALUE(RIGHT(C31,4)),VALUE(MID(SUBSTITUTE(C31,"/","-"),FIND("-",SUBSTITUTE(C31,"/","-"))+1,FIND("-",SUBSTITUTE(C31,"/","-"),FIND("-",SUBSTITUTE(C31,"/","-"))+1)-FIND("-",SUBSTITUTE(C31,"/","-"))-1)),VALUE(LEFT(SUBSTITUTE(C31,"/","-"),FIND("-",SUBSTITUTE(C31,"/","-"))-1)))), DATE(1995,1,1) ) -> 46254
A32: 24 | B32: 2117 | C32: 21-06-2026 | D32: 1464715285 | E32: FAN | F32: Printing and Packaging | G32: 3201010004 | H32: Body Sticker-5601 | I32: Pcs | J32: 40425 | K32: 12216.85 | L32: 40425 | M32: 12216.85 | N32: 0 | O32: 0 | P32: PENDING | Q32: 144 | R32: 46196.36 | AA32: =IFERROR( IF(ISNUMBER(C32),C32,DATE(VALUE(RIGHT(C32,4)),VALUE(MID(SUBSTITUTE(C32,"/","-"),FIND("-",SUBSTITUTE(C32,"/","-"))+1,FIND("-",SUBSTITUTE(C32,"/","-"),FIND("-",SUBSTITUTE(C32,"/","-"))+1)-FIND("-",SUBSTITUTE(C32,"/","-"))-1)),VALUE(LEFT(SUBSTITUTE(C32,"/","-"),FIND("-",SUBSTITUTE(C32,"/","-"))-1)))), DATE(1995,1,1) ) -> 46194
A33: 25 | B33: 2206 | C33: 22-07-2026 | D33: 15333 | E33: FAN | F33: Printing and Packaging | G33: 3201010004 | H33: Body Sticker-5601 | I33: Pcs | J33: 31500 | K33: 9519.63 | L33: 31500 | M33: 9519.63 | N33: 0 | O33: 0 | P33: PENDING | Q33: 144 | R33: 46228.398 | AA33: =IFERROR( IF(ISNUMBER(C33),C33,DATE(VALUE(RIGHT(C33,4)),VALUE(MID(SUBSTITUTE(C33,"/","-"),FIND("-",SUBSTITUTE(C33,"/","-"))+1,FIND("-",SUBSTITUTE(C33,"/","-"),FIND("-",SUBSTITUTE(C33,"/","-"))+1)-FIND("-",SUBSTITUTE(C33,"/","-"))-1)),VALUE(LEFT(SUBSTITUTE(C33,"/","-"),FIND("-",SUBSTITUTE(C33,"/","-"))-1)))), DATE(1995,1,1) ) -> 46225
A34: 26 | B34: 2283 | C34: 20-08-2026 | E34: FAN | F34: Printing and Packaging | G34: 3201010006 | H34: Body Sticker Speed King | I34: Pcs | J34: 10500 | K34: 3152.5 | M34: 0 | N34: 10500 | O34: 3152.5 | P34: CHECKED | Q34: 144 | R34: 46260.691 | AA34: =IFERROR( IF(ISNUMBER(C34),C34,DATE(VALUE(RIGHT(C34,4)),VALUE(MID(SUBSTITUTE(C34,"/","-"),FIND("-",SUBSTITUTE(C34,"/","-"))+1,FIND("-",SUBSTITUTE(C34,"/","-"),FIND("-",SUBSTITUTE(C34,"/","-"))+1)-FIND("-",SUBSTITUTE(C34,"/","-"))-1)),VALUE(LEFT(SUBSTITUTE(C34,"/","-"),FIND("-",SUBSTITUTE(C34,"/","-"))-1)))), DATE(1995,1,1) ) -> 46254
A35: 27 | B35: 2206 | C35: 22-07-2026 | D35: 15333 | E35: FAN | F35: Printing and Packaging | G35: 3201010007 | H35: Body Sticker-4801 | I35: Pcs | J35: 5250 | K35: 1503.11 | L35: 5250 | M35: 1503.11 | N35: 0 | O35: 0 | P35: PENDING | Q35: 144 | R35: 46228.398 | AA35: =IFERROR( IF(ISNUMBER(C35),C35,DATE(VALUE(RIGHT(C35,4)),VALUE(MID(SUBSTITUTE(C35,"/","-"),FIND("-",SUBSTITUTE(C35,"/","-"))+1,FIND("-",SUBSTITUTE(C35,"/","-"),FIND("-",SUBSTITUTE(C35,"/","-"))+1)-FIND("-",SUBSTITUTE(C35,"/","-"))-1)),VALUE(LEFT(SUBSTITUTE(C35,"/","-"),FIND("-",SUBSTITUTE(C35,"/","-"))-1)))), DATE(1995,1,1) ) -> 46225
A36: 28 | B36: 2206 | C36: 22-07-2026 | D36: 15333 | E36: FAN | F36: Printing and Packaging | G36: 3201010008 | H36: Body Sticker-3601 | I36: Pcs | J36: 5250 | K36: 1525.91 | L36: 5250 | M36: 1525.91 | N36: 0 | O36: 0 | P36: PENDING | Q36: 144 | R36: 46228.398 | AA36: =IFERROR( IF(ISNUMBER(C36),C36,DATE(VALUE(RIGHT(C36,4)),VALUE(MID(SUBSTITUTE(C36,"/","-"),FIND("-",SUBSTITUTE(C36,"/","-"))+1,FIND("-",SUBSTITUTE(C36,"/","-"),FIND("-",SUBSTITUTE(C36,"/","-"))+1)-FIND("-",SUBSTITUTE(C36,"/","-"))-1)),VALUE(LEFT(SUBSTITUTE(C36,"/","-"),FIND("-",SUBSTITUTE(C36,"/","-"))-1)))), DATE(1995,1,1) ) -> 46225
A37: 29 | B37: 2283 | C37: 20-08-2026 | E37: FAN | F37: Printing and Packaging | G37: 3201010008 | H37: Body Sticker-3601 | I37: Pcs | J37: 5000 | K37: 1453.25 | M37: 0 | N37: 5000 | O37: 1453.25 | P37: CHECKED | Q37: 144 | R37: 46260.691 | AA37: =IFERROR( IF(ISNUMBER(C37),C37,DATE(VALUE(RIGHT(C37,4)),VALUE(MID(SUBSTITUTE(C37,"/","-"),FIND("-",SUBSTITUTE(C37,"/","-"))+1,FIND("-",SUBSTITUTE(C37,"/","-"),FIND("-",SUBSTITUTE(C37,"/","-"))+1)-FIND("-",SUBSTITUTE(C37,"/","-"))-1)),VALUE(LEFT(SUBSTITUTE(C37,"/","-"),FIND("-",SUBSTITUTE(C37,"/","-"))-1)))), DATE(1995,1,1) ) -> 46254
A38: 30 | B38: 2117 | C38: 21-06-2026 | E38: FAN | F38: Printing and Packaging | G38: 3201010009 | H38: Body Sticker-2401 | I38: Pcs | J38: 5250 | K38: 1886.17 | M38: 0 | N38: 5250 | O38: 1886.17 | P38: PENDING | Q38: 144 | R38: 46196.36 | AA38: =IFERROR( IF(ISNUMBER(C38),C38,DATE(VALUE(RIGHT(C38,4)),VALUE(MID(SUBSTITUTE(C38,"/","-"),FIND("-",SUBSTITUTE(C38,"/","-"))+1,FIND("-",SUBSTITUTE(C38,"/","-"),FIND("-",SUBSTITUTE(C38,"/","-"))+1)-FIND("-",SUBSTITUTE(C38,"/","-"))-1)),VALUE(LEFT(SUBSTITUTE(C38,"/","-"),FIND("-",SUBSTITUTE(C38,"/","-"))-1)))), DATE(1995,1,1) ) -> 46194
A39: 31 | B39: 2206 | C39: 22-07-2026 | D39: 15338 | E39: FAN | F39: Printing and Packaging | G39: 3201010009 | H39: Body Sticker-2401 | I39: Pcs | J39: 5250 | K39: 1886.17 | L39: 5000 | M39: 1796.35 | N39: 250 | O39: 89.82 | P39: PENDING | Q39: 144 | R39: 46228.398 | AA39: =IFERROR( IF(ISNUMBER(C39),C39,DATE(VALUE(RIGHT(C39,4)),VALUE(MID(SUBSTITUTE(C39,"/","-"),FIND("-",SUBSTITUTE(C39,"/","-"))+1,FIND("-",SUBSTITUTE(C39,"/","-"),FIND("-",SUBSTITUTE(C39,"/","-"))+1)-FIND("-",SUBSTITUTE(C39,"/","-"))-1)),VALUE(LEFT(SUBSTITUTE(C39,"/","-"),FIND("-",SUBSTITUTE(C39,"/","-"))-1)))), DATE(1995,1,1) ) -> 46225
A40: 32 | B40: 2117 | C40: 21-06-2026 | D40: 1579414576 | E40: FAN | F40: Printing and Packaging | G40: 3201010010 | H40: Fan Canopy Sticker | I40: Pcs | J40: 93450 | K40: 45924.6 | L40: 33050 | M40: 16241.93 | N40: 60400 | O40: 29682.67 | P40: PENDING | Q40: 144 | R40: 46196.36 | AA40: =IFERROR( IF(ISNUMBER(C40),C40,DATE(VALUE(RIGHT(C40,4)),VALUE(MID(SUBSTITUTE(C40,"/","-"),FIND("-",SUBSTITUTE(C40,"/","-"))+1,FIND("-",SUBSTITUTE(C40,"/","-"),FIND("-",SUBSTITUTE(C40,"/","-"))+1)-FIND("-",SUBSTITUTE(C40,"/","-"))-1)),VALUE(LEFT(SUBSTITUTE(C40,"/","-"),FIND("-",SUBSTITUTE(C40,"/","-"))-1)))), DATE(1995,1,1) ) -> 46194
A41: 33 | B41: 2206 | C41: 22-07-2026 | D41: 15547 | E41: FAN | F41: Printing and Packaging | G41: 3201010010 | H41: Fan Canopy Sticker | I41: Pcs | J41: 94500 | K41: 46440.61 | L41: 94500 | M41: 46440.61 | N41: 0 | O41: 0 | P41: PENDING | Q41: 144 | R41: 46228.398 | AA41: =IFERROR( IF(ISNUMBER(C41),C41,DATE(VALUE(RIGHT(C41,4)),VALUE(MID(SUBSTITUTE(C41,"/","-"),FIND("-",SUBSTITUTE(C41,"/","-"))+1,FIND("-",SUBSTITUTE(C41,"/","-"),FIND("-",SUBSTITUTE(C41,"/","-"))+1)-FIND("-",SUBSTITUTE(C41,"/","-"))-1)),VALUE(LEFT(SUBSTITUTE(C41,"/","-"),FIND("-",SUBSTITUTE(C41,"/","-"))-1)))), DATE(1995,1,1) ) -> 46225
A42: 34 | B42: 2283 | C42: 20-08-2026 | E42: FAN | F42: Printing and Packaging | G42: 3201010010 | H42: Fan Canopy Sticker | I42: Pcs | J42: 60000 | K42: 29486.1 | M42: 0 | N42: 60000 | O42: 29486.1 | P42: CHECKED | Q42: 144 | R42: 46260.691 | AA42: =IFERROR( IF(ISNUMBER(C42),C42,DATE(VALUE(RIGHT(C42,4)),VALUE(MID(SUBSTITUTE(C42,"/","-"),FIND("-",SUBSTITUTE(C42,"/","-"))+1,FIND("-",SUBSTITUTE(C42,"/","-"),FIND("-",SUBSTITUTE(C42,"/","-"))+1)-FIND("-",SUBSTITUTE(C42,"/","-"))-1)),VALUE(LEFT(SUBSTITUTE(C42,"/","-"),FIND("-",SUBSTITUTE(C42,"/","-"))-1)))), DATE(1995,1,1) ) -> 46254
A43: 35 | B43: 2283 | C43: 20-08-2026 | E43: FAN | F43: Printing and Packaging | G43: 3201010011 | H43: Canopy Sticker Speed King | I43: Pcs | J43: 20000 | K43: 8769.68 | M43: 0 | N43: 20000 | O43: 8769.68 | P43: CHECKED | Q43: 144 | R43: 46260.691 | AA43: =IFERROR( IF(ISNUMBER(C43),C43,DATE(VALUE(RIGHT(C43,4)),VALUE(MID(SUBSTITUTE(C43,"/","-"),FIND("-",SUBSTITUTE(C43,"/","-"))+1,FIND("-",SUBSTITUTE(C43,"/","-"),FIND("-",SUBSTITUTE(C43,"/","-"))+1)-FIND("-",SUBSTITUTE(C43,"/","-"))-1)),VALUE(LEFT(SUBSTITUTE(C43,"/","-"),FIND("-",SUBSTITUTE(C43,"/","-"))-1)))), DATE(1995,1,1) ) -> 46254
A44: 36 | B44: 2117 | C44: 21-06-2026 | E44: FAN | F44: Printing and Packaging | G44: 3201010013 | H44: Fan Down Pipe Sticker | I44: Pcs | J44: 41475 | K44: 15508.05 | M44: 0 | N44: 41475 | O44: 15508.05 | P44: PENDING | Q44: 144 | R44: 46196.36 | AA44: =IFERROR( IF(ISNUMBER(C44),C44,DATE(VALUE(RIGHT(C44,4)),VALUE(MID(SUBSTITUTE(C44,"/","-"),FIND("-",SUBSTITUTE(C44,"/","-"))+1,FIND("-",SUBSTITUTE(C44,"/","-"),FIND("-",SUBSTITUTE(C44,"/","-"))+1)-FIND("-",SUBSTITUTE(C44,"/","-"))-1)),VALUE(LEFT(SUBSTITUTE(C44,"/","-"),FIND("-",SUBSTITUTE(C44,"/","-"))-1)))), DATE(1995,1,1) ) -> 46194
A45: 37 | B45: 2206 | C45: 22-07-2026 | D45: 15338 | E45: FAN | F45: Printing and Packaging | G45: 3201010013 | H45: Fan Down Pipe Sticker | I45: Pcs | J45: 36750 | K45: 13741.31 | L45: 17500 | M45: 6543.48 | N45: 19250 | O45: 7197.83 | P45: PENDING | Q45: 144 | R45: 46228.398 | AA45: =IFERROR( IF(ISNUMBER(C45),C45,DATE(VALUE(RIGHT(C45,4)),VALUE(MID(SUBSTITUTE(C45,"/","-"),FIND("-",SUBSTITUTE(C45,"/","-"))+1,FIND("-",SUBSTITUTE(C45,"/","-"),FIND("-",SUBSTITUTE(C45,"/","-"))+1)-FIND("-",SUBSTITUTE(C45,"/","-"))-1)),VALUE(LEFT(SUBSTITUTE(C45,"/","-"),FIND("-",SUBSTITUTE(C45,"/","-"))-1)))), DATE(1995,1,1) ) -> 46225
A46: 38 | B46: 2283 | C46: 20-08-2026 | E46: FAN | F46: Printing and Packaging | G46: 3201010013 | H46: Fan Down Pipe Sticker | I46: Pcs | J46: 21000 | K46: 7852.18 | M46: 0 | N46: 21000 | O46: 7852.18 | P46: CHECKED | Q46: 144 | R46: 46260.691 | AA46: =IFERROR( IF(ISNUMBER(C46),C46,DATE(VALUE(RIGHT(C46,4)),VALUE(MID(SUBSTITUTE(C46,"/","-"),FIND("-",SUBSTITUTE(C46,"/","-"))+1,FIND("-",SUBSTITUTE(C46,"/","-"),FIND("-",SUBSTITUTE(C46,"/","-"))+1)-FIND("-",SUBSTITUTE(C46,"/","-"))-1)),VALUE(LEFT(SUBSTITUTE(C46,"/","-"),FIND("-",SUBSTITUTE(C46,"/","-"))-1)))), DATE(1995,1,1) ) -> 46254
A47: 39 | B47: 2108 | C47: 20-06-2026 | E47: FAN | F47: Printing and Packaging | G47: 3201010014 | H47: Fan QC Sticker | I47: Pcs | J47: 6000 | K47: 1353.8 | M47: 0 | N47: 6000 | O47: 1353.8 | P47: PENDING | Q47: 144 | R47: 46193.793 | AA47: =IFERROR( IF(ISNUMBER(C47),C47,DATE(VALUE(RIGHT(C47,4)),VALUE(MID(SUBSTITUTE(C47,"/","-"),FIND("-",SUBSTITUTE(C47,"/","-"))+1,FIND("-",SUBSTITUTE(C47,"/","-"),FIND("-",SUBSTITUTE(C47,"/","-"))+1)-FIND("-",SUBSTITUTE(C47,"/","-"))-1)),VALUE(LEFT(SUBSTITUTE(C47,"/","-"),FIND("-",SUBSTITUTE(C47,"/","-"))-1)))), DATE(1995,1,1) ) -> 46193
A48: 40 | B48: 2111 | C48: 21-06-2026 | D48: 14908 | E48: FAN | F48: Printing and Packaging | G48: 3201010014 | H48: Fan QC Sticker | I48: Pcs | J48: 15500 | K48: 3497.32 | L48: 12750 | M48: 2876.82 | N48: 2750 | O48: 620.49 | P48: PENDING | Q48: 144 | R48: 46196.358 | AA48: =IFERROR( IF(ISNUMBER(C48),C48,DATE(VALUE(RIGHT(C48,4)),VALUE(MID(SUBSTITUTE(C48,"/","-"),FIND("-",SUBSTITUTE(C48,"/","-"))+1,FIND("-",SUBSTITUTE(C48,"/","-"),FIND("-",SUBSTITUTE(C48,"/","-"))+1)-FIND("-",SUBSTITUTE(C48,"/","-"))-1)),VALUE(LEFT(SUBSTITUTE(C48,"/","-"),FIND("-",SUBSTITUTE(C48,"/","-"))-1)))), DATE(1995,1,1) ) -> 46194
A49: 41 | B49: 2117 | C49: 21-06-2026 | D49: 14909 | E49: FAN | F49: Printing and Packaging | G49: 3201010014 | H49: Fan QC Sticker | I49: Pcs | J49: 47250 | K49: 10661.17 | L49: 47250 | M49: 10661.17 | N49: 0 | O49: 0 | P49: PENDING | Q49: 144 | R49: 46196.36 | AA49: =IFERROR( IF(ISNUMBER(C49),C49,DATE(VALUE(RIGHT(C49,4)),VALUE(MID(SUBSTITUTE(C49,"/","-"),FIND("-",SUBSTITUTE(C49,"/","-"))+1,FIND("-",SUBSTITUTE(C49,"/","-"),FIND("-",SUBSTITUTE(C49,"/","-"))+1)-FIND("-",SUBSTITUTE(C49,"/","-"))-1)),VALUE(LEFT(SUBSTITUTE(C49,"/","-"),FIND("-",SUBSTITUTE(C49,"/","-"))-1)))), DATE(1995,1,1) ) -> 46194
A50: 42 | B50: 2206 | C50: 22-07-2026 | D50: 15354 | E50: FAN | F50: Printing and Packaging | G50: 3201010014 | H50: Fan QC Sticker | I50: Pcs | J50: 47250 | K50: 10661.17 | L50: 40000 | M50: 9025.33 | N50: 7250 | O50: 1635.84 | P50: PENDING | Q50: 144 | R50: 46228.398 | AA50: =IFERROR( IF(ISNUMBER(C50),C50,DATE(VALUE(RIGHT(C50,4)),VALUE(MID(SUBSTITUTE(C50,"/","-"),FIND("-",SUBSTITUTE(C50,"/","-"))+1,FIND("-",SUBSTITUTE(C50,"/","-"),FIND("-",SUBSTITUTE(C50,"/","-"))+1)-FIND("-",SUBSTITUTE(C50,"/","-"))-1)),VALUE(LEFT(SUBSTITUTE(C50,"/","-"),FIND("-",SUBSTITUTE(C50,"/","-"))-1)))), DATE(1995,1,1) ) -> 46225
A51: 43 | B51: 2219 | C51: 26-07-2026 | D51: 15353 | E51: FAN | F51: Printing and Packaging | G51: 3201010014 | H51: Fan QC Sticker | I51: Pcs | J51: 20000 | K51: 4512.67 | L51: 20000 | M51: 4512.67 | N51: 0 | O51: 0 | P51: PENDING | Q51: 144 | R51: 46229.685 | AA51: =IFERROR( IF(ISNUMBER(C51),C51,DATE(VALUE(RIGHT(C51,4)),VALUE(MID(SUBSTITUTE(C51,"/","-"),FIND("-",SUBSTITUTE(C51,"/","-"))+1,FIND("-",SUBSTITUTE(C51,"/","-"),FIND("-",SUBSTITUTE(C51,"/","-"))+1)-FIND("-",SUBSTITUTE(C51,"/","-"))-1)),VALUE(LEFT(SUBSTITUTE(C51,"/","-"),FIND("-",SUBSTITUTE(C51,"/","-"))-1)))), DATE(1995,1,1) ) -> 46229
A52: 44 | B52: 2282 | C52: 20-08-2026 | E52: FAN | F52: Printing and Packaging | G52: 3201010014 | H52: Fan QC Sticker | I52: Pcs | J52: 0 | K52: 0 | M52: 0 | N52: 0 | O52: 0 | P52: CHECKED | Q52: 144 | R52: 46260.682 | AA52: =IFERROR( IF(ISNUMBER(C52),C52,DATE(VALUE(RIGHT(C52,4)),VALUE(MID(SUBSTITUTE(C52,"/","-"),FIND("-",SUBSTITUTE(C52,"/","-"))+1,FIND("-",SUBSTITUTE(C52,"/","-"),FIND("-",SUBSTITUTE(C52,"/","-"))+1)-FIND("-",SUBSTITUTE(C52,"/","-"))-1)),VALUE(LEFT(SUBSTITUTE(C52,"/","-"),FIND("-",SUBSTITUTE(C52,"/","-"))-1)))), DATE(1995,1,1) ) -> 46254
A53: 45 | B53: 2283 | C53: 20-08-2026 | E53: FAN | F53: Printing and Packaging | G53: 3201010014 | H53: Fan QC Sticker | I53: Pcs | J53: 43000 | K53: 9702.23 | M53: 0 | N53: 43000 | O53: 9702.23 | P53: CHECKED | Q53: 144 | R53: 46260.691 | AA53: =IFERROR( IF(ISNUMBER(C53),C53,DATE(VALUE(RIGHT(C53,4)),VALUE(MID(SUBSTITUTE(C53,"/","-"),FIND("-",SUBSTITUTE(C53,"/","-"))+1,FIND("-",SUBSTITUTE(C53,"/","-"),FIND("-",SUBSTITUTE(C53,"/","-"))+1)-FIND("-",SUBSTITUTE(C53,"/","-"))-1)),VALUE(LEFT(SUBSTITUTE(C53,"/","-"),FIND("-",SUBSTITUTE(C53,"/","-"))-1)))), DATE(1995,1,1) ) -> 46254
A54: 46 | B54: 2117 | C54: 21-06-2026 | D54: 1.4459149e+19 | E54: FAN | F54: Printing and Packaging | G54: 3201010015 | H54: Guarantee Card -5601 | I54: Pcs | J54: 41475 | K54: 60623.1 | L54: 27775 | M54: 40598.11 | N54: 13700 | O54: 20024.99 | P54: PENDING | Q54: 144 | R54: 46196.36 | AA54: =IFERROR( IF(ISNUMBER(C54),C54,DATE(VALUE(RIGHT(C54,4)),VALUE(MID(SUBSTITUTE(C54,"/","-"),FIND("-",SUBSTITUTE(C54,"/","-"))+1,FIND("-",SUBSTITUTE(C54,"/","-"),FIND("-",SUBSTITUTE(C54,"/","-"))+1)-FIND("-",SUBSTITUTE(C54,"/","-"))-1)),VALUE(LEFT(SUBSTITUTE(C54,"/","-"),FIND("-",SUBSTITUTE(C54,"/","-"))-1)))), DATE(1995,1,1) ) -> 46194
A55: 47 | B55: 2206 | C55: 22-07-2026 | D55: 15409 | E55: FAN | F55: Printing and Packaging | G55: 3201010015 | H55: Guarantee Card -5601 | I55: Pcs | J55: 31500 | K55: 46042.86 | L55: 31500 | M55: 46042.86 | N55: 0 | O55: 0 | P55: PENDING | Q55: 144 | R55: 46228.398 | AA55: =IFERROR( IF(ISNUMBER(C55),C55,DATE(VALUE(RIGHT(C55,4)),VALUE(MID(SUBSTITUTE(C55,"/","-"),FIND("-",SUBSTITUTE(C55,"/","-"))+1,FIND("-",SUBSTITUTE(C55,"/","-"),FIND("-",SUBSTITUTE(C55,"/","-"))+1)-FIND("-",SUBSTITUTE(C55,"/","-"))-1)),VALUE(LEFT(SUBSTITUTE(C55,"/","-"),FIND("-",SUBSTITUTE(C55,"/","-"))-1)))), DATE(1995,1,1) ) -> 46225
A56: 48 | B56: 2283 | C56: 20-08-2026 | E56: FAN | F56: Printing and Packaging | G56: 3201010015 | H56: Guarantee Card -5601 | I56: Pcs | J56: 21210 | K56: 31002.2 | M56: 0 | N56: 21210 | O56: 31002.2 | P56: CHECKED | Q56: 144 | R56: 46260.691 | AA56: =IFERROR( IF(ISNUMBER(C56),C56,DATE(VALUE(RIGHT(C56,4)),VALUE(MID(SUBSTITUTE(C56,"/","-"),FIND("-",SUBSTITUTE(C56,"/","-"))+1,FIND("-",SUBSTITUTE(C56,"/","-"),FIND("-",SUBSTITUTE(C56,"/","-"))+1)-FIND("-",SUBSTITUTE(C56,"/","-"))-1)),VALUE(LEFT(SUBSTITUTE(C56,"/","-"),FIND("-",SUBSTITUTE(C56,"/","-"))-1)))), DATE(1995,1,1) ) -> 46254
A57: 49 | B57: 2206 | C57: 22-07-2026 | D57: 15426 | E57: FAN | F57: Printing and Packaging | G57: 3201010016 | H57: Guarantee Card -4801 | I57: Pcs | J57: 5250 | K57: 8986.68 | L57: 5000 | M57: 8558.74 | N57: 250 | O57: 427.94 | P57: PENDING | Q57: 144 | R57: 46228.398 | AA57: =IFERROR( IF(ISNUMBER(C57),C57,DATE(VALUE(RIGHT(C57,4)),VALUE(MID(SUBSTITUTE(C57,"/","-"),FIND("-",SUBSTITUTE(C57,"/","-"))+1,FIND("-",SUBSTITUTE(C57,"/","-"),FIND("-",SUBSTITUTE(C57,"/","-"))+1)-FIND("-",SUBSTITUTE(C57,"/","-"))-1)),VALUE(LEFT(SUBSTITUTE(C57,"/","-"),FIND("-",SUBSTITUTE(C57,"/","-"))-1)))), DATE(1995,1,1) ) -> 46225
A58: 50 | B58: 2283 | C58: 20-08-2026 | E58: FAN | F58: Printing and Packaging | G58: 3201010017 | H58: Guarantee Card Speed King | I58: Pcs | J58: 10500 | K58: 23464.27 | M58: 0 | N58: 10500 | O58: 23464.27 | P58: CHECKED | Q58: 144 | R58: 46260.691 | AA58: =IFERROR( IF(ISNUMBER(C58),C58,DATE(VALUE(RIGHT(C58,4)),VALUE(MID(SUBSTITUTE(C58,"/","-"),FIND("-",SUBSTITUTE(C58,"/","-"))+1,FIND("-",SUBSTITUTE(C58,"/","-"),FIND("-",SUBSTITUTE(C58,"/","-"))+1)-FIND("-",SUBSTITUTE(C58,"/","-"))-1)),VALUE(LEFT(SUBSTITUTE(C58,"/","-"),FIND("-",SUBSTITUTE(C58,"/","-"))-1)))), DATE(1995,1,1) ) -> 46254
A59: 51 | B59: 2117 | C59: 21-06-2026 | E59: FAN | F59: Printing and Packaging | G59: 3201010018 | H59: Guarantee Card -2401,3601 | I59: Pcs | J59: 5250 | K59: 6405.84 | M59: 0 | N59: 5250 | O59: 6405.84 | P59: PENDING | Q59: 144 | R59: 46196.36 | AA59: =IFERROR( IF(ISNUMBER(C59),C59,DATE(VALUE(RIGHT(C59,4)),VALUE(MID(SUBSTITUTE(C59,"/","-"),FIND("-",SUBSTITUTE(C59,"/","-"))+1,FIND("-",SUBSTITUTE(C59,"/","-"),FIND("-",SUBSTITUTE(C59,"/","-"))+1)-FIND("-",SUBSTITUTE(C59,"/","-"))-1)),VALUE(LEFT(SUBSTITUTE(C59,"/","-"),FIND("-",SUBSTITUTE(C59,"/","-"))-1)))), DATE(1995,1,1) ) -> 46194
A60: 52 | B60: 2206 | C60: 22-07-2026 | D60: 15703 | E60: FAN | F60: Printing and Packaging | G60: 3201010018 | H60: Guarantee Card -2401,3601 | I60: Pcs | J60: 10500 | K60: 12811.67 | L60: 10000 | M60: 12201.59 | N60: 500 | O60: 610.08 | P60: PENDING | Q60: 144 | R60: 46228.398 | AA60: =IFERROR( IF(ISNUMBER(C60),C60,DATE(VALUE(RIGHT(C60,4)),VALUE(MID(SUBSTITUTE(C60,"/","-"),FIND("-",SUBSTITUTE(C60,"/","-"))+1,FIND("-",SUBSTITUTE(C60,"/","-"),FIND("-",SUBSTITUTE(C60,"/","-"))+1)-FIND("-",SUBSTITUTE(C60,"/","-"))-1)),VALUE(LEFT(SUBSTITUTE(C60,"/","-"),FIND("-",SUBSTITUTE(C60,"/","-"))-1)))), DATE(1995,1,1) ) -> 46225
A61: 53 | B61: 2283 | C61: 20-08-2026 | E61: FAN | F61: Printing and Packaging | G61: 3201010018 | H61: Guarantee Card -2401,3601 | I61: Pcs | J61: 10500 | K61: 12811.67 | M61: 0 | N61: 10500 | O61: 12811.67 | P61: CHECKED | Q61: 144 | R61: 46260.691 | AA61: =IFERROR( IF(ISNUMBER(C61),C61,DATE(VALUE(RIGHT(C61,4)),VALUE(MID(SUBSTITUTE(C61,"/","-"),FIND("-",SUBSTITUTE(C61,"/","-"))+1,FIND("-",SUBSTITUTE(C61,"/","-"),FIND("-",SUBSTITUTE(C61,"/","-"))+1)-FIND("-",SUBSTITUTE(C61,"/","-"))-1)),VALUE(LEFT(SUBSTITUTE(C61,"/","-"),FIND("-",SUBSTITUTE(C61,"/","-"))-1)))), DATE(1995,1,1) ) -> 46254
A62: 54 | B62: 2117 | C62: 21-06-2026 | D62: 1.4803149e+84 | E62: FAN | F62: Printing and Packaging | G62: 3201010019 | H62: Cork Sheet -5601````/4801```` | I62: Pcs | J62: 41475 | K62: 797041.27 | L62: 14000 | M62: 269043.47 | N62: 27475 | O62: 527997.8 | P62: PENDING | Q62: 144 | R62: 46196.36 | AA62: =IFERROR( IF(ISNUMBER(C62),C62,DATE(VALUE(RIGHT(C62,4)),VALUE(MID(SUBSTITUTE(C62,"/","-"),FIND("-",SUBSTITUTE(C62,"/","-"))+1,FIND("-",SUBSTITUTE(C62,"/","-"),FIND("-",SUBSTITUTE(C62,"/","-"))+1)-FIND("-",SUBSTITUTE(C62,"/","-"))-1)),VALUE(LEFT(SUBSTITUTE(C62,"/","-"),FIND("-",SUBSTITUTE(C62,"/","-"))-1)))), DATE(1995,1,1) ) -> 46194
A63: 55 | B63: 2206 | C63: 22-07-2026 | D63: 1.5776154e+144 | E63: FAN | F63: Printing and Packaging | G63: 3201010019 | H63: Cork Sheet -5601````/4801```` | I63: Pcs | J63: 36750 | K63: 706239.1 | L63: 24250 | M63: 466021.72 | N63: 12500 | O63: 240217.38 | P63: PENDING | Q63: 144 | R63: 46228.398 | AA63: =IFERROR( IF(ISNUMBER(C63),C63,DATE(VALUE(RIGHT(C63,4)),VALUE(MID(SUBSTITUTE(C63,"/","-"),FIND("-",SUBSTITUTE(C63,"/","-"))+1,FIND("-",SUBSTITUTE(C63,"/","-"),FIND("-",SUBSTITUTE(C63,"/","-"))+1)-FIND("-",SUBSTITUTE(C63,"/","-"))-1)),VALUE(LEFT(SUBSTITUTE(C63,"/","-"),FIND("-",SUBSTITUTE(C63,"/","-"))-1)))), DATE(1995,1,1) ) -> 46225
A64: 56 | B64: 2283 | C64: 20-08-2026 | E64: FAN | F64: Printing and Packaging | G64: 3201010019 | H64: Cork Sheet -5601````/4801```` | I64: Pcs | J64: 21210 | K64: 407600.85 | M64: 0 | N64: 21210 | O64: 407600.85 | P64: CHECKED | Q64: 144 | R64: 46260.691 | AA64: =IFERROR( IF(ISNUMBER(C64),C64,DATE(VALUE(RIGHT(C64,4)),VALUE(MID(SUBSTITUTE(C64,"/","-"),FIND("-",SUBSTITUTE(C64,"/","-"))+1,FIND("-",SUBSTITUTE(C64,"/","-"),FIND("-",SUBSTITUTE(C64,"/","-"))+1)-FIND("-",SUBSTITUTE(C64,"/","-"))-1)),VALUE(LEFT(SUBSTITUTE(C64,"/","-"),FIND("-",SUBSTITUTE(C64,"/","-"))-1)))), DATE(1995,1,1) ) -> 46254
A65: 57 | B65: 2283 | C65: 20-08-2026 | E65: FAN | F65: Printing and Packaging | G65: 3201010020 | H65: Cork Sheet -5602```` | I65: Pcs | J65: 10500 | K65: 22369.56 | M65: 0 | N65: 10500 | O65: 22369.56 | P65: CHECKED | Q65: 144 | R65: 46260.691 | AA65: =IFERROR( IF(ISNUMBER(C65),C65,DATE(VALUE(RIGHT(C65,4)),VALUE(MID(SUBSTITUTE(C65,"/","-"),FIND("-",SUBSTITUTE(C65,"/","-"))+1,FIND("-",SUBSTITUTE(C65,"/","-"),FIND("-",SUBSTITUTE(C65,"/","-"))+1)-FIND("-",SUBSTITUTE(C65,"/","-"))-1)),VALUE(LEFT(SUBSTITUTE(C65,"/","-"),FIND("-",SUBSTITUTE(C65,"/","-"))-1)))), DATE(1995,1,1) ) -> 46254
A66: 58 | B66: 2117 | C66: 21-06-2026 | E66: FAN | F66: Printing and Packaging | G66: 3201010021 | H66: Cork Sheet -2401/3601 | I66: Pcs | J66: 5250 | K66: 116862.63 | M66: 0 | N66: 5250 | O66: 116862.63 | P66: PENDING | Q66: 144 | R66: 46196.36 | AA66: =IFERROR( IF(ISNUMBER(C66),C66,DATE(VALUE(RIGHT(C66,4)),VALUE(MID(SUBSTITUTE(C66,"/","-"),FIND("-",SUBSTITUTE(C66,"/","-"))+1,FIND("-",SUBSTITUTE(C66,"/","-"),FIND("-",SUBSTITUTE(C66,"/","-"))+1)-FIND("-",SUBSTITUTE(C66,"/","-"))-1)),VALUE(LEFT(SUBSTITUTE(C66,"/","-"),FIND("-",SUBSTITUTE(C66,"/","-"))-1)))), DATE(1995,1,1) ) -> 46194
A67: 59 | B67: 2206 | C67: 22-07-2026 | D67: 1.5807159e+44 | E67: FAN | F67: Printing and Packaging | G67: 3201010021 | H67: Cork Sheet -2401/3601 | I67: Pcs | J67: 10500 | K67: 233725.26 | L67: 7800 | M67: 173624.48 | N67: 2700 | O67: 60100.78 | P67: PENDING | Q67: 144 | R67: 46228.398 | AA67: =IFERROR( IF(ISNUMBER(C67),C67,DATE(VALUE(RIGHT(C67,4)),VALUE(MID(SUBSTITUTE(C67,"/","-"),FIND("-",SUBSTITUTE(C67,"/","-"))+1,FIND("-",SUBSTITUTE(C67,"/","-"),FIND("-",SUBSTITUTE(C67,"/","-"))+1)-FIND("-",SUBSTITUTE(C67,"/","-"))-1)),VALUE(LEFT(SUBSTITUTE(C67,"/","-"),FIND("-",SUBSTITUTE(C67,"/","-"))-1)))), DATE(1995,1,1) ) -> 46225
A68: 60 | B68: 2283 | C68: 20-08-2026 | E68: FAN | F68: Printing and Packaging | G68: 3201010021 | H68: Cork Sheet -2401/3601 | I68: Pcs | J68: 10500 | K68: 233725.26 | M68: 0 | N68: 10500 | O68: 233725.26 | P68: CHECKED | Q68: 144 | R68: 46260.691 | AA68: =IFERROR( IF(ISNUMBER(C68),C68,DATE(VALUE(RIGHT(C68,4)),VALUE(MID(SUBSTITUTE(C68,"/","-"),FIND("-",SUBSTITUTE(C68,"/","-"))+1,FIND("-",SUBSTITUTE(C68,"/","-"),FIND("-",SUBSTITUTE(C68,"/","-"))+1)-FIND("-",SUBSTITUTE(C68,"/","-"))-1)),VALUE(LEFT(SUBSTITUTE(C68,"/","-"),FIND("-",SUBSTITUTE(C68,"/","-"))-1)))), DATE(1995,1,1) ) -> 46254
A69: 61 | B69: 2117 | C69: 21-06-2026 | D69: 1.483115e+54 | E69: FAN | F69: Printing and Packaging | G69: 3201010022 | H69: Body Carton -Premium (5601)-263x264x213mm | I69: Pcs | J69: 40425 | K69: 1743712.2 | L69: 6350 | M69: 273904.08 | N69: 34075 | O69: 1469808.1 | P69: PENDING | Q69: 144 | R69: 46196.36 | AA69: =IFERROR( IF(ISNUMBER(C69),C69,DATE(VALUE(RIGHT(C69,4)),VALUE(MID(SUBSTITUTE(C69,"/","-"),FIND("-",SUBSTITUTE(C69,"/","-"))+1,FIND("-",SUBSTITUTE(C69,"/","-"),FIND("-",SUBSTITUTE(C69,"/","-"))+1)-FIND("-",SUBSTITUTE(C69,"/","-"))-1)),VALUE(LEFT(SUBSTITUTE(C69,"/","-"),FIND("-",SUBSTITUTE(C69,"/","-"))-1)))), DATE(1995,1,1) ) -> 46194
A70: 62 | B70: 2206 | C70: 22-07-2026 | D70: 1.5519156e+174 | E70: FAN | F70: Printing and Packaging | G70: 3201010022 | H70: Body Carton -Premium (5601)-263x264x213mm | I70: Pcs | J70: 31500 | K70: 1358736.8 | L70: 23775 | M70: 1025522.8 | N70: 7725 | O70: 333214.02 | P70: PENDING | Q70: 144 | R70: 46228.398 | AA70: =IFERROR( IF(ISNUMBER(C70),C70,DATE(VALUE(RIGHT(C70,4)),VALUE(MID(SUBSTITUTE(C70,"/","-"),FIND("-",SUBSTITUTE(C70,"/","-"))+1,FIND("-",SUBSTITUTE(C70,"/","-"),FIND("-",SUBSTITUTE(C70,"/","-"))+1)-FIND("-",SUBSTITUTE(C70,"/","-"))-1)),VALUE(LEFT(SUBSTITUTE(C70,"/","-"),FIND("-",SUBSTITUTE(C70,"/","-"))-1)))), DATE(1995,1,1) ) -> 46225
A71: 63 | B71: 2283 | C71: 20-08-2026 | E71: FAN | F71: Printing and Packaging | G71: 3201010022 | H71: Body Carton -Premium (5601)-263x264x213mm | I71: Pcs | J71: 18900 | K71: 815242.06 | M71: 0 | N71: 18900 | O71: 815242.06 | P71: CHECKED | Q71: 144 | R71: 46260.691 | AA71: =IFERROR( IF(ISNUMBER(C71),C71,DATE(VALUE(RIGHT(C71,4)),VALUE(MID(SUBSTITUTE(C71,"/","-"),FIND("-",SUBSTITUTE(C71,"/","-"))+1,FIND("-",SUBSTITUTE(C71,"/","-"),FIND("-",SUBSTITUTE(C71,"/","-"))+1)-FIND("-",SUBSTITUTE(C71,"/","-"))-1)),VALUE(LEFT(SUBSTITUTE(C71,"/","-"),FIND("-",SUBSTITUTE(C71,"/","-"))-1)))), DATE(1995,1,1) ) -> 46254
A72: 64 | B72: 2117 | C72: 21-06-2026 | D72: 15231 | E72: FAN | F72: Printing and Packaging | G72: 3201010023 | H72: Body Carton Premium Gold (5603) | I72: Pcs | J72: 1050 | K72: 43835.52 | L72: 322 | M72: 13442.89 | N72: 728 | O72: 30392.63 | P72: PENDING | Q72: 144 | R72: 46196.36 | AA72: =IFERROR( IF(ISNUMBER(C72),C72,DATE(VALUE(RIGHT(C72,4)),VALUE(MID(SUBSTITUTE(C72,"/","-"),FIND("-",SUBSTITUTE(C72,"/","-"))+1,FIND("-",SUBSTITUTE(C72,"/","-"),FIND("-",SUBSTITUTE(C72,"/","-"))+1)-FIND("-",SUBSTITUTE(C72,"/","-"))-1)),VALUE(LEFT(SUBSTITUTE(C72,"/","-"),FIND("-",SUBSTITUTE(C72,"/","-"))-1)))), DATE(1995,1,1) ) -> 46194
A73: 65 | B73: 2283 | C73: 20-08-2026 | E73: FAN | F73: Printing and Packaging | G73: 3201010023 | H73: Body Carton Premium Gold (5603) | I73: Pcs | J73: 2500 | K73: 104370.28 | M73: 0 | N73: 2500 | O73: 104370.28 | P73: CHECKED | Q73: 144 | R73: 46260.691 | AA73: =IFERROR( IF(ISNUMBER(C73),C73,DATE(VALUE(RIGHT(C73,4)),VALUE(MID(SUBSTITUTE(C73,"/","-"),FIND("-",SUBSTITUTE(C73,"/","-"))+1,FIND("-",SUBSTITUTE(C73,"/","-"),FIND("-",SUBSTITUTE(C73,"/","-"))+1)-FIND("-",SUBSTITUTE(C73,"/","-"))-1)),VALUE(LEFT(SUBSTITUTE(C73,"/","-"),FIND("-",SUBSTITUTE(C73,"/","-"))-1)))), DATE(1995,1,1) ) -> 46254
A74: 66 | B74: 2283 | C74: 20-08-2026 | E74: FAN | F74: Printing and Packaging | G74: 3201010024 | H74: Body Carton Premium Plus (5606) | I74: Pcs | J74: 300 | K74: 35411.81 | M74: 0 | N74: 300 | O74: 35411.81 | P74: CHECKED | Q74: 144 | R74: 46260.691 | AA74: =IFERROR( IF(ISNUMBER(C74),C74,DATE(VALUE(RIGHT(C74,4)),VALUE(MID(SUBSTITUTE(C74,"/","-"),FIND("-",SUBSTITUTE(C74,"/","-"))+1,FIND("-",SUBSTITUTE(C74,"/","-"),FIND("-",SUBSTITUTE(C74,"/","-"))+1)-FIND("-",SUBSTITUTE(C74,"/","-"))-1)),VALUE(LEFT(SUBSTITUTE(C74,"/","-"),FIND("-",SUBSTITUTE(C74,"/","-"))-1)))), DATE(1995,1,1) ) -> 46254
A75: 67 | B75: 2283 | C75: 20-08-2026 | E75: FAN | F75: Printing and Packaging | G75: 3201010026 | H75: Body Carton -Speed king (5602) -220x220x208mm | I75: Pcs | J75: 10500 | K75: 394509.83 | M75: 0 | N75: 10500 | O75: 394509.83 | P75: CHECKED | Q75: 144 | R75: 46260.691 | AA75: =IFERROR( IF(ISNUMBER(C75),C75,DATE(VALUE(RIGHT(C75,4)),VALUE(MID(SUBSTITUTE(C75,"/","-"),FIND("-",SUBSTITUTE(C75,"/","-"))+1,FIND("-",SUBSTITUTE(C75,"/","-"),FIND("-",SUBSTITUTE(C75,"/","-"))+1)-FIND("-",SUBSTITUTE(C75,"/","-"))-1)),VALUE(LEFT(SUBSTITUTE(C75,"/","-"),FIND("-",SUBSTITUTE(C75,"/","-"))-1)))), DATE(1995,1,1) ) -> 46254
A76: 68 | B76: 2206 | C76: 22-07-2026 | D76: 15906 | E76: FAN | F76: Printing and Packaging | G76: 3201010027 | H76: Body Carton -Popular (4801)-264x262x200mm | I76: Pcs | J76: 5250 | K76: 219364.04 | L76: 375 | M76: 15668.86 | N76: 4875 | O76: 203695.18 | P76: PENDING | Q76: 144 | R76: 46228.398 | AA76: =IFERROR( IF(ISNUMBER(C76),C76,DATE(VALUE(RIGHT(C76,4)),VALUE(MID(SUBSTITUTE(C76,"/","-"),FIND("-",SUBSTITUTE(C76,"/","-"))+1,FIND("-",SUBSTITUTE(C76,"/","-"),FIND("-",SUBSTITUTE(C76,"/","-"))+1)-FIND("-",SUBSTITUTE(C76,"/","-"))-1)),VALUE(LEFT(SUBSTITUTE(C76,"/","-"),FIND("-",SUBSTITUTE(C76,"/","-"))-1)))), DATE(1995,1,1) ) -> 46225
A77: 69 | B77: 2206 | C77: 22-07-2026 | D77: 1.5432157e+49 | E77: FAN | F77: Printing and Packaging | G77: 3201010028 | H77: Body Carton -Hero (3601)-195x195x230mm | I77: Pcs | J77: 5250 | K77: 187671.23 | L77: 5195 | M77: 185705.15 | N77: 55 | O77: 1966.08 | P77: PENDING | Q77: 144 | R77: 46228.398 | AA77: =IFERROR( IF(ISNUMBER(C77),C77,DATE(VALUE(RIGHT(C77,4)),VALUE(MID(SUBSTITUTE(C77,"/","-"),FIND("-",SUBSTITUTE(C77,"/","-"))+1,FIND("-",SUBSTITUTE(C77,"/","-"),FIND("-",SUBSTITUTE(C77,"/","-"))+1)-FIND("-",SUBSTITUTE(C77,"/","-"))-1)),VALUE(LEFT(SUBSTITUTE(C77,"/","-"),FIND("-",SUBSTITUTE(C77,"/","-"))-1)))), DATE(1995,1,1) ) -> 46225
A78: 70 | B78: 2283 | C78: 20-08-2026 | E78: FAN | F78: Printing and Packaging | G78: 3201010028 | H78: Body Carton -Hero (3601)-195x195x230mm | I78: Pcs | J78: 10500 | K78: 375342.46 | M78: 0 | N78: 10500 | O78: 375342.46 | P78: CHECKED | Q78: 144 | R78: 46260.691 | AA78: =IFERROR( IF(ISNUMBER(C78),C78,DATE(VALUE(RIGHT(C78,4)),VALUE(MID(SUBSTITUTE(C78,"/","-"),FIND("-",SUBSTITUTE(C78,"/","-"))+1,FIND("-",SUBSTITUTE(C78,"/","-"),FIND("-",SUBSTITUTE(C78,"/","-"))+1)-FIND("-",SUBSTITUTE(C78,"/","-"))-1)),VALUE(LEFT(SUBSTITUTE(C78,"/","-"),FIND("-",SUBSTITUTE(C78,"/","-"))-1)))), DATE(1995,1,1) ) -> 46254
A79: 71 | B79: 2117 | C79: 21-06-2026 | D79: 1458514574 | E79: FAN | F79: Printing and Packaging | G79: 3201010029 | H79: Body Carton -Super (2401)-185x185x267mm | I79: Pcs | J79: 5250 | K79: 199376.48 | L79: 1225 | M79: 46521.18 | N79: 4025 | O79: 152855.3 | P79: PENDING | Q79: 144 | R79: 46196.36 | AA79: =IFERROR( IF(ISNUMBER(C79),C79,DATE(VALUE(RIGHT(C79,4)),VALUE(MID(SUBSTITUTE(C79,"/","-"),FIND("-",SUBSTITUTE(C79,"/","-"))+1,FIND("-",SUBSTITUTE(C79,"/","-"),FIND("-",SUBSTITUTE(C79,"/","-"))+1)-FIND("-",SUBSTITUTE(C79,"/","-"))-1)),VALUE(LEFT(SUBSTITUTE(C79,"/","-"),FIND("-",SUBSTITUTE(C79,"/","-"))-1)))), DATE(1995,1,1) ) -> 46194
A80: 72 | B80: 2206 | C80: 22-07-2026 | D80: 1.5867159e+39 | E80: FAN | F80: Printing and Packaging | G80: 3201010029 | H80: Body Carton -Super (2401)-185x185x267mm | I80: Pcs | J80: 5250 | K80: 199376.48 | L80: 4875 | M80: 185135.31 | N80: 375 | O80: 14241.18 | P80: PENDING | Q80: 144 | R80: 46228.398 | AA80: =IFERROR( IF(ISNUMBER(C80),C80,DATE(VALUE(RIGHT(C80,4)),VALUE(MID(SUBSTITUTE(C80,"/","-"),FIND("-",SUBSTITUTE(C80,"/","-"))+1,FIND("-",SUBSTITUTE(C80,"/","-"),FIND("-",SUBSTITUTE(C80,"/","-"))+1)-FIND("-",SUBSTITUTE(C80,"/","-"))-1)),VALUE(LEFT(SUBSTITUTE(C80,"/","-"),FIND("-",SUBSTITUTE(C80,"/","-"))-1)))), DATE(1995,1,1) ) -> 46225
A81: 73 | B81: 2117 | C81: 21-06-2026 | D81: 1.5095151e+39 | E81: FAN | F81: Printing and Packaging | G81: 3201010030 | H81: Blade Carton-Premium (5601)-622x153x34mm | I81: Pcs | J81: 40425 | K81: 879077.6 | L81: 7300 | M81: 158745 | N81: 33125 | O81: 720332.61 | P81: PENDING | Q81: 144 | R81: 46196.36 | AA81: =IFERROR( IF(ISNUMBER(C81),C81,DATE(VALUE(RIGHT(C81,4)),VALUE(MID(SUBSTITUTE(C81,"/","-"),FIND("-",SUBSTITUTE(C81,"/","-"))+1,FIND("-",SUBSTITUTE(C81,"/","-"),FIND("-",SUBSTITUTE(C81,"/","-"))+1)-FIND("-",SUBSTITUTE(C81,"/","-"))-1)),VALUE(LEFT(SUBSTITUTE(C81,"/","-"),FIND("-",SUBSTITUTE(C81,"/","-"))-1)))), DATE(1995,1,1) ) -> 46194
A82: 74 | B82: 2206 | C82: 22-07-2026 | D82: 1.5384155e+134 | E82: FAN | F82: Printing and Packaging | G82: 3201010030 | H82: Blade Carton-Premium (5601)-622x153x34mm | I82: Pcs | J82: 31500 | K82: 684995.53 | L82: 23723 | M82: 515877.75 | N82: 7777 | O82: 169117.79 | P82: PENDING | Q82: 144 | R82: 46228.398 | AA82: =IFERROR( IF(ISNUMBER(C82),C82,DATE(VALUE(RIGHT(C82,4)),VALUE(MID(SUBSTITUTE(C82,"/","-"),FIND("-",SUBSTITUTE(C82,"/","-"))+1,FIND("-",SUBSTITUTE(C82,"/","-"),FIND("-",SUBSTITUTE(C82,"/","-"))+1)-FIND("-",SUBSTITUTE(C82,"/","-"))-1)),VALUE(LEFT(SUBSTITUTE(C82,"/","-"),FIND("-",SUBSTITUTE(C82,"/","-"))-1)))), DATE(1995,1,1) ) -> 46225
A83: 75 | B83: 2283 | C83: 20-08-2026 | E83: FAN | F83: Printing and Packaging | G83: 3201010030 | H83: Blade Carton-Premium (5601)-622x153x34mm | I83: Pcs | J83: 18900 | K83: 410997.32 | M83: 0 | N83: 18900 | O83: 410997.32 | P83: CHECKED | Q83: 144 | R83: 46260.691 | AA83: =IFERROR( IF(ISNUMBER(C83),C83,DATE(VALUE(RIGHT(C83,4)),VALUE(MID(SUBSTITUTE(C83,"/","-"),FIND("-",SUBSTITUTE(C83,"/","-"))+1,FIND("-",SUBSTITUTE(C83,"/","-"),FIND("-",SUBSTITUTE(C83,"/","-"))+1)-FIND("-",SUBSTITUTE(C83,"/","-"))-1)),VALUE(LEFT(SUBSTITUTE(C83,"/","-"),FIND("-",SUBSTITUTE(C83,"/","-"))-1)))), DATE(1995,1,1) ) -> 46254
A84: 76 | B84: 2117 | C84: 21-06-2026 | E84: FAN | F84: Printing and Packaging | G84: 3201010031 | H84: Blade Carton-Premium Gold (5603) | I84: Pcs | J84: 1050 | K84: 74106.26 | M84: 0 | N84: 1050 | O84: 74106.26 | P84: PENDING | Q84: 144 | R84: 46196.36 | AA84: =IFERROR( IF(ISNUMBER(C84),C84,DATE(VALUE(RIGHT(C84,4)),VALUE(MID(SUBSTITUTE(C84,"/","-"),FIND("-",SUBSTITUTE(C84,"/","-"))+1,FIND("-",SUBSTITUTE(C84,"/","-"),FIND("-",SUBSTITUTE(C84,"/","-"))+1)-FIND("-",SUBSTITUTE(C84,"/","-"))-1)),VALUE(LEFT(SUBSTITUTE(C84,"/","-"),FIND("-",SUBSTITUTE(C84,"/","-"))-1)))), DATE(1995,1,1) ) -> 46194
A85: 77 | B85: 2283 | C85: 20-08-2026 | E85: FAN | F85: Printing and Packaging | G85: 3201010031 | H85: Blade Carton-Premium Gold (5603) | I85: Pcs | J85: 2100 | K85: 148212.52 | M85: 0 | N85: 2100 | O85: 148212.52 | P85: CHECKED | Q85: 144 | R85: 46260.691 | AA85: =IFERROR( IF(ISNUMBER(C85),C85,DATE(VALUE(RIGHT(C85,4)),VALUE(MID(SUBSTITUTE(C85,"/","-"),FIND("-",SUBSTITUTE(C85,"/","-"))+1,FIND("-",SUBSTITUTE(C85,"/","-"),FIND("-",SUBSTITUTE(C85,"/","-"))+1)-FIND("-",SUBSTITUTE(C85,"/","-"))-1)),VALUE(LEFT(SUBSTITUTE(C85,"/","-"),FIND("-",SUBSTITUTE(C85,"/","-"))-1)))), DATE(1995,1,1) ) -> 46254
A86: 78 | B86: 2283 | C86: 20-08-2026 | E86: FAN | F86: Printing and Packaging | G86: 3201010032 | H86: Blade Carton-Premium Plus (5606) | I86: Pcs | J86: 210 | K86: 32074.66 | M86: 0 | N86: 210 | O86: 32074.66 | P86: CHECKED | Q86: 144 | R86: 46260.691 | AA86: =IFERROR( IF(ISNUMBER(C86),C86,DATE(VALUE(RIGHT(C86,4)),VALUE(MID(SUBSTITUTE(C86,"/","-"),FIND("-",SUBSTITUTE(C86,"/","-"))+1,FIND("-",SUBSTITUTE(C86,"/","-"),FIND("-",SUBSTITUTE(C86,"/","-"))+1)-FIND("-",SUBSTITUTE(C86,"/","-"))-1)),VALUE(LEFT(SUBSTITUTE(C86,"/","-"),FIND("-",SUBSTITUTE(C86,"/","-"))-1)))), DATE(1995,1,1) ) -> 46254
A87: 79 | B87: 2283 | C87: 20-08-2026 | E87: FAN | F87: Printing and Packaging | G87: 3201010034 | H87: Blade Carton -Speed king (5602)-622x127x30mm | I87: Pcs | J87: 10500 | K87: 115622.08 | M87: 0 | N87: 10500 | O87: 115622.08 | P87: CHECKED | Q87: 144 | R87: 46260.691 | AA87: =IFERROR( IF(ISNUMBER(C87),C87,DATE(VALUE(RIGHT(C87,4)),VALUE(MID(SUBSTITUTE(C87,"/","-"),FIND("-",SUBSTITUTE(C87,"/","-"))+1,FIND("-",SUBSTITUTE(C87,"/","-"),FIND("-",SUBSTITUTE(C87,"/","-"))+1)-FIND("-",SUBSTITUTE(C87,"/","-"))-1)),VALUE(LEFT(SUBSTITUTE(C87,"/","-"),FIND("-",SUBSTITUTE(C87,"/","-"))-1)))), DATE(1995,1,1) ) -> 46254
A88: 80 | B88: 2206 | C88: 22-07-2026 | E88: FAN | F88: Printing and Packaging | G88: 3201010035 | H88: Blade Carton -Popular (4801)-528x144x32mm | I88: Pcs | J88: 5250 | K88: 94667.97 | M88: 0 | N88: 5250 | O88: 94667.97 | P88: PENDING | Q88: 144 | R88: 46228.398 | AA88: =IFERROR( IF(ISNUMBER(C88),C88,DATE(VALUE(RIGHT(C88,4)),VALUE(MID(SUBSTITUTE(C88,"/","-"),FIND("-",SUBSTITUTE(C88,"/","-"))+1,FIND("-",SUBSTITUTE(C88,"/","-"),FIND("-",SUBSTITUTE(C88,"/","-"))+1)-FIND("-",SUBSTITUTE(C88,"/","-"))-1)),VALUE(LEFT(SUBSTITUTE(C88,"/","-"),FIND("-",SUBSTITUTE(C88,"/","-"))-1)))), DATE(1995,1,1) ) -> 46225
A89: 81 | B89: 2206 | C89: 22-07-2026 | D89: 1.5867159e+34 | E89: FAN | F89: Printing and Packaging | G89: 3201010036 | H89: Blade Carton -Hero (3601)-400x120x29mm | I89: Pcs | J89: 5250 | K89: 67565.22 | L89: 5250 | M89: 67565.22 | N89: 0 | O89: 0 | P89: PENDING | Q89: 144 | R89: 46228.398 | AA89: =IFERROR( IF(ISNUMBER(C89),C89,DATE(VALUE(RIGHT(C89,4)),VALUE(MID(SUBSTITUTE(C89,"/","-"),FIND("-",SUBSTITUTE(C89,"/","-"))+1,FIND("-",SUBSTITUTE(C89,"/","-"),FIND("-",SUBSTITUTE(C89,"/","-"))+1)-FIND("-",SUBSTITUTE(C89,"/","-"))-1)),VALUE(LEFT(SUBSTITUTE(C89,"/","-"),FIND("-",SUBSTITUTE(C89,"/","-"))-1)))), DATE(1995,1,1) ) -> 46225
A90: 82 | B90: 2283 | C90: 20-08-2026 | E90: FAN | F90: Printing and Packaging | G90: 3201010036 | H90: Blade Carton -Hero (3601)-400x120x29mm | I90: Pcs | J90: 10500 | K90: 135130.43 | M90: 0 | N90: 10500 | O90: 135130.43 | P90: CHECKED | Q90: 144 | R90: 46260.691 | AA90: =IFERROR( IF(ISNUMBER(C90),C90,DATE(VALUE(RIGHT(C90,4)),VALUE(MID(SUBSTITUTE(C90,"/","-"),FIND("-",SUBSTITUTE(C90,"/","-"))+1,FIND("-",SUBSTITUTE(C90,"/","-"),FIND("-",SUBSTITUTE(C90,"/","-"))+1)-FIND("-",SUBSTITUTE(C90,"/","-"))-1)),VALUE(LEFT(SUBSTITUTE(C90,"/","-"),FIND("-",SUBSTITUTE(C90,"/","-"))-1)))), DATE(1995,1,1) ) -> 46254
A91: 83 | B91: 2117 | C91: 21-06-2026 | D91: 1512115848 | E91: FAN | F91: Printing and Packaging | G91: 3201010037 | H91: HDPE Poly (L=15``, W=15``, T=0.035mm) | I91: KG | J91: 425 | K91: 118642.92 | L91: 214 | M91: 59740.2 | N91: 211 | O91: 58902.72 | P91: PENDING | Q91: 144 | R91: 46196.36 | AA91: =IFERROR( IF(ISNUMBER(C91),C91,DATE(VALUE(RIGHT(C91,4)),VALUE(MID(SUBSTITUTE(C91,"/","-"),FIND("-",SUBSTITUTE(C91,"/","-"))+1,FIND("-",SUBSTITUTE(C91,"/","-"),FIND("-",SUBSTITUTE(C91,"/","-"))+1)-FIND("-",SUBSTITUTE(C91,"/","-"))-1)),VALUE(LEFT(SUBSTITUTE(C91,"/","-"),FIND("-",SUBSTITUTE(C91,"/","-"))-1)))), DATE(1995,1,1) ) -> 46194
A92: 84 | B92: 2206 | C92: 22-07-2026 | D92: 1584615819 | E92: FAN | F92: Printing and Packaging | G92: 3201010037 | H92: HDPE Poly (L=15``, W=15``, T=0.035mm) | I92: KG | J92: 375 | K92: 104684.93 | L92: 375 | M92: 104684.93 | N92: 0 | O92: 0 | P92: PENDING | Q92: 144 | R92: 46228.398 | AA92: =IFERROR( IF(ISNUMBER(C92),C92,DATE(VALUE(RIGHT(C92,4)),VALUE(MID(SUBSTITUTE(C92,"/","-"),FIND("-",SUBSTITUTE(C92,"/","-"))+1,FIND("-",SUBSTITUTE(C92,"/","-"),FIND("-",SUBSTITUTE(C92,"/","-"))+1)-FIND("-",SUBSTITUTE(C92,"/","-"))-1)),VALUE(LEFT(SUBSTITUTE(C92,"/","-"),FIND("-",SUBSTITUTE(C92,"/","-"))-1)))), DATE(1995,1,1) ) -> 46225
A93: 85 | B93: 2283 | C93: 20-08-2026 | E93: FAN | F93: Printing and Packaging | G93: 3201010037 | H93: HDPE Poly (L=15``, W=15``, T=0.035mm) | I93: KG | J93: 0 | K93: 0 | M93: 0 | N93: 0 | O93: 0 | P93: CHECKED | Q93: 144 | R93: 46260.691 | AA93: =IFERROR( IF(ISNUMBER(C93),C93,DATE(VALUE(RIGHT(C93,4)),VALUE(MID(SUBSTITUTE(C93,"/","-"),FIND("-",SUBSTITUTE(C93,"/","-"))+1,FIND("-",SUBSTITUTE(C93,"/","-"),FIND("-",SUBSTITUTE(C93,"/","-"))+1)-FIND("-",SUBSTITUTE(C93,"/","-"))-1)),VALUE(LEFT(SUBSTITUTE(C93,"/","-"),FIND("-",SUBSTITUTE(C93,"/","-"))-1)))), DATE(1995,1,1) ) -> 46254
A94: 86 | B94: 2117 | C94: 21-06-2026 | D94: 1456414542 | E94: FAN | F94: Printing and Packaging | G94: 3201010038 | H94: HDPE Poly (L=14``, W=12``,T=0.035mm) | I94: KG | J94: 50 | K94: 14435.48 | L94: 31.7 | M94: 9152.09 | N94: 18.3 | O94: 5283.38 | P94: PENDING | Q94: 144 | R94: 46196.36 | AA94: =IFERROR( IF(ISNUMBER(C94),C94,DATE(VALUE(RIGHT(C94,4)),VALUE(MID(SUBSTITUTE(C94,"/","-"),FIND("-",SUBSTITUTE(C94,"/","-"))+1,FIND("-",SUBSTITUTE(C94,"/","-"),FIND("-",SUBSTITUTE(C94,"/","-"))+1)-FIND("-",SUBSTITUTE(C94,"/","-"))-1)),VALUE(LEFT(SUBSTITUTE(C94,"/","-"),FIND("-",SUBSTITUTE(C94,"/","-"))-1)))), DATE(1995,1,1) ) -> 46194
A95: 87 | B95: 2206 | C95: 22-07-2026 | E95: FAN | F95: Printing and Packaging | G95: 3201010038 | H95: HDPE Poly (L=14``, W=12``,T=0.035mm) | I95: KG | J95: 105 | K95: 30314.5 | M95: 0 | N95: 105 | O95: 30314.5 | P95: PENDING | Q95: 144 | R95: 46228.398 | AA95: =IFERROR( IF(ISNUMBER(C95),C95,DATE(VALUE(RIGHT(C95,4)),VALUE(MID(SUBSTITUTE(C95,"/","-"),FIND("-",SUBSTITUTE(C95,"/","-"))+1,FIND("-",SUBSTITUTE(C95,"/","-"),FIND("-",SUBSTITUTE(C95,"/","-"))+1)-FIND("-",SUBSTITUTE(C95,"/","-"))-1)),VALUE(LEFT(SUBSTITUTE(C95,"/","-"),FIND("-",SUBSTITUTE(C95,"/","-"))-1)))), DATE(1995,1,1) ) -> 46225
A96: 88 | B96: 2283 | C96: 20-08-2026 | E96: FAN | F96: Printing and Packaging | G96: 3201010038 | H96: HDPE Poly (L=14``, W=12``,T=0.035mm) | I96: KG | J96: 0 | K96: 0 | M96: 0 | N96: 0 | O96: 0 | P96: CHECKED | Q96: 144 | R96: 46260.691 | AA96: =IFERROR( IF(ISNUMBER(C96),C96,DATE(VALUE(RIGHT(C96,4)),VALUE(MID(SUBSTITUTE(C96,"/","-"),FIND("-",SUBSTITUTE(C96,"/","-"))+1,FIND("-",SUBSTITUTE(C96,"/","-"),FIND("-",SUBSTITUTE(C96,"/","-"))+1)-FIND("-",SUBSTITUTE(C96,"/","-"))-1)),VALUE(LEFT(SUBSTITUTE(C96,"/","-"),FIND("-",SUBSTITUTE(C96,"/","-"))-1)))), DATE(1995,1,1) ) -> 46254
A97: 89 | B97: 2117 | C97: 21-06-2026 | E97: FAN | F97: Printing and Packaging | G97: 3201010039 | H97: HDPE Poly (L=27``, W=8``, T=0.035mm) | I97: KG | J97: 400 | K97: 118605.14 | M97: 0 | N97: 400 | O97: 118605.14 | P97: PENDING | Q97: 144 | R97: 46196.36 | AA97: =IFERROR( IF(ISNUMBER(C97),C97,DATE(VALUE(RIGHT(C97,4)),VALUE(MID(SUBSTITUTE(C97,"/","-"),FIND("-",SUBSTITUTE(C97,"/","-"))+1,FIND("-",SUBSTITUTE(C97,"/","-"),FIND("-",SUBSTITUTE(C97,"/","-"))+1)-FIND("-",SUBSTITUTE(C97,"/","-"))-1)),VALUE(LEFT(SUBSTITUTE(C97,"/","-"),FIND("-",SUBSTITUTE(C97,"/","-"))-1)))), DATE(1995,1,1) ) -> 46194
A98: 90 | B98: 2206 | C98: 22-07-2026 | D98: 158191572615867 | E98: FAN | F98: Printing and Packaging | G98: 3201010039 | H98: HDPE Poly (L=27``, W=8``, T=0.035mm) | I98: KG | J98: 325 | K98: 96366.68 | L98: 126 | M98: 37360.62 | N98: 199 | O98: 59006.06 | P98: PENDING | Q98: 144 | R98: 46228.398 | AA98: =IFERROR( IF(ISNUMBER(C98),C98,DATE(VALUE(RIGHT(C98,4)),VALUE(MID(SUBSTITUTE(C98,"/","-"),FIND("-",SUBSTITUTE(C98,"/","-"))+1,FIND("-",SUBSTITUTE(C98,"/","-"),FIND("-",SUBSTITUTE(C98,"/","-"))+1)-FIND("-",SUBSTITUTE(C98,"/","-"))-1)),VALUE(LEFT(SUBSTITUTE(C98,"/","-"),FIND("-",SUBSTITUTE(C98,"/","-"))-1)))), DATE(1995,1,1) ) -> 46225
A99: 91 | B99: 2283 | C99: 20-08-2026 | E99: FAN | F99: Printing and Packaging | G99: 3201010039 | H99: HDPE Poly (L=27``, W=8``, T=0.035mm) | I99: KG | J99: 0 | K99: 0 | M99: 0 | N99: 0 | O99: 0 | P99: CHECKED | Q99: 144 | R99: 46260.691 | AA99: =IFERROR( IF(ISNUMBER(C99),C99,DATE(VALUE(RIGHT(C99,4)),VALUE(MID(SUBSTITUTE(C99,"/","-"),FIND("-",SUBSTITUTE(C99,"/","-"))+1,FIND("-",SUBSTITUTE(C99,"/","-"),FIND("-",SUBSTITUTE(C99,"/","-"))+1)-FIND("-",SUBSTITUTE(C99,"/","-"))-1)),VALUE(LEFT(SUBSTITUTE(C99,"/","-"),FIND("-",SUBSTITUTE(C99,"/","-"))-1)))), DATE(1995,1,1) ) -> 46254
A100: 92 | B100: 2117 | C100: 21-06-2026 | D100: 15119 | E100: FAN | F100: Printing and Packaging | G100: 3201010040 | H100: HDPE Poly (L=18``, W=7``, T=0.035mm) | I100: KG | J100: 50 | K100: 14540.43 | L100: 50 | M100: 14540.43 | N100: 0 | O100: 0 | P100: PENDING | Q100: 144 | R100: 46196.36 | AA100: =IFERROR( IF(ISNUMBER(C100),C100,DATE(VALUE(RIGHT(C100,4)),VALUE(MID(SUBSTITUTE(C100,"/","-"),FIND("-",SUBSTITUTE(C100,"/","-"))+1,FIND("-",SUBSTITUTE(C100,"/","-"),FIND("-",SUBSTITUTE(C100,"/","-"))+1)-FIND("-",SUBSTITUTE(C100,"/","-"))-1)),VALUE(LEFT(SUBSTITUTE(C100,"/","-"),FIND("-",SUBSTITUTE(C100,"/","-"))-1)))), DATE(1995,1,1) ) -> 46194
...

Sheet Plastic Entry
A1: MEP FAN LIMITED. | AA1: =IFERROR( IF(ISNUMBER(C1),C1,DATE(VALUE(RIGHT(C1,4)),VALUE(MID(SUBSTITUTE(C1,"/","-"),FIND("-",SUBSTITUTE(C1,"/","-"))+1,FIND("-",SUBSTITUTE(C1,"/","-"),FIND("-",SUBSTITUTE(C1,"/","-"))+1)-FIND("-",SUBSTITUTE(C1,"/","-"))-1)),VALUE(LEFT(SUBSTITUTE(C1,"/","-"),FIND("-",SUBSTITUTE(C1,"/","-"))-1)))), DATE(1995,1,1) ) -> 34700
AA2: =IFERROR( IF(ISNUMBER(C2),C2,DATE(VALUE(RIGHT(C2,4)),VALUE(MID(SUBSTITUTE(C2,"/","-"),FIND("-",SUBSTITUTE(C2,"/","-"))+1,FIND("-",SUBSTITUTE(C2,"/","-"),FIND("-",SUBSTITUTE(C2,"/","-"))+1)-FIND("-",SUBSTITUTE(C2,"/","-"))-1)),VALUE(LEFT(SUBSTITUTE(C2,"/","-"),FIND("-",SUBSTITUTE(C2,"/","-"))-1)))), DATE(1995,1,1) ) -> 34700
A3: Inter Sales Requisition Details Report | AA3: =IFERROR( IF(ISNUMBER(C3),C3,DATE(VALUE(RIGHT(C3,4)),VALUE(MID(SUBSTITUTE(C3,"/","-"),FIND("-",SUBSTITUTE(C3,"/","-"))+1,FIND("-",SUBSTITUTE(C3,"/","-"),FIND("-",SUBSTITUTE(C3,"/","-"))+1)-FIND("-",SUBSTITUTE(C3,"/","-"))-1)),VALUE(LEFT(SUBSTITUTE(C3,"/","-"),FIND("-",SUBSTITUTE(C3,"/","-"))-1)))), DATE(1995,1,1) ) -> 34700
AA4: =IFERROR( IF(ISNUMBER(C4),C4,DATE(VALUE(RIGHT(C4,4)),VALUE(MID(SUBSTITUTE(C4,"/","-"),FIND("-",SUBSTITUTE(C4,"/","-"))+1,FIND("-",SUBSTITUTE(C4,"/","-"),FIND("-",SUBSTITUTE(C4,"/","-"))+1)-FIND("-",SUBSTITUTE(C4,"/","-"))-1)),VALUE(LEFT(SUBSTITUTE(C4,"/","-"),FIND("-",SUBSTITUTE(C4,"/","-"))-1)))), DATE(1995,1,1) ) -> 34700
A5: 20-06-2026 To 29-08-2026 | AA5: =IFERROR( IF(ISNUMBER(C5),C5,DATE(VALUE(RIGHT(C5,4)),VALUE(MID(SUBSTITUTE(C5,"/","-"),FIND("-",SUBSTITUTE(C5,"/","-"))+1,FIND("-",SUBSTITUTE(C5,"/","-"),FIND("-",SUBSTITUTE(C5,"/","-"))+1)-FIND("-",SUBSTITUTE(C5,"/","-"))-1)),VALUE(LEFT(SUBSTITUTE(C5,"/","-"),FIND("-",SUBSTITUTE(C5,"/","-"))-1)))), DATE(1995,1,1) ) -> 34700
AA6: =IFERROR( IF(ISNUMBER(C6),C6,DATE(VALUE(RIGHT(C6,4)),VALUE(MID(SUBSTITUTE(C6,"/","-"),FIND("-",SUBSTITUTE(C6,"/","-"))+1,FIND("-",SUBSTITUTE(C6,"/","-"),FIND("-",SUBSTITUTE(C6,"/","-"))+1)-FIND("-",SUBSTITUTE(C6,"/","-"))-1)),VALUE(LEFT(SUBSTITUTE(C6,"/","-"),FIND("-",SUBSTITUTE(C6,"/","-"))-1)))), DATE(1995,1,1) ) -> 34700
A7: Reporting Time: 02:43 PM 29-08-2026 | AA7: =IFERROR( IF(ISNUMBER(C7),C7,DATE(VALUE(RIGHT(C7,4)),VALUE(MID(SUBSTITUTE(C7,"/","-"),FIND("-",SUBSTITUTE(C7,"/","-"))+1,FIND("-",SUBSTITUTE(C7,"/","-"),FIND("-",SUBSTITUTE(C7,"/","-"))+1)-FIND("-",SUBSTITUTE(C7,"/","-"))-1)),VALUE(LEFT(SUBSTITUTE(C7,"/","-"),FIND("-",SUBSTITUTE(C7,"/","-"))-1)))), DATE(1995,1,1) ) -> 34700
A8: S/L | B8: Req No | C8: Req Date | D8: Issue NO | E8: Company (Purchase) | F8: Company (Sales) | G8: Item Code | H8: Item Name | I8: Unit Name | J8: Req Qty | K8: Req Value | L8: Issue Qty | M8: Issue Value | N8: Pending Qty | O8: Pending Value | P8: Status | Q8: Entry By | R8: Entry At | AA8: =IFERROR( IF(ISNUMBER(C8),C8,DATE(VALUE(RIGHT(C8,4)),VALUE(MID(SUBSTITUTE(C8,"/","-"),FIND("-",SUBSTITUTE(C8,"/","-"))+1,FIND("-",SUBSTITUTE(C8,"/","-"),FIND("-",SUBSTITUTE(C8,"/","-"))+1)-FIND("-",SUBSTITUTE(C8,"/","-"))-1)),VALUE(LEFT(SUBSTITUTE(C8,"/","-"),FIND("-",SUBSTITUTE(C8,"/","-"))-1)))), DATE(1995,1,1) ) -> 34700
A9: 1 | B9: 2118 | C9: 21-06-2026 | E9: FAN | F9: MEP | G9: 3101010016 | H9: Super Wire (SWG 33) / 0.253mm | I9: KG | J9: 14000 | K9: 26874577 | M9: 0 | N9: 14000 | O9: 26874577 | P9: PENDING | Q9: 144 | R9: 46196.36 | AA9: =IFERROR( IF(ISNUMBER(C9),C9,DATE(VALUE(RIGHT(C9,4)),VALUE(MID(SUBSTITUTE(C9,"/","-"),FIND("-",SUBSTITUTE(C9,"/","-"))+1,FIND("-",SUBSTITUTE(C9,"/","-"),FIND("-",SUBSTITUTE(C9,"/","-"))+1)-FIND("-",SUBSTITUTE(C9,"/","-"))-1)),VALUE(LEFT(SUBSTITUTE(C9,"/","-"),FIND("-",SUBSTITUTE(C9,"/","-"))-1)))), DATE(1995,1,1) ) -> 46194
A10: 2 | B10: 2209 | C10: 22-07-2026 | E10: FAN | F10: MEP | G10: 3101010016 | H10: Super Wire (SWG 33) / 0.253mm | I10: KG | J10: 11000 | K10: 21115739 | M10: 0 | N10: 11000 | O10: 21115739 | P10: PENDING | Q10: 144 | R10: 46228.357 | AA10: =IFERROR( IF(ISNUMBER(C10),C10,DATE(VALUE(RIGHT(C10,4)),VALUE(MID(SUBSTITUTE(C10,"/","-"),FIND("-",SUBSTITUTE(C10,"/","-"))+1,FIND("-",SUBSTITUTE(C10,"/","-"),FIND("-",SUBSTITUTE(C10,"/","-"))+1)-FIND("-",SUBSTITUTE(C10,"/","-"))-1)),VALUE(LEFT(SUBSTITUTE(C10,"/","-"),FIND("-",SUBSTITUTE(C10,"/","-"))-1)))), DATE(1995,1,1) ) -> 46225
A11: 3 | B11: 2288 | C11: 22-08-2026 | E11: FAN | F11: MEP | G11: 3101010016 | H11: Super Wire (SWG 33) / 0.253mm | I11: KG | J11: 8000 | K11: 15356901 | M11: 0 | N11: 8000 | O11: 15356901 | P11: CHECKED | Q11: 144 | R11: 46260.692 | AA11: =IFERROR( IF(ISNUMBER(C11),C11,DATE(VALUE(RIGHT(C11,4)),VALUE(MID(SUBSTITUTE(C11,"/","-"),FIND("-",SUBSTITUTE(C11,"/","-"))+1,FIND("-",SUBSTITUTE(C11,"/","-"),FIND("-",SUBSTITUTE(C11,"/","-"))+1)-FIND("-",SUBSTITUTE(C11,"/","-"))-1)),VALUE(LEFT(SUBSTITUTE(C11,"/","-"),FIND("-",SUBSTITUTE(C11,"/","-"))-1)))), DATE(1995,1,1) ) -> 46256
A12: 4 | B12: 2209 | C12: 22-07-2026 | E12: FAN | F12: MEP | G12: 3101010017 | H12: Super Wire (SWG 34) / 0.233mm | I12: KG | J12: 1500 | K12: 3046328.5 | M12: 0 | N12: 1500 | O12: 3046328.5 | P12: PENDING | Q12: 144 | R12: 46228.357 | AA12: =IFERROR( IF(ISNUMBER(C12),C12,DATE(VALUE(RIGHT(C12,4)),VALUE(MID(SUBSTITUTE(C12,"/","-"),FIND("-",SUBSTITUTE(C12,"/","-"))+1,FIND("-",SUBSTITUTE(C12,"/","-"),FIND("-",SUBSTITUTE(C12,"/","-"))+1)-FIND("-",SUBSTITUTE(C12,"/","-"))-1)),VALUE(LEFT(SUBSTITUTE(C12,"/","-"),FIND("-",SUBSTITUTE(C12,"/","-"))-1)))), DATE(1995,1,1) ) -> 46225
A13: 5 | B13: 2288 | C13: 22-08-2026 | E13: FAN | F13: MEP | G13: 3101010017 | H13: Super Wire (SWG 34) / 0.233mm | I13: KG | J13: 3000 | K13: 6092657.1 | M13: 0 | N13: 3000 | O13: 6092657.1 | P13: CHECKED | Q13: 144 | R13: 46260.692 | AA13: =IFERROR( IF(ISNUMBER(C13),C13,DATE(VALUE(RIGHT(C13,4)),VALUE(MID(SUBSTITUTE(C13,"/","-"),FIND("-",SUBSTITUTE(C13,"/","-"))+1,FIND("-",SUBSTITUTE(C13,"/","-"),FIND("-",SUBSTITUTE(C13,"/","-"))+1)-FIND("-",SUBSTITUTE(C13,"/","-"))-1)),VALUE(LEFT(SUBSTITUTE(C13,"/","-"),FIND("-",SUBSTITUTE(C13,"/","-"))-1)))), DATE(1995,1,1) ) -> 46256
A14: 6 | B14: 2118 | C14: 21-06-2026 | E14: FAN | F14: MEP | G14: 3101010018 | H14: Super Wire (SWG 35) / 0.213mm | I14: KG | J14: 2000 | K14: 2486567.2 | M14: 0 | N14: 2000 | O14: 2486567.2 | P14: PENDING | Q14: 144 | R14: 46196.36 | AA14: =IFERROR( IF(ISNUMBER(C14),C14,DATE(VALUE(RIGHT(C14,4)),VALUE(MID(SUBSTITUTE(C14,"/","-"),FIND("-",SUBSTITUTE(C14,"/","-"))+1,FIND("-",SUBSTITUTE(C14,"/","-"),FIND("-",SUBSTITUTE(C14,"/","-"))+1)-FIND("-",SUBSTITUTE(C14,"/","-"))-1)),VALUE(LEFT(SUBSTITUTE(C14,"/","-"),FIND("-",SUBSTITUTE(C14,"/","-"))-1)))), DATE(1995,1,1) ) -> 46194
A15: 7 | B15: 2209 | C15: 22-07-2026 | E15: FAN | F15: MEP | G15: 3101010018 | H15: Super Wire (SWG 35) / 0.213mm | I15: KG | J15: 2500 | K15: 3108209 | M15: 0 | N15: 2500 | O15: 3108209 | P15: PENDING | Q15: 144 | R15: 46228.357 | AA15: =IFERROR( IF(ISNUMBER(C15),C15,DATE(VALUE(RIGHT(C15,4)),VALUE(MID(SUBSTITUTE(C15,"/","-"),FIND("-",SUBSTITUTE(C15,"/","-"))+1,FIND("-",SUBSTITUTE(C15,"/","-"),FIND("-",SUBSTITUTE(C15,"/","-"))+1)-FIND("-",SUBSTITUTE(C15,"/","-"))-1)),VALUE(LEFT(SUBSTITUTE(C15,"/","-"),FIND("-",SUBSTITUTE(C15,"/","-"))-1)))), DATE(1995,1,1) ) -> 46225
A16: 8 | B16: 2288 | C16: 22-08-2026 | E16: FAN | F16: MEP | G16: 3101010018 | H16: Super Wire (SWG 35) / 0.213mm | I16: KG | J16: 3000 | K16: 3729850.8 | M16: 0 | N16: 3000 | O16: 3729850.8 | P16: CHECKED | Q16: 144 | R16: 46260.692 | AA16: =IFERROR( IF(ISNUMBER(C16),C16,DATE(VALUE(RIGHT(C16,4)),VALUE(MID(SUBSTITUTE(C16,"/","-"),FIND("-",SUBSTITUTE(C16,"/","-"))+1,FIND("-",SUBSTITUTE(C16,"/","-"),FIND("-",SUBSTITUTE(C16,"/","-"))+1)-FIND("-",SUBSTITUTE(C16,"/","-"))-1)),VALUE(LEFT(SUBSTITUTE(C16,"/","-"),FIND("-",SUBSTITUTE(C16,"/","-"))-1)))), DATE(1995,1,1) ) -> 46256
A17: 9 | B17: 2116 | C17: 21-06-2026 | D17: 1526714869 | E17: FAN | F17: MEP | G17: 3101010070 | H17: Ms Washer 3/16 (1910/kg) | I17: KG | J17: 24 | K17: 8639.55 | L17: 18.8 | M17: 6767.65 | N17: 5.2 | O17: 1871.9 | P17: PENDING | Q17: 144 | R17: 46196.359 | AA17: =IFERROR( IF(ISNUMBER(C17),C17,DATE(VALUE(RIGHT(C17,4)),VALUE(MID(SUBSTITUTE(C17,"/","-"),FIND("-",SUBSTITUTE(C17,"/","-"))+1,FIND("-",SUBSTITUTE(C17,"/","-"),FIND("-",SUBSTITUTE(C17,"/","-"))+1)-FIND("-",SUBSTITUTE(C17,"/","-"))-1)),VALUE(LEFT(SUBSTITUTE(C17,"/","-"),FIND("-",SUBSTITUTE(C17,"/","-"))-1)))), DATE(1995,1,1) ) -> 46194
A18: 10 | B18: 2203 | C18: 22-07-2026 | D18: 15788 | E18: FAN | F18: MEP | G18: 3101010070 | H18: Ms Washer 3/16 (1910/kg) | I18: KG | J18: 22 | K18: 7919.59 | L18: 10.4 | M18: 3743.8 | N18: 11.6 | O18: 4175.78 | P18: PENDING | Q18: 144 | R18: 46228.355 | AA18: =IFERROR( IF(ISNUMBER(C18),C18,DATE(VALUE(RIGHT(C18,4)),VALUE(MID(SUBSTITUTE(C18,"/","-"),FIND("-",SUBSTITUTE(C18,"/","-"))+1,FIND("-",SUBSTITUTE(C18,"/","-"),FIND("-",SUBSTITUTE(C18,"/","-"))+1)-FIND("-",SUBSTITUTE(C18,"/","-"))-1)),VALUE(LEFT(SUBSTITUTE(C18,"/","-"),FIND("-",SUBSTITUTE(C18,"/","-"))-1)))), DATE(1995,1,1) ) -> 46225
A19: 11 | B19: 2287 | C19: 22-08-2026 | E19: FAN | F19: MEP | G19: 3101010070 | H19: Ms Washer 3/16 (1910/kg) | I19: KG | J19: 15 | K19: 5399.72 | M19: 0 | N19: 15 | O19: 5399.72 | P19: CHECKED | Q19: 144 | R19: 46260.691 | AA19: =IFERROR( IF(ISNUMBER(C19),C19,DATE(VALUE(RIGHT(C19,4)),VALUE(MID(SUBSTITUTE(C19,"/","-"),FIND("-",SUBSTITUTE(C19,"/","-"))+1,FIND("-",SUBSTITUTE(C19,"/","-"),FIND("-",SUBSTITUTE(C19,"/","-"))+1)-FIND("-",SUBSTITUTE(C19,"/","-"))-1)),VALUE(LEFT(SUBSTITUTE(C19,"/","-"),FIND("-",SUBSTITUTE(C19,"/","-"))-1)))), DATE(1995,1,1) ) -> 46256
A20: 12 | B20: 2116 | C20: 21-06-2026 | D20: 1.4789147e+99 | E20: FAN | F20: MEP | G20: 3101010071 | H20: Down Pipe Bolt 8mm x 1.5```` (50/kg) | I20: Pcs | J20: 130200 | K20: 387203.48 | L20: 91802 | M20: 273011.16 | N20: 38398 | O20: 114192.31 | P20: PENDING | Q20: 144 | R20: 46196.359 | AA20: =IFERROR( IF(ISNUMBER(C20),C20,DATE(VALUE(RIGHT(C20,4)),VALUE(MID(SUBSTITUTE(C20,"/","-"),FIND("-",SUBSTITUTE(C20,"/","-"))+1,FIND("-",SUBSTITUTE(C20,"/","-"),FIND("-",SUBSTITUTE(C20,"/","-"))+1)-FIND("-",SUBSTITUTE(C20,"/","-"))-1)),VALUE(LEFT(SUBSTITUTE(C20,"/","-"),FIND("-",SUBSTITUTE(C20,"/","-"))-1)))), DATE(1995,1,1) ) -> 46194
A21: 13 | B21: 2203 | C21: 22-07-2026 | D21: 1.5594158e+94 | E21: FAN | F21: MEP | G21: 3101010071 | H21: Down Pipe Bolt 8mm x 1.5```` (50/kg) | I21: Pcs | J21: 120750 | K21: 359100 | L21: 75795 | M21: 225407.74 | N21: 44955 | O21: 133692.26 | P21: PENDING | Q21: 144 | R21: 46228.355 | AA21: =IFERROR( IF(ISNUMBER(C21),C21,DATE(VALUE(RIGHT(C21,4)),VALUE(MID(SUBSTITUTE(C21,"/","-"),FIND("-",SUBSTITUTE(C21,"/","-"))+1,FIND("-",SUBSTITUTE(C21,"/","-"),FIND("-",SUBSTITUTE(C21,"/","-"))+1)-FIND("-",SUBSTITUTE(C21,"/","-"))-1)),VALUE(LEFT(SUBSTITUTE(C21,"/","-"),FIND("-",SUBSTITUTE(C21,"/","-"))-1)))), DATE(1995,1,1) ) -> 46225
A22: 14 | B22: 2287 | C22: 22-08-2026 | E22: FAN | F22: MEP | G22: 3101010071 | H22: Down Pipe Bolt 8mm x 1.5```` (50/kg) | I22: Pcs | J22: 84000 | K22: 249808.7 | M22: 0 | N22: 84000 | O22: 249808.7 | P22: CHECKED | Q22: 144 | R22: 46260.691 | AA22: =IFERROR( IF(ISNUMBER(C22),C22,DATE(VALUE(RIGHT(C22,4)),VALUE(MID(SUBSTITUTE(C22,"/","-"),FIND("-",SUBSTITUTE(C22,"/","-"))+1,FIND("-",SUBSTITUTE(C22,"/","-"),FIND("-",SUBSTITUTE(C22,"/","-"))+1)-FIND("-",SUBSTITUTE(C22,"/","-"))-1)),VALUE(LEFT(SUBSTITUTE(C22,"/","-"),FIND("-",SUBSTITUTE(C22,"/","-"))-1)))), DATE(1995,1,1) ) -> 46256
A23: 15 | B23: 2116 | C23: 21-06-2026 | D23: 151951515415225 | E23: FAN | F23: MEP | G23: 3101010072 | H23: Down Pipe Bolt 8mm x 2```` (45/kg) | I23: Pcs | J23: 5775 | K23: 20036.74 | L23: 3457.8 | M23: 11997.06 | N23: 2317.2 | O23: 8039.68 | P23: PENDING | Q23: 144 | R23: 46196.359 | AA23: =IFERROR( IF(ISNUMBER(C23),C23,DATE(VALUE(RIGHT(C23,4)),VALUE(MID(SUBSTITUTE(C23,"/","-"),FIND("-",SUBSTITUTE(C23,"/","-"))+1,FIND("-",SUBSTITUTE(C23,"/","-"),FIND("-",SUBSTITUTE(C23,"/","-"))+1)-FIND("-",SUBSTITUTE(C23,"/","-"))-1)),VALUE(LEFT(SUBSTITUTE(C23,"/","-"),FIND("-",SUBSTITUTE(C23,"/","-"))-1)))), DATE(1995,1,1) ) -> 46194
A24: 16 | B24: 2203 | C24: 22-07-2026 | D24: 15365 | E24: FAN | F24: MEP | G24: 3101010072 | H24: Down Pipe Bolt 8mm x 2```` (45/kg) | I24: Pcs | J24: 10500 | K24: 36430.43 | L24: 9526 | M24: 33051.08 | N24: 974 | O24: 3379.36 | P24: PENDING | Q24: 144 | R24: 46228.355 | AA24: =IFERROR( IF(ISNUMBER(C24),C24,DATE(VALUE(RIGHT(C24,4)),VALUE(MID(SUBSTITUTE(C24,"/","-"),FIND("-",SUBSTITUTE(C24,"/","-"))+1,FIND("-",SUBSTITUTE(C24,"/","-"),FIND("-",SUBSTITUTE(C24,"/","-"))+1)-FIND("-",SUBSTITUTE(C24,"/","-"))-1)),VALUE(LEFT(SUBSTITUTE(C24,"/","-"),FIND("-",SUBSTITUTE(C24,"/","-"))-1)))), DATE(1995,1,1) ) -> 46225
A25: 17 | B25: 2287 | C25: 22-08-2026 | E25: FAN | F25: MEP | G25: 3101010072 | H25: Down Pipe Bolt 8mm x 2```` (45/kg) | I25: Pcs | J25: 21000 | K25: 72860.87 | M25: 0 | N25: 21000 | O25: 72860.87 | P25: CHECKED | Q25: 144 | R25: 46260.691 | AA25: =IFERROR( IF(ISNUMBER(C25),C25,DATE(VALUE(RIGHT(C25,4)),VALUE(MID(SUBSTITUTE(C25,"/","-"),FIND("-",SUBSTITUTE(C25,"/","-"))+1,FIND("-",SUBSTITUTE(C25,"/","-"),FIND("-",SUBSTITUTE(C25,"/","-"))+1)-FIND("-",SUBSTITUTE(C25,"/","-"))-1)),VALUE(LEFT(SUBSTITUTE(C25,"/","-"),FIND("-",SUBSTITUTE(C25,"/","-"))-1)))), DATE(1995,1,1) ) -> 46256
A26: 18 | B26: 2116 | C26: 21-06-2026 | D26: 146501513115034 | E26: FAN | F26: MEP | G26: 3101010073 | H26: Down Pipe Sira Pin(Fan) | I26: Pcs | J26: 136500 | K26: 23739.13 | L26: 136500 | M26: 23739.13 | N26: 0 | O26: 0 | P26: PENDING | Q26: 144 | R26: 46196.359 | AA26: =IFERROR( IF(ISNUMBER(C26),C26,DATE(VALUE(RIGHT(C26,4)),VALUE(MID(SUBSTITUTE(C26,"/","-"),FIND("-",SUBSTITUTE(C26,"/","-"))+1,FIND("-",SUBSTITUTE(C26,"/","-"),FIND("-",SUBSTITUTE(C26,"/","-"))+1)-FIND("-",SUBSTITUTE(C26,"/","-"))-1)),VALUE(LEFT(SUBSTITUTE(C26,"/","-"),FIND("-",SUBSTITUTE(C26,"/","-"))-1)))), DATE(1995,1,1) ) -> 46194
A27: 19 | B27: 2203 | C27: 22-07-2026 | D27: 1.5487157e+24 | E27: FAN | F27: MEP | G27: 3101010073 | H27: Down Pipe Sira Pin(Fan) | I27: Pcs | J27: 131250 | K27: 22826.09 | L27: 131249 | M27: 22825.91 | N27: 1 | O27: 0.17 | P27: PENDING | Q27: 144 | R27: 46228.355 | AA27: =IFERROR( IF(ISNUMBER(C27),C27,DATE(VALUE(RIGHT(C27,4)),VALUE(MID(SUBSTITUTE(C27,"/","-"),FIND("-",SUBSTITUTE(C27,"/","-"))+1,FIND("-",SUBSTITUTE(C27,"/","-"),FIND("-",SUBSTITUTE(C27,"/","-"))+1)-FIND("-",SUBSTITUTE(C27,"/","-"))-1)),VALUE(LEFT(SUBSTITUTE(C27,"/","-"),FIND("-",SUBSTITUTE(C27,"/","-"))-1)))), DATE(1995,1,1) ) -> 46225
A28: 20 | B28: 2287 | C28: 22-08-2026 | E28: FAN | F28: MEP | G28: 3101010073 | H28: Down Pipe Sira Pin(Fan) | I28: Pcs | J28: 70000 | K28: 12173.91 | M28: 0 | N28: 70000 | O28: 12173.91 | P28: CHECKED | Q28: 144 | R28: 46260.691 | AA28: =IFERROR( IF(ISNUMBER(C28),C28,DATE(VALUE(RIGHT(C28,4)),VALUE(MID(SUBSTITUTE(C28,"/","-"),FIND("-",SUBSTITUTE(C28,"/","-"))+1,FIND("-",SUBSTITUTE(C28,"/","-"),FIND("-",SUBSTITUTE(C28,"/","-"))+1)-FIND("-",SUBSTITUTE(C28,"/","-"))-1)),VALUE(LEFT(SUBSTITUTE(C28,"/","-"),FIND("-",SUBSTITUTE(C28,"/","-"))-1)))), DATE(1995,1,1) ) -> 46256
A29: 21 | B29: 2116 | C29: 21-06-2026 | D29: 1.4901153e+24 | E29: FAN | F29: MEP | G29: 3101010074 | H29: Shaft/XL /Safity lock Screw 3/16x3/8```` (400/kg) | I29: KG | J29: 176 | K29: 30800 | L29: 126.9 | M29: 22207.5 | N29: 49.1 | O29: 8592.5 | P29: PENDING | Q29: 144 | R29: 46196.359 | AA29: =IFERROR( IF(ISNUMBER(C29),C29,DATE(VALUE(RIGHT(C29,4)),VALUE(MID(SUBSTITUTE(C29,"/","-"),FIND("-",SUBSTITUTE(C29,"/","-"))+1,FIND("-",SUBSTITUTE(C29,"/","-"),FIND("-",SUBSTITUTE(C29,"/","-"))+1)-FIND("-",SUBSTITUTE(C29,"/","-"))-1)),VALUE(LEFT(SUBSTITUTE(C29,"/","-"),FIND("-",SUBSTITUTE(C29,"/","-"))-1)))), DATE(1995,1,1) ) -> 46194
A30: 22 | B30: 2203 | C30: 22-07-2026 | D30: 1.5686156e+19 | E30: FAN | F30: MEP | G30: 3101010074 | H30: Shaft/XL /Safity lock Screw 3/16x3/8```` (400/kg) | I30: KG | J30: 168 | K30: 29400 | L30: 160.2 | M30: 28035 | N30: 7.8 | O30: 1365 | P30: PENDING | Q30: 144 | R30: 46228.355 | AA30: =IFERROR( IF(ISNUMBER(C30),C30,DATE(VALUE(RIGHT(C30,4)),VALUE(MID(SUBSTITUTE(C30,"/","-"),FIND("-",SUBSTITUTE(C30,"/","-"))+1,FIND("-",SUBSTITUTE(C30,"/","-"),FIND("-",SUBSTITUTE(C30,"/","-"))+1)-FIND("-",SUBSTITUTE(C30,"/","-"))-1)),VALUE(LEFT(SUBSTITUTE(C30,"/","-"),FIND("-",SUBSTITUTE(C30,"/","-"))-1)))), DATE(1995,1,1) ) -> 46225
A31: 23 | B31: 2287 | C31: 22-08-2026 | E31: FAN | F31: MEP | G31: 3101010074 | H31: Shaft/XL /Safity lock Screw 3/16x3/8```` (400/kg) | I31: KG | J31: 126 | K31: 22050 | M31: 0 | N31: 126 | O31: 22050 | P31: CHECKED | Q31: 144 | R31: 46260.691 | AA31: =IFERROR( IF(ISNUMBER(C31),C31,DATE(VALUE(RIGHT(C31,4)),VALUE(MID(SUBSTITUTE(C31,"/","-"),FIND("-",SUBSTITUTE(C31,"/","-"))+1,FIND("-",SUBSTITUTE(C31,"/","-"),FIND("-",SUBSTITUTE(C31,"/","-"))+1)-FIND("-",SUBSTITUTE(C31,"/","-"))-1)),VALUE(LEFT(SUBSTITUTE(C31,"/","-"),FIND("-",SUBSTITUTE(C31,"/","-"))-1)))), DATE(1995,1,1) ) -> 46256
A32: 24 | B32: 2116 | C32: 21-06-2026 | D32: 14731 | E32: FAN | F32: MEP | G32: 3101010075 | H32: Body Screw 18x6mm,H=10mm (200/kg) | I32: KG | J32: 30 | K32: 5250.15 | L32: 20.2 | M32: 3535.1 | N32: 9.8 | O32: 1715.05 | P32: PENDING | Q32: 144 | R32: 46196.359 | AA32: =IFERROR( IF(ISNUMBER(C32),C32,DATE(VALUE(RIGHT(C32,4)),VALUE(MID(SUBSTITUTE(C32,"/","-"),FIND("-",SUBSTITUTE(C32,"/","-"))+1,FIND("-",SUBSTITUTE(C32,"/","-"),FIND("-",SUBSTITUTE(C32,"/","-"))+1)-FIND("-",SUBSTITUTE(C32,"/","-"))-1)),VALUE(LEFT(SUBSTITUTE(C32,"/","-"),FIND("-",SUBSTITUTE(C32,"/","-"))-1)))), DATE(1995,1,1) ) -> 46194
A33: 25 | B33: 2203 | C33: 22-07-2026 | D33: 158251585415872 | E33: FAN | F33: MEP | G33: 3101010075 | H33: Body Screw 18x6mm,H=10mm (200/kg) | I33: KG | J33: 84 | K33: 14700.43 | L33: 84 | M33: 14700.43 | N33: 0 | O33: 0 | P33: PENDING | Q33: 144 | R33: 46228.355 | AA33: =IFERROR( IF(ISNUMBER(C33),C33,DATE(VALUE(RIGHT(C33,4)),VALUE(MID(SUBSTITUTE(C33,"/","-"),FIND("-",SUBSTITUTE(C33,"/","-"))+1,FIND("-",SUBSTITUTE(C33,"/","-"),FIND("-",SUBSTITUTE(C33,"/","-"))+1)-FIND("-",SUBSTITUTE(C33,"/","-"))-1)),VALUE(LEFT(SUBSTITUTE(C33,"/","-"),FIND("-",SUBSTITUTE(C33,"/","-"))-1)))), DATE(1995,1,1) ) -> 46225
A34: 26 | B34: 2287 | C34: 22-08-2026 | E34: FAN | F34: MEP | G34: 3101010075 | H34: Body Screw 18x6mm,H=10mm (200/kg) | I34: KG | J34: 20 | K34: 3500.1 | M34: 0 | N34: 20 | O34: 3500.1 | P34: CHECKED | Q34: 144 | R34: 46260.691 | AA34: =IFERROR( IF(ISNUMBER(C34),C34,DATE(VALUE(RIGHT(C34,4)),VALUE(MID(SUBSTITUTE(C34,"/","-"),FIND("-",SUBSTITUTE(C34,"/","-"))+1,FIND("-",SUBSTITUTE(C34,"/","-"),FIND("-",SUBSTITUTE(C34,"/","-"))+1)-FIND("-",SUBSTITUTE(C34,"/","-"))-1)),VALUE(LEFT(SUBSTITUTE(C34,"/","-"),FIND("-",SUBSTITUTE(C34,"/","-"))-1)))), DATE(1995,1,1) ) -> 46256
A35: 27 | B35: 2287 | C35: 22-08-2026 | E35: FAN | F35: MEP | G35: 3101010076 | H35: Body Screw 15x6mm,H=10mm (230/kg) | I35: KG | J35: 168 | K35: 29400 | M35: 0 | N35: 168 | O35: 29400 | P35: CHECKED | Q35: 144 | R35: 46260.691 | AA35: =IFERROR( IF(ISNUMBER(C35),C35,DATE(VALUE(RIGHT(C35,4)),VALUE(MID(SUBSTITUTE(C35,"/","-"),FIND("-",SUBSTITUTE(C35,"/","-"))+1,FIND("-",SUBSTITUTE(C35,"/","-"),FIND("-",SUBSTITUTE(C35,"/","-"))+1)-FIND("-",SUBSTITUTE(C35,"/","-"))-1)),VALUE(LEFT(SUBSTITUTE(C35,"/","-"),FIND("-",SUBSTITUTE(C35,"/","-"))-1)))), DATE(1995,1,1) ) -> 46256
A36: 28 | B36: 2116 | C36: 21-06-2026 | D36: 1.4756152e+99 | E36: FAN | F36: MEP | G36: 3101010077 | H36: Blade/Body Screw 12.7x6mm,H=10mm (220/kg) | I36: KG | J36: 1749 | K36: 306009.55 | L36: 1651.5 | M36: 288950.7 | N36: 97.5 | O36: 17058.85 | P36: PENDING | Q36: 144 | R36: 46196.359 | AA36: =IFERROR( IF(ISNUMBER(C36),C36,DATE(VALUE(RIGHT(C36,4)),VALUE(MID(SUBSTITUTE(C36,"/","-"),FIND("-",SUBSTITUTE(C36,"/","-"))+1,FIND("-",SUBSTITUTE(C36,"/","-"),FIND("-",SUBSTITUTE(C36,"/","-"))+1)-FIND("-",SUBSTITUTE(C36,"/","-"))-1)),VALUE(LEFT(SUBSTITUTE(C36,"/","-"),FIND("-",SUBSTITUTE(C36,"/","-"))-1)))), DATE(1995,1,1) ) -> 46194
A37: 29 | B37: 2203 | C37: 22-07-2026 | D37: 1.5809159e+99 | E37: FAN | F37: MEP | G37: 3101010077 | H37: Blade/Body Screw 12.7x6mm,H=10mm (220/kg) | I37: KG | J37: 1500 | K37: 262443.87 | L37: 1335.2 | M37: 233610.04 | N37: 164.8 | O37: 28833.83 | P37: PENDING | Q37: 144 | R37: 46228.355 | AA37: =IFERROR( IF(ISNUMBER(C37),C37,DATE(VALUE(RIGHT(C37,4)),VALUE(MID(SUBSTITUTE(C37,"/","-"),FIND("-",SUBSTITUTE(C37,"/","-"))+1,FIND("-",SUBSTITUTE(C37,"/","-"),FIND("-",SUBSTITUTE(C37,"/","-"))+1)-FIND("-",SUBSTITUTE(C37,"/","-"))-1)),VALUE(LEFT(SUBSTITUTE(C37,"/","-"),FIND("-",SUBSTITUTE(C37,"/","-"))-1)))), DATE(1995,1,1) ) -> 46225
A38: 30 | B38: 2287 | C38: 22-08-2026 | E38: FAN | F38: MEP | G38: 3101010077 | H38: Blade/Body Screw 12.7x6mm,H=10mm (220/kg) | I38: KG | J38: 1380 | K38: 241448.36 | M38: 0 | N38: 1380 | O38: 241448.36 | P38: CHECKED | Q38: 144 | R38: 46260.691 | AA38: =IFERROR( IF(ISNUMBER(C38),C38,DATE(VALUE(RIGHT(C38,4)),VALUE(MID(SUBSTITUTE(C38,"/","-"),FIND("-",SUBSTITUTE(C38,"/","-"))+1,FIND("-",SUBSTITUTE(C38,"/","-"),FIND("-",SUBSTITUTE(C38,"/","-"))+1)-FIND("-",SUBSTITUTE(C38,"/","-"))-1)),VALUE(LEFT(SUBSTITUTE(C38,"/","-"),FIND("-",SUBSTITUTE(C38,"/","-"))-1)))), DATE(1995,1,1) ) -> 46256
A39: 31 | B39: 2115 | C39: 21-06-2026 | D39: 1.5280154e+34 | E39: FAN | F39: MEP | G39: 3101010078 | H39: Canopy Big | I39: Pcs | J39: 93450 | K39: 962941.3 | L39: 28410 | M39: 292746.52 | N39: 65040 | O39: 670194.78 | P39: PENDING | Q39: 144 | R39: 46196.359 | AA39: =IFERROR( IF(ISNUMBER(C39),C39,DATE(VALUE(RIGHT(C39,4)),VALUE(MID(SUBSTITUTE(C39,"/","-"),FIND("-",SUBSTITUTE(C39,"/","-"))+1,FIND("-",SUBSTITUTE(C39,"/","-"),FIND("-",SUBSTITUTE(C39,"/","-"))+1)-FIND("-",SUBSTITUTE(C39,"/","-"))-1)),VALUE(LEFT(SUBSTITUTE(C39,"/","-"),FIND("-",SUBSTITUTE(C39,"/","-"))-1)))), DATE(1995,1,1) ) -> 46194
A40: 32 | B40: 2202 | C40: 22-07-2026 | D40: 1.5582158e+69 | E40: FAN | F40: MEP | G40: 3101010078 | H40: Canopy Big | I40: Pcs | J40: 94500 | K40: 973760.87 | L40: 86435 | M40: 890656.3 | N40: 8065 | O40: 83104.57 | P40: PENDING | Q40: 144 | R40: 46228.355 | AA40: =IFERROR( IF(ISNUMBER(C40),C40,DATE(VALUE(RIGHT(C40,4)),VALUE(MID(SUBSTITUTE(C40,"/","-"),FIND("-",SUBSTITUTE(C40,"/","-"))+1,FIND("-",SUBSTITUTE(C40,"/","-"),FIND("-",SUBSTITUTE(C40,"/","-"))+1)-FIND("-",SUBSTITUTE(C40,"/","-"))-1)),VALUE(LEFT(SUBSTITUTE(C40,"/","-"),FIND("-",SUBSTITUTE(C40,"/","-"))-1)))), DATE(1995,1,1) ) -> 46225
A41: 33 | B41: 2285 | C41: 22-08-2026 | E41: FAN | F41: MEP | G41: 3101010078 | H41: Canopy Big | I41: Pcs | J41: 84000 | K41: 865565.22 | M41: 0 | N41: 84000 | O41: 865565.22 | P41: CHECKED | Q41: 144 | R41: 46260.691 | AA41: =IFERROR( IF(ISNUMBER(C41),C41,DATE(VALUE(RIGHT(C41,4)),VALUE(MID(SUBSTITUTE(C41,"/","-"),FIND("-",SUBSTITUTE(C41,"/","-"))+1,FIND("-",SUBSTITUTE(C41,"/","-"),FIND("-",SUBSTITUTE(C41,"/","-"))+1)-FIND("-",SUBSTITUTE(C41,"/","-"))-1)),VALUE(LEFT(SUBSTITUTE(C41,"/","-"),FIND("-",SUBSTITUTE(C41,"/","-"))-1)))), DATE(1995,1,1) ) -> 46256
A42: 34 | B42: 2115 | C42: 21-06-2026 | D42: 153461469215313 | E42: FAN | F42: MEP | G42: 3101010080 | H42: Capacitor Cover | I42: Pcs | J42: 46725 | K42: 43880.87 | L42: 26686 | M42: 25061.63 | N42: 20039 | O42: 18819.23 | P42: PENDING | Q42: 144 | R42: 46196.359 | AA42: =IFERROR( IF(ISNUMBER(C42),C42,DATE(VALUE(RIGHT(C42,4)),VALUE(MID(SUBSTITUTE(C42,"/","-"),FIND("-",SUBSTITUTE(C42,"/","-"))+1,FIND("-",SUBSTITUTE(C42,"/","-"),FIND("-",SUBSTITUTE(C42,"/","-"))+1)-FIND("-",SUBSTITUTE(C42,"/","-"))-1)),VALUE(LEFT(SUBSTITUTE(C42,"/","-"),FIND("-",SUBSTITUTE(C42,"/","-"))-1)))), DATE(1995,1,1) ) -> 46194
A43: 35 | B43: 2202 | C43: 22-07-2026 | D43: 15915 | E43: FAN | F43: MEP | G43: 3101010080 | H43: Capacitor Cover | I43: Pcs | J43: 47250 | K43: 44373.91 | L43: 20300 | M43: 19064.35 | N43: 26950 | O43: 25309.57 | P43: PENDING | Q43: 144 | R43: 46228.355 | AA43: =IFERROR( IF(ISNUMBER(C43),C43,DATE(VALUE(RIGHT(C43,4)),VALUE(MID(SUBSTITUTE(C43,"/","-"),FIND("-",SUBSTITUTE(C43,"/","-"))+1,FIND("-",SUBSTITUTE(C43,"/","-"),FIND("-",SUBSTITUTE(C43,"/","-"))+1)-FIND("-",SUBSTITUTE(C43,"/","-"))-1)),VALUE(LEFT(SUBSTITUTE(C43,"/","-"),FIND("-",SUBSTITUTE(C43,"/","-"))-1)))), DATE(1995,1,1) ) -> 46225
A44: 36 | B44: 2285 | C44: 22-08-2026 | E44: FAN | F44: MEP | G44: 3101010080 | H44: Capacitor Cover | I44: Pcs | J44: 42000 | K44: 39443.48 | M44: 0 | N44: 42000 | O44: 39443.48 | P44: CHECKED | Q44: 144 | R44: 46260.691 | AA44: =IFERROR( IF(ISNUMBER(C44),C44,DATE(VALUE(RIGHT(C44,4)),VALUE(MID(SUBSTITUTE(C44,"/","-"),FIND("-",SUBSTITUTE(C44,"/","-"))+1,FIND("-",SUBSTITUTE(C44,"/","-"),FIND("-",SUBSTITUTE(C44,"/","-"))+1)-FIND("-",SUBSTITUTE(C44,"/","-"))-1)),VALUE(LEFT(SUBSTITUTE(C44,"/","-"),FIND("-",SUBSTITUTE(C44,"/","-"))-1)))), DATE(1995,1,1) ) -> 46256
A45: 37 | B45: 2115 | C45: 21-06-2026 | D45: 146921481014890 | E45: FAN | F45: MEP | G45: 3101010081 | H45: Rubber Gasket (56`` 48``) | I45: Pcs | J45: 126000 | K45: 42730.43 | L45: 27348 | M45: 9274.54 | N45: 98652 | O45: 33455.9 | P45: PENDING | Q45: 144 | R45: 46196.359 | AA45: =IFERROR( IF(ISNUMBER(C45),C45,DATE(VALUE(RIGHT(C45,4)),VALUE(MID(SUBSTITUTE(C45,"/","-"),FIND("-",SUBSTITUTE(C45,"/","-"))+1,FIND("-",SUBSTITUTE(C45,"/","-"),FIND("-",SUBSTITUTE(C45,"/","-"))+1)-FIND("-",SUBSTITUTE(C45,"/","-"))-1)),VALUE(LEFT(SUBSTITUTE(C45,"/","-"),FIND("-",SUBSTITUTE(C45,"/","-"))-1)))), DATE(1995,1,1) ) -> 46194
A46: 38 | B46: 2202 | C46: 22-07-2026 | D46: 159151558315462 | E46: FAN | F46: MEP | G46: 3101010081 | H46: Rubber Gasket (56`` 48``) | I46: Pcs | J46: 110250 | K46: 37389.13 | L46: 87900 | M46: 29809.56 | N46: 22350 | O46: 7579.57 | P46: PENDING | Q46: 144 | R46: 46228.355 | AA46: =IFERROR( IF(ISNUMBER(C46),C46,DATE(VALUE(RIGHT(C46,4)),VALUE(MID(SUBSTITUTE(C46,"/","-"),FIND("-",SUBSTITUTE(C46,"/","-"))+1,FIND("-",SUBSTITUTE(C46,"/","-"),FIND("-",SUBSTITUTE(C46,"/","-"))+1)-FIND("-",SUBSTITUTE(C46,"/","-"))-1)),VALUE(LEFT(SUBSTITUTE(C46,"/","-"),FIND("-",SUBSTITUTE(C46,"/","-"))-1)))), DATE(1995,1,1) ) -> 46225
A47: 39 | B47: 2285 | C47: 22-08-2026 | E47: FAN | F47: MEP | G47: 3101010081 | H47: Rubber Gasket (56`` 48``) | I47: Pcs | J47: 63000 | K47: 21365.22 | M47: 0 | N47: 63000 | O47: 21365.22 | P47: CHECKED | Q47: 144 | R47: 46260.691 | AA47: =IFERROR( IF(ISNUMBER(C47),C47,DATE(VALUE(RIGHT(C47,4)),VALUE(MID(SUBSTITUTE(C47,"/","-"),FIND("-",SUBSTITUTE(C47,"/","-"))+1,FIND("-",SUBSTITUTE(C47,"/","-"),FIND("-",SUBSTITUTE(C47,"/","-"))+1)-FIND("-",SUBSTITUTE(C47,"/","-"))-1)),VALUE(LEFT(SUBSTITUTE(C47,"/","-"),FIND("-",SUBSTITUTE(C47,"/","-"))-1)))), DATE(1995,1,1) ) -> 46256
A48: 40 | B48: 2115 | C48: 21-06-2026 | E48: FAN | F48: MEP | G48: 3101010083 | H48: Rubber Gasket (2401,3601) | I48: Pcs | J48: 21000 | K48: 5295.6 | M48: 0 | N48: 21000 | O48: 5295.6 | P48: PENDING | Q48: 144 | R48: 46196.359 | AA48: =IFERROR( IF(ISNUMBER(C48),C48,DATE(VALUE(RIGHT(C48,4)),VALUE(MID(SUBSTITUTE(C48,"/","-"),FIND("-",SUBSTITUTE(C48,"/","-"))+1,FIND("-",SUBSTITUTE(C48,"/","-"),FIND("-",SUBSTITUTE(C48,"/","-"))+1)-FIND("-",SUBSTITUTE(C48,"/","-"))-1)),VALUE(LEFT(SUBSTITUTE(C48,"/","-"),FIND("-",SUBSTITUTE(C48,"/","-"))-1)))), DATE(1995,1,1) ) -> 46194
A49: 41 | B49: 2202 | C49: 22-07-2026 | E49: FAN | F49: MEP | G49: 3101010083 | H49: Rubber Gasket (2401,3601) | I49: Pcs | J49: 36750 | K49: 9267.29 | M49: 0 | N49: 36750 | O49: 9267.29 | P49: PENDING | Q49: 144 | R49: 46228.355 | AA49: =IFERROR( IF(ISNUMBER(C49),C49,DATE(VALUE(RIGHT(C49,4)),VALUE(MID(SUBSTITUTE(C49,"/","-"),FIND("-",SUBSTITUTE(C49,"/","-"))+1,FIND("-",SUBSTITUTE(C49,"/","-"),FIND("-",SUBSTITUTE(C49,"/","-"))+1)-FIND("-",SUBSTITUTE(C49,"/","-"))-1)),VALUE(LEFT(SUBSTITUTE(C49,"/","-"),FIND("-",SUBSTITUTE(C49,"/","-"))-1)))), DATE(1995,1,1) ) -> 46225
A50: 42 | B50: 2285 | C50: 22-08-2026 | E50: FAN | F50: MEP | G50: 3101010083 | H50: Rubber Gasket (2401,3601) | I50: Pcs | J50: 31500 | K50: 7943.39 | M50: 0 | N50: 31500 | O50: 7943.39 | P50: CHECKED | Q50: 144 | R50: 46260.691 | AA50: =IFERROR( IF(ISNUMBER(C50),C50,DATE(VALUE(RIGHT(C50,4)),VALUE(MID(SUBSTITUTE(C50,"/","-"),FIND("-",SUBSTITUTE(C50,"/","-"))+1,FIND("-",SUBSTITUTE(C50,"/","-"),FIND("-",SUBSTITUTE(C50,"/","-"))+1)-FIND("-",SUBSTITUTE(C50,"/","-"))-1)),VALUE(LEFT(SUBSTITUTE(C50,"/","-"),FIND("-",SUBSTITUTE(C50,"/","-"))-1)))), DATE(1995,1,1) ) -> 46256
A51: 43 | B51: 2115 | C51: 21-06-2026 | E51: FAN | F51: MEP | G51: 3101010084 | H51: Plastic XL Cap | I51: Pcs | J51: 46725 | K51: 9345 | M51: 0 | N51: 46725 | O51: 9345 | P51: PENDING | Q51: 144 | R51: 46196.359 | AA51: =IFERROR( IF(ISNUMBER(C51),C51,DATE(VALUE(RIGHT(C51,4)),VALUE(MID(SUBSTITUTE(C51,"/","-"),FIND("-",SUBSTITUTE(C51,"/","-"))+1,FIND("-",SUBSTITUTE(C51,"/","-"),FIND("-",SUBSTITUTE(C51,"/","-"))+1)-FIND("-",SUBSTITUTE(C51,"/","-"))-1)),VALUE(LEFT(SUBSTITUTE(C51,"/","-"),FIND("-",SUBSTITUTE(C51,"/","-"))-1)))), DATE(1995,1,1) ) -> 46194
A52: 44 | B52: 2202 | C52: 22-07-2026 | D52: 154711550515915 | E52: FAN | F52: MEP | G52: 3101010084 | H52: Plastic XL Cap | I52: Pcs | J52: 47250 | K52: 9450 | L52: 41302 | M52: 8260.4 | N52: 5948 | O52: 1189.6 | P52: PENDING | Q52: 144 | R52: 46228.355 | AA52: =IFERROR( IF(ISNUMBER(C52),C52,DATE(VALUE(RIGHT(C52,4)),VALUE(MID(SUBSTITUTE(C52,"/","-"),FIND("-",SUBSTITUTE(C52,"/","-"))+1,FIND("-",SUBSTITUTE(C52,"/","-"),FIND("-",SUBSTITUTE(C52,"/","-"))+1)-FIND("-",SUBSTITUTE(C52,"/","-"))-1)),VALUE(LEFT(SUBSTITUTE(C52,"/","-"),FIND("-",SUBSTITUTE(C52,"/","-"))-1)))), DATE(1995,1,1) ) -> 46225
A53: 45 | B53: 2285 | C53: 22-08-2026 | E53: FAN | F53: MEP | G53: 3101010084 | H53: Plastic XL Cap | I53: Pcs | J53: 42000 | K53: 8400 | M53: 0 | N53: 42000 | O53: 8400 | P53: CHECKED | Q53: 144 | R53: 46260.691 | AA53: =IFERROR( IF(ISNUMBER(C53),C53,DATE(VALUE(RIGHT(C53,4)),VALUE(MID(SUBSTITUTE(C53,"/","-"),FIND("-",SUBSTITUTE(C53,"/","-"))+1,FIND("-",SUBSTITUTE(C53,"/","-"),FIND("-",SUBSTITUTE(C53,"/","-"))+1)-FIND("-",SUBSTITUTE(C53,"/","-"))-1)),VALUE(LEFT(SUBSTITUTE(C53,"/","-"),FIND("-",SUBSTITUTE(C53,"/","-"))-1)))), DATE(1995,1,1) ) -> 46256
A54: 46 | B54: 2115 | C54: 21-06-2026 | D54: 1537815345 | E54: FAN | F54: MEP | G54: 3101010085 | H54: Insulation Rubber | I54: Pcs | J54: 40000 | K54: 93913.05 | L54: 15150 | M54: 35569.57 | N54: 24850 | O54: 58343.48 | P54: PENDING | Q54: 144 | R54: 46196.359 | AA54: =IFERROR( IF(ISNUMBER(C54),C54,DATE(VALUE(RIGHT(C54,4)),VALUE(MID(SUBSTITUTE(C54,"/","-"),FIND("-",SUBSTITUTE(C54,"/","-"))+1,FIND("-",SUBSTITUTE(C54,"/","-"),FIND("-",SUBSTITUTE(C54,"/","-"))+1)-FIND("-",SUBSTITUTE(C54,"/","-"))-1)),VALUE(LEFT(SUBSTITUTE(C54,"/","-"),FIND("-",SUBSTITUTE(C54,"/","-"))-1)))), DATE(1995,1,1) ) -> 46194
A55: 47 | B55: 2202 | C55: 22-07-2026 | D55: 15583 | E55: FAN | F55: MEP | G55: 3101010085 | H55: Insulation Rubber | I55: Pcs | J55: 20000 | K55: 46956.52 | L55: 20000 | M55: 46956.52 | N55: 0 | O55: 0 | P55: PENDING | Q55: 144 | R55: 46228.355 | AA55: =IFERROR( IF(ISNUMBER(C55),C55,DATE(VALUE(RIGHT(C55,4)),VALUE(MID(SUBSTITUTE(C55,"/","-"),FIND("-",SUBSTITUTE(C55,"/","-"))+1,FIND("-",SUBSTITUTE(C55,"/","-"),FIND("-",SUBSTITUTE(C55,"/","-"))+1)-FIND("-",SUBSTITUTE(C55,"/","-"))-1)),VALUE(LEFT(SUBSTITUTE(C55,"/","-"),FIND("-",SUBSTITUTE(C55,"/","-"))-1)))), DATE(1995,1,1) ) -> 46225
A56: 48 | B56: 2285 | C56: 22-08-2026 | E56: FAN | F56: MEP | G56: 3101010085 | H56: Insulation Rubber | I56: Pcs | J56: 42000 | K56: 98608.7 | M56: 0 | N56: 42000 | O56: 98608.7 | P56: CHECKED | Q56: 144 | R56: 46260.691 | AA56: =IFERROR( IF(ISNUMBER(C56),C56,DATE(VALUE(RIGHT(C56,4)),VALUE(MID(SUBSTITUTE(C56,"/","-"),FIND("-",SUBSTITUTE(C56,"/","-"))+1,FIND("-",SUBSTITUTE(C56,"/","-"),FIND("-",SUBSTITUTE(C56,"/","-"))+1)-FIND("-",SUBSTITUTE(C56,"/","-"))-1)),VALUE(LEFT(SUBSTITUTE(C56,"/","-"),FIND("-",SUBSTITUTE(C56,"/","-"))-1)))), DATE(1995,1,1) ) -> 46256
A57: 49 | B57: 2115 | C57: 21-06-2026 | D57: 1.5378153e+19 | E57: FAN | F57: MEP | G57: 3101010086 | H57: Canopy Rubber Ring | I57: Pcs | J57: 93450 | K57: 60945.68 | L57: 18748 | M57: 12226.96 | N57: 74702 | O57: 48718.71 | P57: PENDING | Q57: 144 | R57: 46196.359 | AA57: =IFERROR( IF(ISNUMBER(C57),C57,DATE(VALUE(RIGHT(C57,4)),VALUE(MID(SUBSTITUTE(C57,"/","-"),FIND("-",SUBSTITUTE(C57,"/","-"))+1,FIND("-",SUBSTITUTE(C57,"/","-"),FIND("-",SUBSTITUTE(C57,"/","-"))+1)-FIND("-",SUBSTITUTE(C57,"/","-"))-1)),VALUE(LEFT(SUBSTITUTE(C57,"/","-"),FIND("-",SUBSTITUTE(C57,"/","-"))-1)))), DATE(1995,1,1) ) -> 46194
A58: 50 | B58: 2202 | C58: 22-07-2026 | D58: 1.5462157e+19 | E58: FAN | F58: MEP | G58: 3101010086 | H58: Canopy Rubber Ring | I58: Pcs | J58: 94500 | K58: 61630.46 | L58: 74652 | M58: 48686.11 | N58: 19848 | O58: 12944.35 | P58: PENDING | Q58: 144 | R58: 46228.355 | AA58: =IFERROR( IF(ISNUMBER(C58),C58,DATE(VALUE(RIGHT(C58,4)),VALUE(MID(SUBSTITUTE(C58,"/","-"),FIND("-",SUBSTITUTE(C58,"/","-"))+1,FIND("-",SUBSTITUTE(C58,"/","-"),FIND("-",SUBSTITUTE(C58,"/","-"))+1)-FIND("-",SUBSTITUTE(C58,"/","-"))-1)),VALUE(LEFT(SUBSTITUTE(C58,"/","-"),FIND("-",SUBSTITUTE(C58,"/","-"))-1)))), DATE(1995,1,1) ) -> 46225
A59: 51 | B59: 2285 | C59: 22-08-2026 | E59: FAN | F59: MEP | G59: 3101010086 | H59: Canopy Rubber Ring | I59: Pcs | J59: 84000 | K59: 54782.63 | M59: 0 | N59: 84000 | O59: 54782.63 | P59: CHECKED | Q59: 144 | R59: 46260.691 | AA59: =IFERROR( IF(ISNUMBER(C59),C59,DATE(VALUE(RIGHT(C59,4)),VALUE(MID(SUBSTITUTE(C59,"/","-"),FIND("-",SUBSTITUTE(C59,"/","-"))+1,FIND("-",SUBSTITUTE(C59,"/","-"),FIND("-",SUBSTITUTE(C59,"/","-"))+1)-FIND("-",SUBSTITUTE(C59,"/","-"))-1)),VALUE(LEFT(SUBSTITUTE(C59,"/","-"),FIND("-",SUBSTITUTE(C59,"/","-"))-1)))), DATE(1995,1,1) ) -> 46256
A60: 52 | B60: 2118 | C60: 21-06-2026 | D60: 1511615206 | E60: FAN | F60: MEP | G60: 3101010090 | H60: Flaxible Cable 14x0.0076 - Red | I60: Mtr | J60: 43500 | K60: 444279.53 | L60: 39700 | M60: 405468.91 | N60: 3800 | O60: 38810.63 | P60: PENDING | Q60: 144 | R60: 46196.36 | AA60: =IFERROR( IF(ISNUMBER(C60),C60,DATE(VALUE(RIGHT(C60,4)),VALUE(MID(SUBSTITUTE(C60,"/","-"),FIND("-",SUBSTITUTE(C60,"/","-"))+1,FIND("-",SUBSTITUTE(C60,"/","-"),FIND("-",SUBSTITUTE(C60,"/","-"))+1)-FIND("-",SUBSTITUTE(C60,"/","-"))-1)),VALUE(LEFT(SUBSTITUTE(C60,"/","-"),FIND("-",SUBSTITUTE(C60,"/","-"))-1)))), DATE(1995,1,1) ) -> 46194
A61: 53 | B61: 2209 | C61: 22-07-2026 | D61: 1559915372 | E61: FAN | F61: MEP | G61: 3101010090 | H61: Flaxible Cable 14x0.0076 - Red | I61: Mtr | J61: 43200 | K61: 441215.54 | L61: 29100 | M61: 297207.69 | N61: 14100 | O61: 144007.85 | P61: PENDING | Q61: 144 | R61: 46228.357 | AA61: =IFERROR( IF(ISNUMBER(C61),C61,DATE(VALUE(RIGHT(C61,4)),VALUE(MID(SUBSTITUTE(C61,"/","-"),FIND("-",SUBSTITUTE(C61,"/","-"))+1,FIND("-",SUBSTITUTE(C61,"/","-"),FIND("-",SUBSTITUTE(C61,"/","-"))+1)-FIND("-",SUBSTITUTE(C61,"/","-"))-1)),VALUE(LEFT(SUBSTITUTE(C61,"/","-"),FIND("-",SUBSTITUTE(C61,"/","-"))-1)))), DATE(1995,1,1) ) -> 46225
A62: 54 | B62: 2288 | C62: 22-08-2026 | E62: FAN | F62: MEP | G62: 3101010090 | H62: Flaxible Cable 14x0.0076 - Red | I62: Mtr | J62: 38400 | K62: 392191.59 | M62: 0 | N62: 38400 | O62: 392191.59 | P62: CHECKED | Q62: 144 | R62: 46260.692 | AA62: =IFERROR( IF(ISNUMBER(C62),C62,DATE(VALUE(RIGHT(C62,4)),VALUE(MID(SUBSTITUTE(C62,"/","-"),FIND("-",SUBSTITUTE(C62,"/","-"))+1,FIND("-",SUBSTITUTE(C62,"/","-"),FIND("-",SUBSTITUTE(C62,"/","-"))+1)-FIND("-",SUBSTITUTE(C62,"/","-"))-1)),VALUE(LEFT(SUBSTITUTE(C62,"/","-"),FIND("-",SUBSTITUTE(C62,"/","-"))-1)))), DATE(1995,1,1) ) -> 46256
A63: 55 | B63: 2119 | C63: 21-06-2026 | D63: 1.4839154e+94 | E63: FAN | F63: MEP | G63: 3101010107 | H63: Nice Regulator Small White(FAN) | I63: Pcs | J63: 50000 | K63: 2670869.6 | L63: 47667 | M63: 2546246.8 | N63: 2333 | O63: 124622.77 | P63: PENDING | Q63: 144 | R63: 46196.36 | AA63: =IFERROR( IF(ISNUMBER(C63),C63,DATE(VALUE(RIGHT(C63,4)),VALUE(MID(SUBSTITUTE(C63,"/","-"),FIND("-",SUBSTITUTE(C63,"/","-"))+1,FIND("-",SUBSTITUTE(C63,"/","-"),FIND("-",SUBSTITUTE(C63,"/","-"))+1)-FIND("-",SUBSTITUTE(C63,"/","-"))-1)),VALUE(LEFT(SUBSTITUTE(C63,"/","-"),FIND("-",SUBSTITUTE(C63,"/","-"))-1)))), DATE(1995,1,1) ) -> 46194
A64: 56 | B64: 2204 | C64: 22-07-2026 | D64: 1.5575156e+29 | E64: FAN | F64: MEP | G64: 3101010107 | H64: Nice Regulator Small White(FAN) | I64: Pcs | J64: 50000 | K64: 2670869.6 | L64: 26500 | M64: 1415560.9 | N64: 23500 | O64: 1255308.7 | P64: PENDING | Q64: 144 | R64: 46228.355 | AA64: =IFERROR( IF(ISNUMBER(C64),C64,DATE(VALUE(RIGHT(C64,4)),VALUE(MID(SUBSTITUTE(C64,"/","-"),FIND("-",SUBSTITUTE(C64,"/","-"))+1,FIND("-",SUBSTITUTE(C64,"/","-"),FIND("-",SUBSTITUTE(C64,"/","-"))+1)-FIND("-",SUBSTITUTE(C64,"/","-"))-1)),VALUE(LEFT(SUBSTITUTE(C64,"/","-"),FIND("-",SUBSTITUTE(C64,"/","-"))-1)))), DATE(1995,1,1) ) -> 46225
A65: 57 | B65: 2286 | C65: 22-08-2026 | E65: FAN | F65: MEP | G65: 3101010107 | H65: Nice Regulator Small White(FAN) | I65: Pcs | J65: 40000 | K65: 2136695.6 | M65: 0 | N65: 40000 | O65: 2136695.6 | P65: CHECKED | Q65: 144 | R65: 46260.691 | AA65: =IFERROR( IF(ISNUMBER(C65),C65,DATE(VALUE(RIGHT(C65,4)),VALUE(MID(SUBSTITUTE(C65,"/","-"),FIND("-",SUBSTITUTE(C65,"/","-"))+1,FIND("-",SUBSTITUTE(C65,"/","-"),FIND("-",SUBSTITUTE(C65,"/","-"))+1)-FIND("-",SUBSTITUTE(C65,"/","-"))-1)),VALUE(LEFT(SUBSTITUTE(C65,"/","-"),FIND("-",SUBSTITUTE(C65,"/","-"))-1)))), DATE(1995,1,1) ) -> 46256
A66: 58 | B66: 2285 | C66: 22-08-2026 | E66: FAN | F66: MEP | G66: 3101010110 | H66: Rubber Gasket (5602) | I66: Pcs | J66: 31500 | K66: 7943.1 | M66: 0 | N66: 31500 | O66: 7943.1 | P66: CHECKED | Q66: 144 | R66: 46260.691 | AA66: =IFERROR( IF(ISNUMBER(C66),C66,DATE(VALUE(RIGHT(C66,4)),VALUE(MID(SUBSTITUTE(C66,"/","-"),FIND("-",SUBSTITUTE(C66,"/","-"))+1,FIND("-",SUBSTITUTE(C66,"/","-"),FIND("-",SUBSTITUTE(C66,"/","-"))+1)-FIND("-",SUBSTITUTE(C66,"/","-"))-1)),VALUE(LEFT(SUBSTITUTE(C66,"/","-"),FIND("-",SUBSTITUTE(C66,"/","-"))-1)))), DATE(1995,1,1) ) -> 46256
A67: 59 | B67: 2118 | C67: 21-06-2026 | D67: 15652 | E67: FAN | F67: MEP | G67: 3101010111 | H67: Flaxible Cable 14x0.0076 - Yellow | I67: Mtr | J67: 14700 | K67: 149919.66 | L67: 1600 | M67: 16317.79 | N67: 13100 | O67: 133601.87 | P67: PENDING | Q67: 144 | R67: 46196.36 | AA67: =IFERROR( IF(ISNUMBER(C67),C67,DATE(VALUE(RIGHT(C67,4)),VALUE(MID(SUBSTITUTE(C67,"/","-"),FIND("-",SUBSTITUTE(C67,"/","-"))+1,FIND("-",SUBSTITUTE(C67,"/","-"),FIND("-",SUBSTITUTE(C67,"/","-"))+1)-FIND("-",SUBSTITUTE(C67,"/","-"))-1)),VALUE(LEFT(SUBSTITUTE(C67,"/","-"),FIND("-",SUBSTITUTE(C67,"/","-"))-1)))), DATE(1995,1,1) ) -> 46194
A68: 60 | B68: 2209 | C68: 22-07-2026 | D68: 1563815651 | E68: FAN | F68: MEP | G68: 3101010111 | H68: Flaxible Cable 14x0.0076 - Yellow | I68: Mtr | J68: 14400 | K68: 146860.07 | L68: 14400 | M68: 146860.07 | N68: 0 | O68: 0 | P68: PENDING | Q68: 144 | R68: 46228.357 | AA68: =IFERROR( IF(ISNUMBER(C68),C68,DATE(VALUE(RIGHT(C68,4)),VALUE(MID(SUBSTITUTE(C68,"/","-"),FIND("-",SUBSTITUTE(C68,"/","-"))+1,FIND("-",SUBSTITUTE(C68,"/","-"),FIND("-",SUBSTITUTE(C68,"/","-"))+1)-FIND("-",SUBSTITUTE(C68,"/","-"))-1)),VALUE(LEFT(SUBSTITUTE(C68,"/","-"),FIND("-",SUBSTITUTE(C68,"/","-"))-1)))), DATE(1995,1,1) ) -> 46225
A69: 61 | B69: 2288 | C69: 22-08-2026 | E69: FAN | F69: MEP | G69: 3101010111 | H69: Flaxible Cable 14x0.0076 - Yellow | I69: Mtr | J69: 12900 | K69: 131562.15 | M69: 0 | N69: 12900 | O69: 131562.15 | P69: CHECKED | Q69: 144 | R69: 46260.692 | AA69: =IFERROR( IF(ISNUMBER(C69),C69,DATE(VALUE(RIGHT(C69,4)),VALUE(MID(SUBSTITUTE(C69,"/","-"),FIND("-",SUBSTITUTE(C69,"/","-"))+1,FIND("-",SUBSTITUTE(C69,"/","-"),FIND("-",SUBSTITUTE(C69,"/","-"))+1)-FIND("-",SUBSTITUTE(C69,"/","-"))-1)),VALUE(LEFT(SUBSTITUTE(C69,"/","-"),FIND("-",SUBSTITUTE(C69,"/","-"))-1)))), DATE(1995,1,1) ) -> 46256
A70: 62 | B70: 2118 | C70: 21-06-2026 | D70: 1.4712152e+24 | E70: FAN | F70: MEP | G70: 3101010112 | H70: Flaxible Cable 14x0.0076 - Black | I70: Mtr | J70: 43500 | K70: 443822 | L70: 33600 | M70: 342814.23 | N70: 9900 | O70: 101007.76 | P70: PENDING | Q70: 144 | R70: 46196.36 | AA70: =IFERROR( IF(ISNUMBER(C70),C70,DATE(VALUE(RIGHT(C70,4)),VALUE(MID(SUBSTITUTE(C70,"/","-"),FIND("-",SUBSTITUTE(C70,"/","-"))+1,FIND("-",SUBSTITUTE(C70,"/","-"),FIND("-",SUBSTITUTE(C70,"/","-"))+1)-FIND("-",SUBSTITUTE(C70,"/","-"))-1)),VALUE(LEFT(SUBSTITUTE(C70,"/","-"),FIND("-",SUBSTITUTE(C70,"/","-"))-1)))), DATE(1995,1,1) ) -> 46194
A71: 63 | B71: 2209 | C71: 22-07-2026 | D71: 155991569115372 | E71: FAN | F71: MEP | G71: 3101010112 | H71: Flaxible Cable 14x0.0076 - Black | I71: Mtr | J71: 43200 | K71: 440761.16 | L71: 43200 | M71: 440761.16 | N71: 0 | O71: 0 | P71: PENDING | Q71: 144 | R71: 46228.357 | AA71: =IFERROR( IF(ISNUMBER(C71),C71,DATE(VALUE(RIGHT(C71,4)),VALUE(MID(SUBSTITUTE(C71,"/","-"),FIND("-",SUBSTITUTE(C71,"/","-"))+1,FIND("-",SUBSTITUTE(C71,"/","-"),FIND("-",SUBSTITUTE(C71,"/","-"))+1)-FIND("-",SUBSTITUTE(C71,"/","-"))-1)),VALUE(LEFT(SUBSTITUTE(C71,"/","-"),FIND("-",SUBSTITUTE(C71,"/","-"))-1)))), DATE(1995,1,1) ) -> 46225
A72: 64 | B72: 2288 | C72: 22-08-2026 | E72: FAN | F72: MEP | G72: 3101010112 | H72: Flaxible Cable 14x0.0076 - Black | I72: Mtr | J72: 38400 | K72: 391787.69 | M72: 0 | N72: 38400 | O72: 391787.69 | P72: CHECKED | Q72: 144 | R72: 46260.692 | AA72: =IFERROR( IF(ISNUMBER(C72),C72,DATE(VALUE(RIGHT(C72,4)),VALUE(MID(SUBSTITUTE(C72,"/","-"),FIND("-",SUBSTITUTE(C72,"/","-"))+1,FIND("-",SUBSTITUTE(C72,"/","-"),FIND("-",SUBSTITUTE(C72,"/","-"))+1)-FIND("-",SUBSTITUTE(C72,"/","-"))-1)),VALUE(LEFT(SUBSTITUTE(C72,"/","-"),FIND("-",SUBSTITUTE(C72,"/","-"))-1)))), DATE(1995,1,1) ) -> 46256
A73: 65 | B73: 2260 | C73: 46364 | D73: 15868 | E73: FAN | F73: MEP | G73: 3101010119 | H73: Promotional Gang Regulator White (P512) | I73: Pcs | J73: 2000 | K73: 115356.52 | L73: 785 | M73: 45277.43 | N73: 1215 | O73: 70079.09 | P73: PENDING | Q73: 144 | R73: 46250.338 | AA73: =IFERROR( IF(ISNUMBER(C73),C73,DATE(VALUE(RIGHT(C73,4)),VALUE(MID(SUBSTITUTE(C73,"/","-"),FIND("-",SUBSTITUTE(C73,"/","-"))+1,FIND("-",SUBSTITUTE(C73,"/","-"),FIND("-",SUBSTITUTE(C73,"/","-"))+1)-FIND("-",SUBSTITUTE(C73,"/","-"))-1)),VALUE(LEFT(SUBSTITUTE(C73,"/","-"),FIND("-",SUBSTITUTE(C73,"/","-"))-1)))), DATE(1995,1,1) ) -> 46364
A74: 66 | B74: 2203 | C74: 22-07-2026 | E74: FAN | F74: MEP | G74: 3101010130 | H74: Body screw- 3/16`` x 35mm | I74: KG | J74: 20 | K74: 3730.01 | M74: 0 | N74: 20 | O74: 3730.01 | P74: PENDING | Q74: 144 | R74: 46228.355 | AA74: =IFERROR( IF(ISNUMBER(C74),C74,DATE(VALUE(RIGHT(C74,4)),VALUE(MID(SUBSTITUTE(C74,"/","-"),FIND("-",SUBSTITUTE(C74,"/","-"))+1,FIND("-",SUBSTITUTE(C74,"/","-"),FIND("-",SUBSTITUTE(C74,"/","-"))+1)-FIND("-",SUBSTITUTE(C74,"/","-"))-1)),VALUE(LEFT(SUBSTITUTE(C74,"/","-"),FIND("-",SUBSTITUTE(C74,"/","-"))-1)))), DATE(1995,1,1) ) -> 46225
A75: 67 | B75: 2110 | C75: 20-06-2026 | E75: FAN | F75: MEP | G75: 3102010001 | H75: Exhaust Fan Base (8``) | I75: Pcs | J75: 3200 | K75: 158413.91 | M75: 0 | N75: 3200 | O75: 158413.91 | P75: PENDING | Q75: 144 | R75: 46193.793 | AA75: =IFERROR( IF(ISNUMBER(C75),C75,DATE(VALUE(RIGHT(C75,4)),VALUE(MID(SUBSTITUTE(C75,"/","-"),FIND("-",SUBSTITUTE(C75,"/","-"))+1,FIND("-",SUBSTITUTE(C75,"/","-"),FIND("-",SUBSTITUTE(C75,"/","-"))+1)-FIND("-",SUBSTITUTE(C75,"/","-"))-1)),VALUE(LEFT(SUBSTITUTE(C75,"/","-"),FIND("-",SUBSTITUTE(C75,"/","-"))-1)))), DATE(1995,1,1) ) -> 46193
A76: 68 | B76: 2114 | C76: 21-06-2026 | D76: 1.5046151e+24 | E76: FAN | F76: MEP | G76: 3102010001 | H76: Exhaust Fan Base (8``) | I76: Pcs | J76: 6200 | K76: 306926.96 | L76: 3941 | M76: 195096.63 | N76: 2259 | O76: 111830.32 | P76: PENDING | Q76: 144 | R76: 46196.359 | AA76: =IFERROR( IF(ISNUMBER(C76),C76,DATE(VALUE(RIGHT(C76,4)),VALUE(MID(SUBSTITUTE(C76,"/","-"),FIND("-",SUBSTITUTE(C76,"/","-"))+1,FIND("-",SUBSTITUTE(C76,"/","-"),FIND("-",SUBSTITUTE(C76,"/","-"))+1)-FIND("-",SUBSTITUTE(C76,"/","-"))-1)),VALUE(LEFT(SUBSTITUTE(C76,"/","-"),FIND("-",SUBSTITUTE(C76,"/","-"))-1)))), DATE(1995,1,1) ) -> 46194
A77: 69 | B77: 2211 | C77: 22-07-2026 | D77: 1.5639157e+19 | E77: FAN | F77: MEP | G77: 3102010001 | H77: Exhaust Fan Base (8``) | I77: Pcs | J77: 5500 | K77: 272273.91 | L77: 3860 | M77: 191086.78 | N77: 1640 | O77: 81187.13 | P77: PENDING | Q77: 144 | R77: 46228.357 | AA77: =IFERROR( IF(ISNUMBER(C77),C77,DATE(VALUE(RIGHT(C77,4)),VALUE(MID(SUBSTITUTE(C77,"/","-"),FIND("-",SUBSTITUTE(C77,"/","-"))+1,FIND("-",SUBSTITUTE(C77,"/","-"),FIND("-",SUBSTITUTE(C77,"/","-"))+1)-FIND("-",SUBSTITUTE(C77,"/","-"))-1)),VALUE(LEFT(SUBSTITUTE(C77,"/","-"),FIND("-",SUBSTITUTE(C77,"/","-"))-1)))), DATE(1995,1,1) ) -> 46225
A78: 70 | B78: 2291 | C78: 22-08-2026 | E78: FAN | F78: MEP | G78: 3102010001 | H78: Exhaust Fan Base (8``) | I78: Pcs | J78: 5775 | K78: 285887.61 | M78: 0 | N78: 5775 | O78: 285887.61 | P78: CHECKED | Q78: 144 | R78: 46260.692 | AA78: =IFERROR( IF(ISNUMBER(C78),C78,DATE(VALUE(RIGHT(C78,4)),VALUE(MID(SUBSTITUTE(C78,"/","-"),FIND("-",SUBSTITUTE(C78,"/","-"))+1,FIND("-",SUBSTITUTE(C78,"/","-"),FIND("-",SUBSTITUTE(C78,"/","-"))+1)-FIND("-",SUBSTITUTE(C78,"/","-"))-1)),VALUE(LEFT(SUBSTITUTE(C78,"/","-"),FIND("-",SUBSTITUTE(C78,"/","-"))-1)))), DATE(1995,1,1) ) -> 46256
A79: 71 | B79: 2110 | C79: 20-06-2026 | E79: FAN | F79: MEP | G79: 3102010002 | H79: Exhaust Fan Cover (8``) | I79: Pcs | J79: 3200 | K79: 105585.12 | M79: 0 | N79: 3200 | O79: 105585.12 | P79: PENDING | Q79: 144 | R79: 46193.793 | AA79: =IFERROR( IF(ISNUMBER(C79),C79,DATE(VALUE(RIGHT(C79,4)),VALUE(MID(SUBSTITUTE(C79,"/","-"),FIND("-",SUBSTITUTE(C79,"/","-"))+1,FIND("-",SUBSTITUTE(C79,"/","-"),FIND("-",SUBSTITUTE(C79,"/","-"))+1)-FIND("-",SUBSTITUTE(C79,"/","-"))-1)),VALUE(LEFT(SUBSTITUTE(C79,"/","-"),FIND("-",SUBSTITUTE(C79,"/","-"))-1)))), DATE(1995,1,1) ) -> 46193
A80: 72 | B80: 2114 | C80: 21-06-2026 | D80: 1.528115e+34 | E80: FAN | F80: MEP | G80: 3102010002 | H80: Exhaust Fan Cover (8``) | I80: Pcs | J80: 6200 | K80: 204571.18 | L80: 5008 | M80: 165240.72 | N80: 1192 | O80: 39330.46 | P80: PENDING | Q80: 144 | R80: 46196.359 | AA80: =IFERROR( IF(ISNUMBER(C80),C80,DATE(VALUE(RIGHT(C80,4)),VALUE(MID(SUBSTITUTE(C80,"/","-"),FIND("-",SUBSTITUTE(C80,"/","-"))+1,FIND("-",SUBSTITUTE(C80,"/","-"),FIND("-",SUBSTITUTE(C80,"/","-"))+1)-FIND("-",SUBSTITUTE(C80,"/","-"))-1)),VALUE(LEFT(SUBSTITUTE(C80,"/","-"),FIND("-",SUBSTITUTE(C80,"/","-"))-1)))), DATE(1995,1,1) ) -> 46194
A81: 73 | B81: 2211 | C81: 22-07-2026 | D81: 1.5669158e+19 | E81: FAN | F81: MEP | G81: 3102010002 | H81: Exhaust Fan Cover (8``) | I81: Pcs | J81: 5500 | K81: 181474.43 | L81: 4461 | M81: 147192.26 | N81: 1039 | O81: 34282.17 | P81: PENDING | Q81: 144 | R81: 46228.357 | AA81: =IFERROR( IF(ISNUMBER(C81),C81,DATE(VALUE(RIGHT(C81,4)),VALUE(MID(SUBSTITUTE(C81,"/","-"),FIND("-",SUBSTITUTE(C81,"/","-"))+1,FIND("-",SUBSTITUTE(C81,"/","-"),FIND("-",SUBSTITUTE(C81,"/","-"))+1)-FIND("-",SUBSTITUTE(C81,"/","-"))-1)),VALUE(LEFT(SUBSTITUTE(C81,"/","-"),FIND("-",SUBSTITUTE(C81,"/","-"))-1)))), DATE(1995,1,1) ) -> 46225
A82: 74 | B82: 2291 | C82: 22-08-2026 | E82: FAN | F82: MEP | G82: 3102010002 | H82: Exhaust Fan Cover (8``) | I82: Pcs | J82: 5775 | K82: 190548.15 | M82: 0 | N82: 5775 | O82: 190548.15 | P82: CHECKED | Q82: 144 | R82: 46260.692 | AA82: =IFERROR( IF(ISNUMBER(C82),C82,DATE(VALUE(RIGHT(C82,4)),VALUE(MID(SUBSTITUTE(C82,"/","-"),FIND("-",SUBSTITUTE(C82,"/","-"))+1,FIND("-",SUBSTITUTE(C82,"/","-"),FIND("-",SUBSTITUTE(C82,"/","-"))+1)-FIND("-",SUBSTITUTE(C82,"/","-"))-1)),VALUE(LEFT(SUBSTITUTE(C82,"/","-"),FIND("-",SUBSTITUTE(C82,"/","-"))-1)))), DATE(1995,1,1) ) -> 46256
A83: 75 | B83: 2110 | C83: 20-06-2026 | D83: 1.4995152e+19 | E83: FAN | F83: MEP | G83: 3102010003 | H83: Exhaust Fan Shutter (8``) | I83: Pcs | J83: 10000 | K83: 33477.69 | L83: 7352 | M83: 24612.8 | N83: 2648 | O83: 8864.89 | P83: PENDING | Q83: 144 | R83: 46193.793 | AA83: =IFERROR( IF(ISNUMBER(C83),C83,DATE(VALUE(RIGHT(C83,4)),VALUE(MID(SUBSTITUTE(C83,"/","-"),FIND("-",SUBSTITUTE(C83,"/","-"))+1,FIND("-",SUBSTITUTE(C83,"/","-"),FIND("-",SUBSTITUTE(C83,"/","-"))+1)-FIND("-",SUBSTITUTE(C83,"/","-"))-1)),VALUE(LEFT(SUBSTITUTE(C83,"/","-"),FIND("-",SUBSTITUTE(C83,"/","-"))-1)))), DATE(1995,1,1) ) -> 46193
A84: 76 | B84: 2114 | C84: 21-06-2026 | D84: 14993 | E84: FAN | F84: MEP | G84: 3102010003 | H84: Exhaust Fan Shutter (8``) | I84: Pcs | J84: 19 | K84: 63.61 | L84: 19 | M84: 63.61 | N84: 0 | O84: 0 | P84: PENDING | Q84: 144 | R84: 46196.359 | AA84: =IFERROR( IF(ISNUMBER(C84),C84,DATE(VALUE(RIGHT(C84,4)),VALUE(MID(SUBSTITUTE(C84,"/","-"),FIND("-",SUBSTITUTE(C84,"/","-"))+1,FIND("-",SUBSTITUTE(C84,"/","-"),FIND("-",SUBSTITUTE(C84,"/","-"))+1)-FIND("-",SUBSTITUTE(C84,"/","-"))-1)),VALUE(LEFT(SUBSTITUTE(C84,"/","-"),FIND("-",SUBSTITUTE(C84,"/","-"))-1)))), DATE(1995,1,1) ) -> 46194
A85: 77 | B85: 2152 | C85: 46060 | D85: 15023 | E85: FAN | F85: MEP | G85: 3102010003 | H85: Exhaust Fan Shutter (8``) | I85: Pcs | J85: 3000 | K85: 10043.31 | L85: 1800 | M85: 6025.99 | N85: 1200 | O85: 4017.32 | P85: PENDING | Q85: 144 | R85: 46209.824 | AA85: =IFERROR( IF(ISNUMBER(C85),C85,DATE(VALUE(RIGHT(C85,4)),VALUE(MID(SUBSTITUTE(C85,"/","-"),FIND("-",SUBSTITUTE(C85,"/","-"))+1,FIND("-",SUBSTITUTE(C85,"/","-"),FIND("-",SUBSTITUTE(C85,"/","-"))+1)-FIND("-",SUBSTITUTE(C85,"/","-"))-1)),VALUE(LEFT(SUBSTITUTE(C85,"/","-"),FIND("-",SUBSTITUTE(C85,"/","-"))-1)))), DATE(1995,1,1) ) -> 46060
A86: 78 | B86: 2211 | C86: 22-07-2026 | D86: 1.5616156e+29 | E86: FAN | F86: MEP | G86: 3102010003 | H86: Exhaust Fan Shutter (8``) | I86: Pcs | J86: 18000 | K86: 60259.85 | L86: 16482 | M86: 55177.94 | N86: 1518 | O86: 5081.91 | P86: PENDING | Q86: 144 | R86: 46228.357 | AA86: =IFERROR( IF(ISNUMBER(C86),C86,DATE(VALUE(RIGHT(C86,4)),VALUE(MID(SUBSTITUTE(C86,"/","-"),FIND("-",SUBSTITUTE(C86,"/","-"))+1,FIND("-",SUBSTITUTE(C86,"/","-"),FIND("-",SUBSTITUTE(C86,"/","-"))+1)-FIND("-",SUBSTITUTE(C86,"/","-"))-1)),VALUE(LEFT(SUBSTITUTE(C86,"/","-"),FIND("-",SUBSTITUTE(C86,"/","-"))-1)))), DATE(1995,1,1) ) -> 46225
A87: 79 | B87: 2291 | C87: 22-08-2026 | E87: FAN | F87: MEP | G87: 3102010003 | H87: Exhaust Fan Shutter (8``) | I87: Pcs | J87: 17325 | K87: 58000.11 | M87: 0 | N87: 17325 | O87: 58000.11 | P87: CHECKED | Q87: 144 | R87: 46260.692 | AA87: =IFERROR( IF(ISNUMBER(C87),C87,DATE(VALUE(RIGHT(C87,4)),VALUE(MID(SUBSTITUTE(C87,"/","-"),FIND("-",SUBSTITUTE(C87,"/","-"))+1,FIND("-",SUBSTITUTE(C87,"/","-"),FIND("-",SUBSTITUTE(C87,"/","-"))+1)-FIND("-",SUBSTITUTE(C87,"/","-"))-1)),VALUE(LEFT(SUBSTITUTE(C87,"/","-"),FIND("-",SUBSTITUTE(C87,"/","-"))-1)))), DATE(1995,1,1) ) -> 46256
A88: 80 | B88: 2110 | C88: 20-06-2026 | D88: 1575414405 | E88: FAN | F88: MEP | G88: 3102010004 | H88: Exhaust Fan Blade (8``) | I88: Pcs | J88: 3200 | K88: 34253.91 | L88: 2108 | M88: 22564.76 | N88: 1092 | O88: 11689.15 | P88: PENDING | Q88: 144 | R88: 46193.793 | AA88: =IFERROR( IF(ISNUMBER(C88),C88,DATE(VALUE(RIGHT(C88,4)),VALUE(MID(SUBSTITUTE(C88,"/","-"),FIND("-",SUBSTITUTE(C88,"/","-"))+1,FIND("-",SUBSTITUTE(C88,"/","-"),FIND("-",SUBSTITUTE(C88,"/","-"))+1)-FIND("-",SUBSTITUTE(C88,"/","-"))-1)),VALUE(LEFT(SUBSTITUTE(C88,"/","-"),FIND("-",SUBSTITUTE(C88,"/","-"))-1)))), DATE(1995,1,1) ) -> 46193
A89: 81 | B89: 2114 | C89: 21-06-2026 | D89: 1.570815e+24 | E89: FAN | F89: MEP | G89: 3102010004 | H89: Exhaust Fan Blade (8``) | I89: Pcs | J89: 6200 | K89: 66366.96 | L89: 4375 | M89: 46831.52 | N89: 1825 | O89: 19535.43 | P89: PENDING | Q89: 144 | R89: 46196.359 | AA89: =IFERROR( IF(ISNUMBER(C89),C89,DATE(VALUE(RIGHT(C89,4)),VALUE(MID(SUBSTITUTE(C89,"/","-"),FIND("-",SUBSTITUTE(C89,"/","-"))+1,FIND("-",SUBSTITUTE(C89,"/","-"),FIND("-",SUBSTITUTE(C89,"/","-"))+1)-FIND("-",SUBSTITUTE(C89,"/","-"))-1)),VALUE(LEFT(SUBSTITUTE(C89,"/","-"),FIND("-",SUBSTITUTE(C89,"/","-"))-1)))), DATE(1995,1,1) ) -> 46194
A90: 82 | B90: 2211 | C90: 22-07-2026 | D90: 1.5532157e+24 | E90: FAN | F90: MEP | G90: 3102010004 | H90: Exhaust Fan Blade (8``) | I90: Pcs | J90: 5500 | K90: 58873.91 | L90: 5500 | M90: 58873.91 | N90: 0 | O90: 0 | P90: PENDING | Q90: 144 | R90: 46228.357 | AA90: =IFERROR( IF(ISNUMBER(C90),C90,DATE(VALUE(RIGHT(C90,4)),VALUE(MID(SUBSTITUTE(C90,"/","-"),FIND("-",SUBSTITUTE(C90,"/","-"))+1,FIND("-",SUBSTITUTE(C90,"/","-"),FIND("-",SUBSTITUTE(C90,"/","-"))+1)-FIND("-",SUBSTITUTE(C90,"/","-"))-1)),VALUE(LEFT(SUBSTITUTE(C90,"/","-"),FIND("-",SUBSTITUTE(C90,"/","-"))-1)))), DATE(1995,1,1) ) -> 46225
A91: 83 | B91: 2291 | C91: 22-08-2026 | E91: FAN | F91: MEP | G91: 3102010004 | H91: Exhaust Fan Blade (8``) | I91: Pcs | J91: 5775 | K91: 61817.61 | M91: 0 | N91: 5775 | O91: 61817.61 | P91: CHECKED | Q91: 144 | R91: 46260.692 | AA91: =IFERROR( IF(ISNUMBER(C91),C91,DATE(VALUE(RIGHT(C91,4)),VALUE(MID(SUBSTITUTE(C91,"/","-"),FIND("-",SUBSTITUTE(C91,"/","-"))+1,FIND("-",SUBSTITUTE(C91,"/","-"),FIND("-",SUBSTITUTE(C91,"/","-"))+1)-FIND("-",SUBSTITUTE(C91,"/","-"))-1)),VALUE(LEFT(SUBSTITUTE(C91,"/","-"),FIND("-",SUBSTITUTE(C91,"/","-"))-1)))), DATE(1995,1,1) ) -> 46256
A92: 84 | B92: 2110 | C92: 20-06-2026 | D92: 15843 | E92: FAN | F92: MEP | G92: 3102010005 | H92: Exhaust Fan Side Stand (8``) | I92: Pcs | J92: 3000 | K92: 27290.4 | L92: 3000 | M92: 27290.4 | N92: 0 | O92: 0 | P92: PENDING | Q92: 144 | R92: 46193.793 | AA92: =IFERROR( IF(ISNUMBER(C92),C92,DATE(VALUE(RIGHT(C92,4)),VALUE(MID(SUBSTITUTE(C92,"/","-"),FIND("-",SUBSTITUTE(C92,"/","-"))+1,FIND("-",SUBSTITUTE(C92,"/","-"),FIND("-",SUBSTITUTE(C92,"/","-"))+1)-FIND("-",SUBSTITUTE(C92,"/","-"))-1)),VALUE(LEFT(SUBSTITUTE(C92,"/","-"),FIND("-",SUBSTITUTE(C92,"/","-"))-1)))), DATE(1995,1,1) ) -> 46193
A93: 85 | B93: 2114 | C93: 21-06-2026 | D93: 153151533115021 | E93: FAN | F93: MEP | G93: 3102010005 | H93: Exhaust Fan Side Stand (8``) | I93: Pcs | J93: 6200 | K93: 56400.17 | L93: 6200 | M93: 56400.17 | N93: 0 | O93: 0 | P93: PENDING | Q93: 144 | R93: 46196.359 | AA93: =IFERROR( IF(ISNUMBER(C93),C93,DATE(VALUE(RIGHT(C93,4)),VALUE(MID(SUBSTITUTE(C93,"/","-"),FIND("-",SUBSTITUTE(C93,"/","-"))+1,FIND("-",SUBSTITUTE(C93,"/","-"),FIND("-",SUBSTITUTE(C93,"/","-"))+1)-FIND("-",SUBSTITUTE(C93,"/","-"))-1)),VALUE(LEFT(SUBSTITUTE(C93,"/","-"),FIND("-",SUBSTITUTE(C93,"/","-"))-1)))), DATE(1995,1,1) ) -> 46194
A94: 86 | B94: 2211 | C94: 22-07-2026 | D94: 153321581015863 | E94: FAN | F94: MEP | G94: 3102010005 | H94: Exhaust Fan Side Stand (8``) | I94: Pcs | J94: 5500 | K94: 50032.41 | L94: 1500 | M94: 13645.2 | N94: 4000 | O94: 36387.2 | P94: PENDING | Q94: 144 | R94: 46228.357 | AA94: =IFERROR( IF(ISNUMBER(C94),C94,DATE(VALUE(RIGHT(C94,4)),VALUE(MID(SUBSTITUTE(C94,"/","-"),FIND("-",SUBSTITUTE(C94,"/","-"))+1,FIND("-",SUBSTITUTE(C94,"/","-"),FIND("-",SUBSTITUTE(C94,"/","-"))+1)-FIND("-",SUBSTITUTE(C94,"/","-"))-1)),VALUE(LEFT(SUBSTITUTE(C94,"/","-"),FIND("-",SUBSTITUTE(C94,"/","-"))-1)))), DATE(1995,1,1) ) -> 46225
A95: 87 | B95: 2291 | C95: 22-08-2026 | E95: FAN | F95: MEP | G95: 3102010005 | H95: Exhaust Fan Side Stand (8``) | I95: Pcs | J95: 5775 | K95: 52534.03 | M95: 0 | N95: 5775 | O95: 52534.03 | P95: CHECKED | Q95: 144 | R95: 46260.692 | AA95: =IFERROR( IF(ISNUMBER(C95),C95,DATE(VALUE(RIGHT(C95,4)),VALUE(MID(SUBSTITUTE(C95,"/","-"),FIND("-",SUBSTITUTE(C95,"/","-"))+1,FIND("-",SUBSTITUTE(C95,"/","-"),FIND("-",SUBSTITUTE(C95,"/","-"))+1)-FIND("-",SUBSTITUTE(C95,"/","-"))-1)),VALUE(LEFT(SUBSTITUTE(C95,"/","-"),FIND("-",SUBSTITUTE(C95,"/","-"))-1)))), DATE(1995,1,1) ) -> 46256
A96: 88 | B96: 2110 | C96: 20-06-2026 | D96: 1440514690 | E96: FAN | F96: MEP | G96: 3102010006 | H96: Exhaust Fan Show Cap With Pitol Bush | I96: Pcs | J96: 6500 | K96: 17578.26 | L96: 5318 | M96: 14381.72 | N96: 1182 | O96: 3196.54 | P96: PENDING | Q96: 144 | R96: 46193.793 | AA96: =IFERROR( IF(ISNUMBER(C96),C96,DATE(VALUE(RIGHT(C96,4)),VALUE(MID(SUBSTITUTE(C96,"/","-"),FIND("-",SUBSTITUTE(C96,"/","-"))+1,FIND("-",SUBSTITUTE(C96,"/","-"),FIND("-",SUBSTITUTE(C96,"/","-"))+1)-FIND("-",SUBSTITUTE(C96,"/","-"))-1)),VALUE(LEFT(SUBSTITUTE(C96,"/","-"),FIND("-",SUBSTITUTE(C96,"/","-"))-1)))), DATE(1995,1,1) ) -> 46193
A97: 89 | B97: 2114 | C97: 21-06-2026 | D97: 1.5021153e+19 | E97: FAN | F97: MEP | G97: 3102010006 | H97: Exhaust Fan Show Cap With Pitol Bush | I97: Pcs | J97: 15500 | K97: 41917.39 | L97: 7106 | M97: 19217.1 | N97: 8394 | O97: 22700.3 | P97: PENDING | Q97: 144 | R97: 46196.359 | AA97: =IFERROR( IF(ISNUMBER(C97),C97,DATE(VALUE(RIGHT(C97,4)),VALUE(MID(SUBSTITUTE(C97,"/","-"),FIND("-",SUBSTITUTE(C97,"/","-"))+1,FIND("-",SUBSTITUTE(C97,"/","-"),FIND("-",SUBSTITUTE(C97,"/","-"))+1)-FIND("-",SUBSTITUTE(C97,"/","-"))-1)),VALUE(LEFT(SUBSTITUTE(C97,"/","-"),FIND("-",SUBSTITUTE(C97,"/","-"))-1)))), DATE(1995,1,1) ) -> 46194
A98: 90 | B98: 2211 | C98: 22-07-2026 | D98: 1.5424155e+24 | E98: FAN | F98: MEP | G98: 3102010006 | H98: Exhaust Fan Show Cap With Pitol Bush | I98: Pcs | J98: 16000 | K98: 43269.57 | L98: 10925 | M98: 29545 | N98: 5075 | O98: 13724.57 | P98: PENDING | Q98: 144 | R98: 46228.357 | AA98: =IFERROR( IF(ISNUMBER(C98),C98,DATE(VALUE(RIGHT(C98,4)),VALUE(MID(SUBSTITUTE(C98,"/","-"),FIND("-",SUBSTITUTE(C98,"/","-"))+1,FIND("-",SUBSTITUTE(C98,"/","-"),FIND("-",SUBSTITUTE(C98,"/","-"))+1)-FIND("-",SUBSTITUTE(C98,"/","-"))-1)),VALUE(LEFT(SUBSTITUTE(C98,"/","-"),FIND("-",SUBSTITUTE(C98,"/","-"))-1)))), DATE(1995,1,1) ) -> 46225
A99: 91 | B99: 2291 | C99: 22-08-2026 | E99: FAN | F99: MEP | G99: 3102010006 | H99: Exhaust Fan Show Cap With Pitol Bush | I99: Pcs | J99: 12600 | K99: 34074.78 | M99: 0 | N99: 12600 | O99: 34074.78 | P99: CHECKED | Q99: 144 | R99: 46260.692 | AA99: =IFERROR( IF(ISNUMBER(C99),C99,DATE(VALUE(RIGHT(C99,4)),VALUE(MID(SUBSTITUTE(C99,"/","-"),FIND("-",SUBSTITUTE(C99,"/","-"))+1,FIND("-",SUBSTITUTE(C99,"/","-"),FIND("-",SUBSTITUTE(C99,"/","-"))+1)-FIND("-",SUBSTITUTE(C99,"/","-"))-1)),VALUE(LEFT(SUBSTITUTE(C99,"/","-"),FIND("-",SUBSTITUTE(C99,"/","-"))-1)))), DATE(1995,1,1) ) -> 46256
A100: 92 | B100: 2110 | C100: 20-06-2026 | D100: 14690 | E100: FAN | F100: MEP | G100: 3102010007 | H100: Exhaust Fan Capacitor Box | I100: Pcs | J100: 6200 | K100: 16766.97 | L100: 6200 | M100: 16766.97 | N100: 0 | O100: 0 | P100: PENDING | Q100: 144 | R100: 46193.793 | AA100: =IFERROR( IF(ISNUMBER(C100),C100,DATE(VALUE(RIGHT(C100,4)),VALUE(MID(SUBSTITUTE(C100,"/","-"),FIND("-",SUBSTITUTE(C100,"/","-"))+1,FIND("-",SUBSTITUTE(C100,"/","-"),FIND("-",SUBSTITUTE(C100,"/","-"))+1)-FIND("-",SUBSTITUTE(C100,"/","-"))-1)),VALUE(LEFT(SUBSTITUTE(C100,"/","-"),FIND("-",SUBSTITUTE(C100,"/","-"))-1)))), DATE(1995,1,1) ) -> 46193
...

Sheet InterCompany Requsition Report
A1: MEP FAN LTD.
A2: SL | B2: Category | C2: FG Code | D2: Item Description | E2: Unit | F2: Demand | G2: Total Received | H2: Pending | I2: Pending (%) | J2: Month | K2: Year
J3: August | K3: 2026 | L3: =J3&K3 -> August2026
A4: MEP Plastic | I4: =AVERAGE(I6:I17) -> 0.33304384
A5: Ceiling Fan
A6: 1 | B6: Raw Materials | C6: 3101010078 | D6: Canopy Big | E6: Pcs | F6: {=SUMIFS(Compile!J:J,Compile!G:G,C6:C142,Compile!AM:AM,$L$3)} -> 94500 | G6: {=SUMIFS(Compile!L:L,Compile!G:G,C6:C142,Compile!AM:AM,$L$3)} -> 86435 | H6: =F6-G6 -> 8065 | I6: =IFERROR(H6/F6, "") -> 0.085343915
A7: 2 | B7: Raw Materials | C7: 3101010080 | D7: Capacitor Cover | E7: Pcs | F7: 47250 | G7: 20300 | H7: =F7-G7 -> 26950 | I7: =IFERROR(H7/F7, "") -> 0.57037037
A8: 3 | B8: Raw Materials | C8: 3101010081 | D8: Rubber Gasket (56`` 48``) | E8: Pcs | F8: 110250 | G8: 87900 | H8: =F8-G8 -> 22350 | I8: =IFERROR(H8/F8, "") -> 0.20272109
A9: 4 | B9: Raw Materials | C9: 3101010083 | D9: Rubber Gasket (2401,3601) | E9: Pcs | F9: 36750 | G9: 0 | H9: =F9-G9 -> 36750 | I9: =IFERROR(H9/F9, "") -> 1
A10: 5 | B10: Raw Materials | C10: 3101010084 | D10: Plastic XL Cap | E10: Pcs | F10: 47250 | G10: 41302 | H10: =F10-G10 -> 5948 | I10: =IFERROR(H10/F10, "") -> 0.1258836
A11: 6 | B11: Raw Materials | C11: 3101010085 | D11: Insulation Rubber | E11: Pcs | F11: 20000 | G11: 20000 | H11: =F11-G11 -> 0 | I11: =IFERROR(H11/F11, "") -> 0
A12: 7 | B12: Raw Materials | C12: 3101010086 | D12: Canopy Rubber Ring | E12: Pcs | F12: 94500 | G12: 74652 | H12: =F12-G12 -> 19848 | I12: =IFERROR(H12/F12, "") -> 0.21003175
A13: 8 | B13: Raw Materials | C13: 3101010107 | D13: Nice Regulator Small White(FAN) | E13: Pcs | F13: 50000 | G13: 26500 | H13: =F13-G13 -> 23500 | I13: =IFERROR(H13/F13, "") -> 0.47 | P13: January | Q13: 2026
A14: 9 | B14: Raw Materials | C14: 3101010110 | D14: Rubber Gasket (5602) | E14: Pcs | F14: 0 | G14: 0 | H14: =F14-G14 -> 0 | I14: =IFERROR(H14/F14, "") | P14: February | Q14: 2027
A15: 10 | B15: Raw Materials | C15: 3101010117 | D15: Canopy White | E15: Pcs | F15: 0 | G15: 0 | H15: =F15-G15 -> 0 | I15: =IFERROR(H15/F15, "") | P15: March | Q15: 2028
A16: 11 | B16: Ceiling Raw | C16: 3101010119 | D16: Promotional Gang Regulator White (P512) | F16: 0 | G16: 0 | H16: =F16-G16 -> 0 | I16: =IFERROR(H16/F16, "")
A17: 12 | B17: Raw Materials | C17: 3101010137 | D17: MEP Cable Tie -2.5 x100mm | E17: Pcs | F17: 0 | G17: 0 | H17: =F17-G17 -> 0 | I17: =IFERROR(H17/F17, "") | P17: April
A18: Exhaust Fan | F18: 0 | G18: 0 | I18: =AVERAGE(I19:I34) -> 0.3210728
A19: 13 | B19: Raw Materials | C19: 3102010001 | D19: Exhaust Fan Base (8``) | E19: Pcs | F19: 5500 | G19: 3860 | H19: =F19-G19 -> 1640 | I19: =IFERROR(H19/F19, "") -> 0.29818182 | P19: May
A20: 14 | B20: Raw Materials | C20: 3102010002 | D20: Exhaust Fan Cover (8``) | E20: Pcs | F20: 5500 | G20: 4461 | H20: =F20-G20 -> 1039 | I20: =IFERROR(H20/F20, "") -> 0.18890909 | P20: June
A21: 15 | B21: Raw Materials | C21: 3102010003 | D21: Exhaust Fan Shutter (8``) | E21: Pcs | F21: 18000 | G21: 16482 | H21: =F21-G21 -> 1518 | I21: =IFERROR(H21/F21, "") -> 0.084333333 | P21: July
A22: 16 | B22: Raw Materials | C22: 3102010004 | D22: Exhaust Fan Blade (8``) | E22: Pcs | F22: 5500 | G22: 5500 | H22: =F22-G22 -> 0 | I22: =IFERROR(H22/F22, "") -> 0 | P22: August
A23: 17 | B23: Raw Materials | C23: 3102010005 | D23: Exhaust Fan Side Stand (8``) | E23: Pcs | F23: 5500 | G23: 1500 | H23: =F23-G23 -> 4000 | I23: =IFERROR(H23/F23, "") -> 0.72727273 | P23: September
A24: 18 | B24: Raw Materials | C24: 3102010006 | D24: Exhaust Fan Show Cap With Pitol Bush | E24: Pcs | F24: 16000 | G24: 10925 | H24: =F24-G24 -> 5075 | I24: =IFERROR(H24/F24, "") -> 0.3171875 | P24: October
A25: 19 | B25: Raw Materials | C25: 3102010007 | D25: Exhaust Fan Capacitor Box | E25: Pcs | F25: 16000 | G25: 16000 | H25: =F25-G25 -> 0 | I25: =IFERROR(H25/F25, "") -> 0 | P25: November
A26: 20 | B26: Raw Materials | C26: 3102010008 | D26: Exhaust Fan Stick (8``) | E26: Pcs | F26: 5500 | G26: 5500 | H26: =F26-G26 -> 0 | I26: =IFERROR(H26/F26, "") -> 0 | P26: December
A27: 21 | B27: Raw Materials | C27: 3102010009 | D27: Exhaust Fan Clam | E27: Pcs | F27: 16000 | G27: 0 | H27: =F27-G27 -> 16000 | I27: =IFERROR(H27/F27, "") -> 1
A28: 22 | B28: Raw Materials | C28: 3102010011 | D28: Exhaust Fan Spring Lock | E28: Pcs | F28: 16000 | G28: 3500 | H28: =F28-G28 -> 12500 | I28: =IFERROR(H28/F28, "") -> 0.78125
A29: 23 | B29: Raw Materials | C29: 3102010019 | D29: MEP Cable Tie -3.5x150mm | E29: Pcs | F29: 16000 | G29: 16000 | H29: =F29-G29 -> 0 | I29: =IFERROR(H29/F29, "") -> 0
A30: 24 | B30: Raw Materials | C30: 3202010010 | D30: Exhaust Fan Base (10``) | E30: Pcs | F30: 11000 | G30: 9351 | H30: =F30-G30 -> 1649 | I30: =IFERROR(H30/F30, "") -> 0.14990909
A31: 25 | B31: Raw Materials | C31: 3202010011 | D31: Exhaust Fan Cover (10``) | E31: Pcs | F31: 11000 | G31: 3750 | H31: =F31-G31 -> 7250 | I31: =IFERROR(H31/F31, "") -> 0.65909091
A32: 26 | B32: Raw Materials | C32: 3202010012 | D32: Exhaust Fan Side Stand (10``) | E32: Pcs | F32: 11000 | G32: 9437 | H32: =F32-G32 -> 1563 | I32: =IFERROR(H32/F32, "") -> 0.14209091
A33: 27 | B33: Raw Materials | C33: 3202010013 | D33: Exhaust Fan Shutter (10``) | E33: Pcs | F33: 33000 | G33: 6965 | H33: =F33-G33 -> 26035 | I33: =IFERROR(H33/F33, "") -> 0.78893939
A34: 28 | B34: Raw Materials | C34: 3202010014 | D34: Exhaust Fan Stick (10``) | E34: Pcs | F34: 11000 | G34: 11000 | H34: =F34-G34 -> 0 | I34: =IFERROR(H34/F34, "") -> 0
A35: MEP National Screw | F35: 0 | G35: 0 | H35: =F35-G35 -> 0 | I35: =AVERAGE(I37:I45) -> 0.26857945
A36: Ceiling Fan | F36: 0 | G36: 0
A37: 1 | B37: Raw Materials | C37: 3101010071 | D37: Down Pipe Bolt 8mm x 1.5```` (50/kg) | E37: Pcs | F37: 120750 | G37: 75795 | H37: =F37-G37 -> 44955 | I37: =IFERROR(H37/F37, "") -> 0.37229814
A38: 2 | B38: Raw Materials | C38: 3101010072 | D38: Down Pipe Bolt 8mm x 2```` (45/kg) | E38: Pcs | F38: 10500 | G38: 9526 | H38: =F38-G38 -> 974 | I38: =IFERROR(H38/F38, "") -> 0.092761905
A39: 3 | B39: Raw Materials | C39: 3101010073 | D39: Down Pipe Sira Pin(Fan) | E39: Pcs | F39: 131250 | G39: 131249 | H39: =F39-G39 -> 1 | I39: =IFERROR(H39/F39, "") -> 7.6190476e-06
A40: 4 | B40: Raw Materials | C40: 3101010074 | D40: Shaft/XL /Safity lock Screw 3/16x3/8```` (400/kg) | E40: KG | F40: 168 | G40: 160.2 | H40: =F40-G40 -> 7.8 | I40: =IFERROR(H40/F40, "") -> 0.046428571
A41: 5 | B41: Raw Materials | C41: 3101010075 | D41: Body Screw 18x6mm,H=10mm (200/kg) | E41: KG | F41: 84 | G41: 84 | H41: =F41-G41 -> 0 | I41: =IFERROR(H41/F41, "") -> 0
A42: 6 | B42: Raw Materials | C42: 3101010076 | D42: Body Screw 15x6mm,H=10mm (230/kg) | E42: KG | F42: 0 | G42: 0 | H42: =F42-G42 -> 0 | I42: =IFERROR(H42/F42, "")
A43: 7 | B43: Raw Materials | C43: 3101010077 | D43: Blade/Body Screw 12.7x6mm,H=10mm (220/kg) | E43: KG | F43: 1500 | G43: 1335.2 | H43: =F43-G43 -> 164.8 | I43: =IFERROR(H43/F43, "") -> 0.10986667
A44: 8 | B44: Raw Materials | C44: 3101010130 | D44: Body screw- 3/16`` x 35mm | E44: KG | F44: 20 | G44: 0 | H44: =F44-G44 -> 20 | I44: =IFERROR(H44/F44, "") -> 1
A45: 9 | B45: Raw Materials | C45: 3101010070 | D45: Ms Washer 3/16 (1910/kg) | E45: KG | F45: 22 | G45: 10.4 | H45: =F45-G45 -> 11.6 | I45: =IFERROR(H45/F45, "") -> 0.52727273
A46: Exhaust Fan | F46: 0 | G46: 0 | I46: =AVERAGEIF(I47:I48, "<>0") -> 0.914
A47: 10 | B47: Raw Materials | C47: 3102010010 | D47: Exhaust Fan Spring (FAN) | E47: KG | F47: 50 | G47: 8.6 | H47: =F47-G47 -> 41.4 | I47: =IFERROR(H47/F47, "") -> 0.828
A48: 11 | B48: Raw Materials | C48: 3102010013 | D48: 5/32 Inch, 9mm Screw | E48: KG | F48: 150 | G48: 0 | H48: =F48-G48 -> 150 | I48: =IFERROR(H48/F48, "") -> 1
A49: MEP Cables | F49: 0 | G49: 0 | H49: =F49-G49 -> 0 | I49: =AVERAGEIF(I51:I56, "<>0") -> 0.83159722
A50: Ceiling Fan | F50: 0 | G50: 0
A51: 1 | B51: Raw Materials | C51: 3101010016 | D51: Super Wire (SWG 33) / 0.253mm | E51: KG | F51: 11000 | G51: 0 | H51: =F51-G51 -> 11000 | I51: =IFERROR(H51/F51, "") -> 1
A52: 2 | B52: Raw Materials | C52: 3101010017 | D52: Super Wire (SWG 34) / 0.233mm | E52: KG | F52: 1500 | G52: 0 | H52: =F52-G52 -> 1500 | I52: =IFERROR(H52/F52, "") -> 1
A53: 3 | B53: Raw Materials | C53: 3101010018 | D53: Super Wire (SWG 35) / 0.213mm | E53: KG | F53: 2500 | G53: 0 | H53: =F53-G53 -> 2500 | I53: =IFERROR(H53/F53, "") -> 1
A54: 4 | B54: Raw Materials | C54: 3101010090 | D54: Flaxible Cable 14x0.0076 - Red | E54: Mtr | F54: 43200 | G54: 29100 | H54: =F54-G54 -> 14100 | I54: =IFERROR(H54/F54, "") -> 0.32638889
A55: 5 | B55: Raw Materials | C55: 3101010111 | D55: Flaxible Cable 14x0.0076 - Yellow | E55: Mtr | F55: 14400 | G55: 14400 | H55: =F55-G55 -> 0 | I55: =IFERROR(H55/F55, "") -> 0
A56: 6 | B56: Raw Materials | C56: 3101010112 | D56: Flaxible Cable 14x0.0076 - Black | E56: Mtr | F56: 43200 | G56: 43200 | H56: =F56-G56 -> 0 | I56: =IFERROR(H56/F56, "") -> 0
A57: Rechargeable Fan | F57: 0 | G57: 0 | I57: =IFERROR(AVERAGEIF(I58,"<>0"),"-") -> -
A58: 7 | B58: Production Consumables - FAN | C58: 700100037 | D58: GI Insulation wire | E58: Mtr | F58: 0 | G58: 0 | H58: =F58-G58 -> 0
A59: Exhaust Fan | F59: 0 | G59: 0 | I59: =AVERAGEIF(I60:I60, "<>0") -> 1
A60: 8 | B60: Raw Materials | C60: 3102010012 | D60: Cable 2x23/0.0076 | E60: Mtr | F60: 10500 | G60: 0 | H60: =F60-G60 -> 10500 | I60: =IFERROR(H60/F60, "") -> 1
A61: MEP BSIC (Packing Materials) | F61: 0 | G61: 0 | H61: =F61-G61 -> 0 | I61: =AVERAGEIF(I63:I121, "<>0") -> 0.45393497
A62: Ceiling Fan | F62: 0 | G62: 0
A63: 1 | B63: Packing Materials | C63: 3201010002 | D63: FAN Shank Paper | E63: Pcs | F63: 136500 | G63: 136500 | H63: =F63-G63 -> 0 | I63: =IFERROR(H63/F63, "") -> 0
A64: 2 | B64: Packing Materials | C64: 3201010004 | D64: Body Sticker-5601 | E64: Pcs | F64: 31500 | G64: 31500 | H64: =F64-G64 -> 0 | I64: =IFERROR(H64/F64, "") -> 0
A65: 3 | B65: Packing Materials | C65: 3201010005 | D65: Body Sticker-Premium Plus(5606) | E65: Pcs | F65: 0 | G65: 0 | H65: =F65-G65 -> 0 | I65: =IFERROR(H65/F65, "")
A66: 4 | B66: Packing Materials | C66: 3201010006 | D66: Body Sticker Speed King | E66: Pcs | F66: 0 | G66: 0 | H66: =F66-G66 -> 0 | I66: =IFERROR(H66/F66, "")
A67: 5 | B67: Packing Materials | C67: 3201010007 | D67: Body Sticker-4801 | E67: Pcs | F67: 5250 | G67: 5250 | H67: =F67-G67 -> 0 | I67: =IFERROR(H67/F67, "") -> 0
A68: 6 | B68: Packing Materials | C68: 3201010008 | D68: Body Sticker-3601 | E68: Pcs | F68: 5250 | G68: 5250 | H68: =F68-G68 -> 0 | I68: =IFERROR(H68/F68, "") -> 0
A69: 7 | B69: Packing Materials | C69: 3201010009 | D69: Body Sticker-2401 | E69: Pcs | F69: 5250 | G69: 5000 | H69: =F69-G69 -> 250 | I69: =IFERROR(H69/F69, "") -> 0.047619048
A70: 8 | B70: Packing Materials | C70: 3201010010 | D70: Fan Canopy Sticker | E70: Pcs | F70: 94500 | G70: 94500 | H70: =F70-G70 -> 0 | I70: =IFERROR(H70/F70, "") -> 0
A71: 9 | B71: Packing Materials | C71: 3201010011 | D71: Canopy Sticker Speed King | E71: Pcs | F71: 0 | G71: 0 | H71: =F71-G71 -> 0 | I71: =IFERROR(H71/F71, "")
A72: 10 | B72: Packing Materials | C72: 3201010013 | D72: Fan Down Pipe Sticker | E72: Pcs | F72: 36750 | G72: 17500 | H72: =F72-G72 -> 19250 | I72: =IFERROR(H72/F72, "") -> 0.52380952
A73: 11 | B73: Packing Materials | C73: 3201010015 | D73: Guarantee Card -5601 | E73: Pcs | F73: 31500 | G73: 31500 | H73: =F73-G73 -> 0 | I73: =IFERROR(H73/F73, "") -> 0
A74: 12 | B74: Packing Materials | C74: 3201010016 | D74: Guarantee Card -4801 | E74: Pcs | F74: 5250 | G74: 5000 | H74: =F74-G74 -> 250 | I74: =IFERROR(H74/F74, "") -> 0.047619048
... A114: 52 | B114: Production Consumables - FAN | C114: 700100038 | D114: Replace Card-Fan | E114: Pcs | F114: 0 | G114: 0 | H114: =F114-G114 -> 0 | I114: =IFERROR(H114/F114, "")
A115: Capacitor | F115: 0 | G115: 0 | I115: =AVERAGEIF(I116:I121, "<>0") -> 0.11661972
A116: 53 | B116: Packing Materials | C116: 3201010073 | D116: Capacitor Master Carton-Fan | E116: Pcs | F116: 3400 | G116: 3400 | H116: =F116-G116 -> 0 | I116: =IFERROR(H116/F116, "") -> 0
A117: 54 | B117: Packing Materials | C117: 3201010074 | D117: Capacitor Inner box 2.5 µF -Fan | E117: Pcs | F117: 6000 | G117: 6000 | H117: =F117-G117 -> 0 | I117: =IFERROR(H117/F117, "") -> 0
A118: 55 | B118: Packing Materials | C118: 3201010075 | D118: Capacitor Inner box 3.5 µF -Fan | E118: Pcs | F118: 7100 | G118: 6272 | H118: =F118-G118 -> 828 | I118: =IFERROR(H118/F118, "") -> 0.11661972
A119: 56 | B119: Packing Materials | C119: 3201010076 | D119: Capacitor Warranty Card 2.5 µF -Fan | E119: Pcs | F119: 71900 | G119: 71900 | H119: =F119-G119 -> 0 | I119: =IFERROR(H119/F119, "") -> 0
A120: 57 | B120: Packing Materials | C120: 3201010077 | D120: Capacitor Warranty Card 3.5 µF -Fan | E120: Pcs | F120: 85600 | G120: 85600 | H120: =F120-G120 -> 0 | I120: =IFERROR(H120/F120, "") -> 0
A121: 58 | B121: Packing Materials | C121: 3201010078 | D121: Zipper poly (3 x 4) inch -Fan | E121: KG | F121: 0 | G121: 0 | H121: =F121-G121 -> 0 | I121: =IFERROR(H121/F121, "")
A122: Exhaust Fan | F122: 0 | G122: 0 | I122: =AVERAGEIF(I123:I131, "<>0") -> 0.5211921
A123: 59 | B123: Packing Materials | C123: 3201010079 | D123: 8 Inch Exhaust Fan Body Carton (Alu) | E123: Pcs | F123: 5565 | G123: 5561 | H123: =F123-G123 -> 4 | I123: =IFERROR(H123/F123, "") -> 0.00071877808
A124: 60 | B124: Packing Materials | C124: 3201010080 | D124: 10 Inch Exhaust Fan Body Carton (Alu) | E124: Pcs | F124: 11025 | G124: 2316 | H124: =F124-G124 -> 8709 | I124: =IFERROR(H124/F124, "") -> 0.78993197
A125: 61 | B125: Packing Materials | C125: 3201010081 | D125: Aero Flow Sticker | E125: Pcs | F125: 20000 | G125: 20000 | H125: =F125-G125 -> 0 | I125: =IFERROR(H125/F125, "") -> 0
A126: 62 | B126: Packing Materials | C126: 3201010083 | D126: Warranty Card (Aero Flow) | E126: Pcs | F126: 17000 | G126: 12000 | H126: =F126-G126 -> 5000 | I126: =IFERROR(H126/F126, "") -> 0.29411765
A127: 63 | B127: Raw Materials | C127: 3202010001 | D127: HDPE Poly 18x22``-(Std.W.- 0.006206 kg) | E127: KG | F127: 100 | G127: 100 | H127: =F127-G127 -> 0 | I127: =IFERROR(H127/F127, "") -> 0
A128: 64 | B128: Raw Materials | C128: 3202010009 | D128: 10 Inch Exhasust Fan Body Carton | E128: Pcs | F128: 0 | G128: 0 | H128: =F128-G128 -> 0 | I128: =IFERROR(H128/F128, "")
A129: 65 | B129: Raw Materials | C129: 3202010008 | D129: HDPE Poly 20x24``-(Std.W.-0.015016 kg) | E129: KG | F129: 200 | G129: 200 | H129: 0
A130: 66 | B130: Raw Materials | C130: 3202010002 | D130: 8 Inch Exhasust Fan Body Carton | E130: Pcs | F130: 0 | G130: 0 | H130: 0
A131: 67 | B131: Raw Materials | C131: 3202010016 | D131: Air Fresher Sticker | E131: Pcs | F131: 0 | G131: 0 | H131: 6000 | I131: 1
A132: Rechargeable Fan | F132: 0 | G132: 0 | I132: =IFERROR(AVERAGEIF(I133:I142,"<>0"),"-") -> -
A133: 68 | B133: Packing Materials | C133: 3201010063 | D133: Body Carton - (Rec-12 inch) | E133: Pcs | F133: 0 | G133: 0 | H133: =F133-G133 -> 0 | I133: =IFERROR(H133/F133, "")
A134: 69 | B134: Packing Materials | C134: 3201010066 | D134: Operation Manual (Rec-12 Inch) | E134: Pcs | F134: 0 | G134: 0 | H134: =F134-G134 -> 0 | I134: =IFERROR(H134/F134, "")
A135: 70 | B135: Packing Materials | C135: 3201010067 | D135: Body Poly - 0.050 mm (24 Inch x 14 Inch) Std Wt. 0.0179 | E135: KG | F135: 0 | G135: 0 | H135: =F135-G135 -> 0 | I135: =IFERROR(H135/F135, "")
A136: 71 | B136: Packing Materials | C136: 3201010068 | D136: Grill Poly- 0.020 mm (20 Inch x 18 Inch) | E136: KG | F136: 0 | G136: 0 | H136: =F136-G136 -> 0 | I136: =IFERROR(H136/F136, "")
A137: 72 | B137: Packing Materials | C137: 3201010070 | D137: Body Carton - (Rec-16 inch) | E137: Pcs | F137: 0 | G137: 0 | H137: =F137-G137 -> 0 | I137: =IFERROR(H137/F137, "")
A138: 73 | B138: Packing Materials | C138: 3201010071 | D138: Operation Manual (Rec-16 Inch) | E138: Pcs | F138: 0 | G138: 0 | H138: =F138-G138 -> 0 | I138: =IFERROR(H138/F138, "")
A139: 74 | B139: Packing Materials | C139: 3201010072 | D139: Warrienty Card (RTF) | E139: Pcs | F139: 0 | G139: 0 | H139: =F139-G139 -> 0 | I139: =IFERROR(H139/F139, "")
...

Sheet Compile
B3: July To August | C3: 46223 | D3: 46253
A4: S/L | B4: Req No | C4: Req Date | D4: Issue NO | E4: Company (Purchase) | F4: Company (Sales) | G4: Item Code | H4: Item Name | I4: Unit Name | J4: Req Qty | K4: Req Value | L4: Issue Qty | M4: Issue Value | N4: Pending Qty | O4: Pending Value | P4: Status | Q4: Entry By | R4: Entry At
A5: {=IFERROR(_xlfn.VSTACK(_xlfn._xlws.FILTER('BSIC Entry'!A1:R1030,('BSIC Entry'!AA1:AA1030>=C3)*('BSIC Entry'!AA1:AA1030<=D3),""),_xlfn._xlws.FILTER('Plastic Entry'!A1:R1030,('Plastic Entry'!AA1:AA1030>=C3)*('Plastic Entry'!AA1:AA1030<=D3),"")),"No Data")} -> 3 | B5: 2219 | C5: 26-07-2026 | D5: 1584715871 | E5: FAN | F5: Printing and Packaging | G5: 3202010001 | H5: HDPE Poly (L=22``, W=18``, T=0.025mm) | I5: KG | J5: 100 | K5: 28989.08 | L5: 100 | M5: 28989.08 | N5: 0 | O5: 0 | P5: PENDING | Q5: 144 | R5: 46229.685 | AK5: August | AL5: 2026 | AM5: =AK5&AL5 -> August2026
A6: 10 | B6: 2219 | C6: 26-07-2026 | D6: 1584715655 | E6: FAN | F6: Printing and Packaging | G6: 3202010008 | H6: HDPE Poly (L=24``, W=20``, T=0.025mm) | I6: KG | J6: 200 | K6: 57728.01 | L6: 200 | M6: 57728.01 | N6: 0 | O6: 0 | P6: PENDING | Q6: 144 | R6: 46229.685 | AK6: August | AL6: 2026 | AM6: =AK6&AL6 -> August2026
A7: 22 | B7: 2206 | C7: 22-07-2026 | D7: 15333 | E7: FAN | F7: Printing and Packaging | G7: 3201010002 | H7: FAN Shank Paper | I7: Pcs | J7: 136500 | K7: 209358.94 | L7: 136500 | M7: 209358.94 | N7: 0 | O7: 0 | P7: PENDING | Q7: 144 | R7: 46228.398 | AK7: August | AL7: 2026 | AM7: =AK7&AL7 -> August2026
A8: 25 | B8: 2206 | C8: 22-07-2026 | D8: 15333 | E8: FAN | F8: Printing and Packaging | G8: 3201010004 | H8: Body Sticker-5601 | I8: Pcs | J8: 31500 | K8: 9519.63 | L8: 31500 | M8: 9519.63 | N8: 0 | O8: 0 | P8: PENDING | Q8: 144 | R8: 46228.398 | AK8: August | AL8: 2026 | AM8: =AK8&AL8 -> August2026
A9: 27 | B9: 2206 | C9: 22-07-2026 | D9: 15333 | E9: FAN | F9: Printing and Packaging | G9: 3201010007 | H9: Body Sticker-4801 | I9: Pcs | J9: 5250 | K9: 1503.11 | L9: 5250 | M9: 1503.11 | N9: 0 | O9: 0 | P9: PENDING | Q9: 144 | R9: 46228.398 | AK9: August | AL9: 2026 | AM9: =AK9&AL9 -> August2026
A10: 28 | B10: 2206 | C10: 22-07-2026 | D10: 15333 | E10: FAN | F10: Printing and Packaging | G10: 3201010008 | H10: Body Sticker-3601 | I10: Pcs | J10: 5250 | K10: 1525.91 | L10: 5250 | M10: 1525.91 | N10: 0 | O10: 0 | P10: PENDING | Q10: 144 | R10: 46228.398 | AK10: August | AL10: 2026 | AM10: =AK10&AL10 -> August2026
A11: 31 | B11: 2206 | C11: 22-07-2026 | D11: 15338 | E11: FAN | F11: Printing and Packaging | G11: 3201010009 | H11: Body Sticker-2401 | I11: Pcs | J11: 5250 | K11: 1886.17 | L11: 5000 | M11: 1796.35 | N11: 250 | O11: 89.82 | P11: PENDING | Q11: 144 | R11: 46228.398 | AK11: August | AL11: 2026 | AM11: =AK11&AL11 -> August2026
A12: 33 | B12: 2206 | C12: 22-07-2026 | D12: 15547 | E12: FAN | F12: Printing and Packaging | G12: 3201010010 | H12: Fan Canopy Sticker | I12: Pcs | J12: 94500 | K12: 46440.61 | L12: 94500 | M12: 46440.61 | N12: 0 | O12: 0 | P12: PENDING | Q12: 144 | R12: 46228.398 | AK12: August | AL12: 2026 | AM12: =AK12&AL12 -> August2026
A13: 37 | B13: 2206 | C13: 22-07-2026 | D13: 15338 | E13: FAN | F13: Printing and Packaging | G13: 3201010013 | H13: Fan Down Pipe Sticker | I13: Pcs | J13: 36750 | K13: 13741.31 | L13: 17500 | M13: 6543.48 | N13: 19250 | O13: 7197.83 | P13: PENDING | Q13: 144 | R13: 46228.398 | AK13: August | AL13: 2026 | AM13: =AK13&AL13 -> August2026
A14: 42 | B14: 2206 | C14: 22-07-2026 | D14: 15354 | E14: FAN | F14: Printing and Packaging | G14: 3201010014 | H14: Fan QC Sticker | I14: Pcs | J14: 47250 | K14: 10661.17 | L14: 40000 | M14: 9025.33 | N14: 7250 | O14: 1635.84 | P14: PENDING | Q14: 144 | R14: 46228.398 | AK14: August | AL14: 2026 | AM14: =AK14&AL14 -> August2026
A15: 43 | B15: 2219 | C15: 26-07-2026 | D15: 15353 | E15: FAN | F15: Printing and Packaging | G15: 3201010014 | H15: Fan QC Sticker | I15: Pcs | J15: 20000 | K15: 4512.67 | L15: 20000 | M15: 4512.67 | N15: 0 | O15: 0 | P15: PENDING | Q15: 144 | R15: 46229.685 | AK15: August | AL15: 2026 | AM15: =AK15&AL15 -> August2026
A16: 47 | B16: 2206 | C16: 22-07-2026 | D16: 15409 | E16: FAN | F16: Printing and Packaging | G16: 3201010015 | H16: Guarantee Card -5601 | I16: Pcs | J16: 31500 | K16: 46042.86 | L16: 31500 | M16: 46042.86 | N16: 0 | O16: 0 | P16: PENDING | Q16: 144 | R16: 46228.398 | AK16: August | AL16: 2026 | AM16: =AK16&AL16 -> August2026
A17: 49 | B17: 2206 | C17: 22-07-2026 | D17: 15426 | E17: FAN | F17: Printing and Packaging | G17: 3201010016 | H17: Guarantee Card -4801 | I17: Pcs | J17: 5250 | K17: 8986.68 | L17: 5000 | M17: 8558.74 | N17: 250 | O17: 427.94 | P17: PENDING | Q17: 144 | R17: 46228.398 | AK17: August | AL17: 2026 | AM17: =AK17&AL17 -> August2026
... A34: 102 | B34: 2206 | C34: 22-07-2026 | D34: 0 | E34: FAN | F34: Printing and Packaging | G34: 3201010043 | H34: PP Poly (L=5``, W=5``, T=0.045mm) With Logo Print | I34: KG | J34: 50 | K34: 16018.69 | L34: 0 | M34: 0 | N34: 50 | O34: 16018.69 | P34: PENDING | Q34: 144 | R34: 46228.398 | AK34: August | AL34: 2026 | AM34: =AK34&AL34 -> August2026
A35: 105 | B35: 2174 | C35: 46241 | D35: 0 | E35: FAN | F35: Printing and Packaging | G35: 3201010051 | H35: Body Sticker - 5603 | I35: Pcs | J35: 2000 | K35: 636.02 | L35: 0 | M35: 0 | N35: 2000 | O35: 636.02 | P35: CHECKED | Q35: 144 | R35: 46211.672 | AK35: August | AL35: 2026 | AM35: =AK35&AL35 -> August2026
A36: 117 | B36: 2174 | C36: 46241 | D36: 14786 | E36: FAN | F36: Printing and Packaging | G36: 3201010064 | H36: Guarantee Card -5603 | I36: Pcs | J36: 3000 | K36: 9026.09 | L36: 3000 | M36: 9026.09 | N36: 0 | O36: 0 | P36: CHECKED | Q36: 144 | R36: 46211.672 | AK36: August | AL36: 2026 | AM36: =AK36&AL36 -> August2026
A37: 128 | B37: 2219 | C37: 26-07-2026 | D37: 1.5358153e+19 | E37: FAN | F37: Printing and Packaging | G37: 3201010073 | H37: Capacitor Master Carton-Fan | I37: Pcs | J37: 3400 | K37: 59751.3 | L37: 3400 | M37: 59751.3 | N37: 0 | O37: 0 | P37: PENDING | Q37: 144 | R37: 46229.685 | AK37: August | AL37: 2026 | AM37: =AK37&AL37 -> August2026
A38: 131 | B38: 2219 | C38: 26-07-2026 | D38: 15361 | E38: FAN | F38: Printing and Packaging | G38: 3201010074 | H38: Capacitor Inner box 2.5 µF -Fan | I38: Pcs | J38: 6000 | K38: 46956.52 | L38: 6000 | M38: 46956.52 | N38: 0 | O38: 0 | P38: PENDING | Q38: 144 | R38: 46229.685 | AK38: August | AL38: 2026 | AM38: =AK38&AL38 -> August2026
A39: 134 | B39: 2219 | C39: 26-07-2026 | D39: 153341536115349 | E39: FAN | F39: Printing and Packaging | G39: 3201010075 | H39: Capacitor Inner box 3.5 µF -Fan | I39: Pcs | J39: 7100 | K39: 55565.22 | L39: 6272 | M39: 49085.22 | N39: 828 | O39: 6480 | P39: PENDING | Q39: 144 | R39: 46229.685 | AK39: August | AL39: 2026 | AM39: =AK39&AL39 -> August2026
A40: 136 | B40: 2219 | C40: 26-07-2026 | D40: 15334 | E40: FAN | F40: Printing and Packaging | G40: 3201010076 | H40: Capacitor Warranty Card 2.5 µF -Fan | I40: Pcs | J40: 71900 | K40: 12504.35 | L40: 71900 | M40: 12504.35 | N40: 0 | O40: 0 | P40: PENDING | Q40: 144 | R40: 46229.685 | AK40: August | AL40: 2026 | AM40: =AK40&AL40 -> August2026
A41: 138 | B41: 2219 | C41: 26-07-2026 | D41: 15334 | E41: FAN | F41: Printing and Packaging | G41: 3201010077 | H41: Capacitor Warranty Card 3.5 µF -Fan | I41: Pcs | J41: 85600 | K41: 14886.96 | L41: 85600 | M41: 14886.96 | N41: 0 | O41: 0 | P41: PENDING | Q41: 144 | R41: 46229.685 | AK41: August | AL41: 2026 | AM41: =AK41&AL41 -> August2026
A42: 141 | B42: 2219 | C42: 26-07-2026 | D42: 1.5453157e+44 | E42: FAN | F42: Printing and Packaging | G42: 3201010079 | H42: 8 Inch Exhaust Fan Body Carton (Alu) | I42: Pcs | J42: 5565 | K42: 237117.39 | L42: 5561 | M42: 236946.96 | N42: 4 | O42: 170.43 | P42: PENDING | Q42: 144 | R42: 46229.685 | AK42: August | AL42: 2026 | AM42: =AK42&AL42 -> August2026
A43: 144 | B43: 2219 | C43: 26-07-2026 | D43: 1.5631154e+34 | E43: FAN | F43: Printing and Packaging | G43: 3201010080 | H43: 10 Inch Exhaust Fan Body Carton (Alu) | I43: Pcs | J43: 11025 | K43: 615482.61 | L43: 2316 | M43: 129293.22 | N43: 8709 | O43: 486189.39 | P43: PENDING | Q43: 144 | R43: 46229.685 | AK43: August | AL43: 2026 | AM43: =AK43&AL43 -> August2026
A44: 147 | B44: 2219 | C44: 26-07-2026 | D44: 1551415334 | E44: FAN | F44: Printing and Packaging | G44: 3201010081 | H44: Aero Flow Sticker | I44: Pcs | J44: 20000 | K44: 4128.81 | L44: 20000 | M44: 4128.81 | N44: 0 | O44: 0 | P44: PENDING | Q44: 144 | R44: 46229.685 | AK44: August | AL44: 2026 | AM44: =AK44&AL44 -> August2026
A45: 149 | B45: 2219 | C45: 26-07-2026 | D45: 15353 | E45: FAN | F45: Printing and Packaging | G45: 3201010083 | H45: Warranty Card (Aero Flow) | I45: Pcs | J45: 17000 | K45: 4655.48 | L45: 12000 | M45: 3286.22 | N45: 5000 | O45: 1369.26 | P45: PENDING | Q45: 144 | R45: 46229.685 | AK45: August | AL45: 2026 | AM45: =AK45&AL45 -> August2026
A46: 154 | B46: 2219 | C46: 26-07-2026 | D46: 15334 | E46: FAN | F46: Printing and Packaging | G46: 700100035 | H46: QC Pass Sticker (Fan)- Blue Color | I46: Pcs | J46: 20000 | K46: 5043.48 | L46: 20000 | M46: 5043.48 | N46: 0 | O46: 0 | P46: PENDING | Q46: 144 | R46: 46229.685 | AK46: August | AL46: 2026 | AM46: =AK46&AL46 -> August2026
A47: 2 | B47: 2209 | C47: 22-07-2026 | D47: 0 | E47: FAN | F47: MEP | G47: 3101010016 | H47: Super Wire (SWG 33) / 0.253mm | I47: KG | J47: 11000 | K47: 21115739 | L47: 0 | M47: 0 | N47: 11000 | O47: 21115739 | P47: PENDING | Q47: 144 | R47: 46228.357 | AK47: August | AL47: 2026 | AM47: =AK47&AL47 -> August2026
A48: 4 | B48: 2209 | C48: 22-07-2026 | D48: 0 | E48: FAN | F48: MEP | G48: 3101010017 | H48: Super Wire (SWG 34) / 0.233mm | I48: KG | J48: 1500 | K48: 3046328.5 | L48: 0 | M48: 0 | N48: 1500 | O48: 3046328.5 | P48: PENDING | Q48: 144 | R48: 46228.357 | AK48: August | AL48: 2026 | AM48: =AK48&AL48 -> August2026
... A89: 144 | B89: 2216 | C89: 23-07-2026 | D89: 0 | E89: FAN | F89: MEP | G89: 700100023 | H89: MS Rivet Armature (FAN) | I89: KG | J89: 50 | K89: 8750 | L89: 0 | M89: 0 | N89: 50 | O89: 8750 | P89: CHECKED | Q89: 144 | R89: 46229.679 | AK89: August | AL89: 2026 | AM89: =AK89&AL89 -> August2026
B91: August to September | C91: 46254 | D91: 46284 | AK91: August | AL91: 2026 | AM91: =AK91&AL91 -> August2026
A92: {=IFERROR(_xlfn.VSTACK(_xlfn._xlws.FILTER('BSIC Entry'!A12:R1030,('BSIC Entry'!AA12:AA1030>=C91)*('BSIC Entry'!AA12:AA1030<=D91),""),_xlfn._xlws.FILTER('Plastic Entry'!A12:R1030,('Plastic Entry'!AA12:AA1030>=C91)*('Plastic Entry'!AA12:AA1030<=D91),"")),"No Data")} -> 4 | B92: 2282 | C92: 20-08-2026 | D92: 0 | E92: FAN | F92: Printing and Packaging | G92: 3202010001 | H92: HDPE Poly (L=22``, W=18``, T=0.025mm) | I92: KG | J92: 0 | K92: 0 | L92: 0 | M92: 0 | N92: 0 | O92: 0 | P92: CHECKED | Q92: 144 | R92: 46260.682 | AK92: September | AL92: 2026 | AM92: =AK92&AL92 -> September2026
A93: 11 | B93: 2282 | C93: 20-08-2026 | D93: 0 | E93: FAN | F93: Printing and Packaging | G93: 3202010008 | H93: HDPE Poly (L=24``, W=20``, T=0.025mm) | I93: KG | J93: 150 | K93: 43296.01 | L93: 0 | M93: 0 | N93: 150 | O93: 43296.01 | P93: CHECKED | Q93: 144 | R93: 46260.682 | AK93: September | AL93: 2026 | AM93: =AK93&AL93 -> September2026
A94: 23 | B94: 2283 | C94: 20-08-2026 | D94: 0 | E94: FAN | F94: Printing and Packaging | G94: 3201010002 | H94: FAN Shank Paper | I94: Pcs | J94: 129780 | K94: 199052.04 | L94: 0 | M94: 0 | N94: 129780 | O94: 199052.04 | P94: CHECKED | Q94: 144 | R94: 46260.691 | AK94: September | AL94: 2026 | AM94: =AK94&AL94 -> September2026
A95: 26 | B95: 2283 | C95: 20-08-2026 | D95: 0 | E95: FAN | F95: Printing and Packaging | G95: 3201010006 | H95: Body Sticker Speed King | I95: Pcs | J95: 10500 | K95: 3152.5 | L95: 0 | M95: 0 | N95: 10500 | O95: 3152.5 | P95: CHECKED | Q95: 144 | R95: 46260.691 | AK95: September | AL95: 2026 | AM95: =AK95&AL95 -> September2026
A96: 29 | B96: 2283 | C96: 20-08-2026 | D96: 0 | E96: FAN | F96: Printing and Packaging | G96: 3201010008 | H96: Body Sticker-3601 | I96: Pcs | J96: 5000 | K96: 1453.25 | L96: 0 | M96: 0 | N96: 5000 | O96: 1453.25 | P96: CHECKED | Q96: 144 | R96: 46260.691 | AK96: September | AL96: 2026 | AM96: =AK96&AL96 -> September2026
A97: 34 | B97: 2283 | C97: 20-08-2026 | D97: 0 | E97: FAN | F97: Printing and Packaging | G97: 3201010010 | H97: Fan Canopy Sticker | I97: Pcs | J97: 60000 | K97: 29486.1 | L97: 0 | M97: 0 | N97: 60000 | O97: 29486.1 | P97: CHECKED | Q97: 144 | R97: 46260.691 | AK97: September | AL97: 2026 | AM97: =AK97&AL97 -> September2026
A98: 35 | B98: 2283 | C98: 20-08-2026 | D98: 0 | E98: FAN | F98: Printing and Packaging | G98: 3201010011 | H98: Canopy Sticker Speed King | I98: Pcs | J98: 20000 | K98: 8769.68 | L98: 0 | M98: 0 | N98: 20000 | O98: 8769.68 | P98: CHECKED | Q98: 144 | R98: 46260.691 | AK98: September | AL98: 2026 | AM98: =AK98&AL98 -> September2026
A99: 38 | B99: 2283 | C99: 20-08-2026 | D99: 0 | E99: FAN | F99: Printing and Packaging | G99: 3201010013 | H99: Fan Down Pipe Sticker | I99: Pcs | J99: 21000 | K99: 7852.18 | L99: 0 | M99: 0 | N99: 21000 | O99: 7852.18 | P99: CHECKED | Q99: 144 | R99: 46260.691 | AK99: September | AL99: 2026 | AM99: =AK99&AL99 -> September2026
A100: 44 | B100: 2282 | C100: 20-08-2026 | D100: 0 | E100: FAN | F100: Printing and Packaging | G100: 3201010014 | H100: Fan QC Sticker | I100: Pcs | J100: 0 | K100: 0 | L100: 0 | M100: 0 | N100: 0 | O100: 0 | P100: CHECKED | Q100: 144 | R100: 46260.682 | AK100: September | AL100: 2026 | AM100: =AK100&AL100 -> September2026
A101: 45 | B101: 2283 | C101: 20-08-2026 | D101: 0 | E101: FAN | F101: Printing and Packaging | G101: 3201010014 | H101: Fan QC Sticker | I101: Pcs | J101: 43000 | K101: 9702.23 | L101: 0 | M101: 0 | N101: 43000 | O101: 9702.23 | P101: CHECKED | Q101: 144 | R101: 46260.691 | AK101: September | AL101: 2026 | AM101: =AK101&AL101 -> September2026
A102: 48 | B102: 2283 | C102: 20-08-2026 | D102: 0 | E102: FAN | F102: Printing and Packaging | G102: 3201010015 | H102: Guarantee Card -5601 | I102: Pcs | J102: 21210 | K102: 31002.2 | L102: 0 | M102: 0 | N102: 21210 | O102: 31002.2 | P102: CHECKED | Q102: 144 | R102: 46260.691 | AK102: September | AL102: 2026 | AM102: =AK102&AL102 -> September2026
A103: 50 | B103: 2283 | C103: 20-08-2026 | D103: 0 | E103: FAN | F103: Printing and Packaging | G103: 3201010017 | H103: Guarantee Card Speed King | I103: Pcs | J103: 10500 | K103: 23464.27 | L103: 0 | M103: 0 | N103: 10500 | O103: 23464.27 | P103: CHECKED | Q103: 144 | R103: 46260.691 | AK103: September | AL103: 2026 | AM103: =AK103&AL103 -> September2026
A104: 53 | B104: 2283 | C104: 20-08-2026 | D104: 0 | E104: FAN | F104: Printing and Packaging | G104: 3201010018 | H104: Guarantee Card -2401,3601 | I104: Pcs | J104: 10500 | K104: 12811.67 | L104: 0 | M104: 0 | N104: 10500 | O104: 12811.67 | P104: CHECKED | Q104: 144 | R104: 46260.691 | AK104: September | AL104: 2026 | AM104: =AK104&AL104 -> September2026
... A180: 143 | B180: 2291 | C180: 22-08-2026 | D180: 0 | E180: FAN | F180: MEP | G180: 3102010019 | H180: MEP Cable Tie -3.5x150mm | I180: Pcs | J180: 15000 | K180: 3782.61 | L180: 0 | M180: 0 | N180: 15000 | O180: 3782.61 | P180: CHECKED | Q180: 144 | R180: 46260.692 | AK180: September | AL180: 2026 | AM180: =AK180&AL180 -> September2026
AK181: September | AL181: 2026 | AM181: =AK181&AL181 -> September2026
AK182: September | AL182: 2026 | AM182: =AK182&AL182 -> September2026

Sheet BOM
A1: SL | B1: Category | C1: Item Code | D1: Item Description | E1: Unit | F1: Quantity | G1: Name
A2: 1 | B2: Ceiling Raw | C2: 3101010023 | D2: FAN Ampere Tube-04 no | E2: Mtr | F2: 0.129 | G2: Ex-08 Copper
A3: 2 | B3: Ceiling Raw | C3: 3101010094 | D3: Soldering Wire | E3: KG | F3: 0.001 | G3: Ex-08 Copper
A4: 3 | B4: Exhaust Raw | C4: 3102010013 | D4: 5/32 Inch, 9mm Screw | E4: KG | F4: 0.009 | G4: Ex-08 Copper
A5: 4 | B5: Exhaust Raw | C5: 3202010002 | D5: 8 Inch Exhasust Fan Body Carton | E5: Pcs | F5: 1 | G5: Ex-08 Copper
A6: 5 | B6: Exhaust Raw | C6: 3202010016 | D6: Air Fresher Sticker | E6: Pcs | F6: 1 | G6: Ex-08 Copper
A7: 6 | B7: Exhaust Raw | C7: 3102010012 | D7: Cable 2x23/0.0076 | E7: Mtr | F7: 0.62 | G7: Ex-08 Copper
A8: 7 | B8: Exhaust Raw | C8: 3102010001 | D8: Exhaust Fan Base (8``) | E8: Pcs | F8: 1 | G8: Ex-08 Copper
A9: 8 | B9: Exhaust Raw | C9: 3102010004 | D9: Exhaust Fan Blade (8``) | E9: Pcs | F9: 1 | G9: Ex-08 Copper
A10: 9 | B10: Exhaust Raw | C10: 3102010016 | D10: Exhaust Fan Capacitor 1.0 (8``) | E10: Pcs | F10: 1 | G10: Ex-08 Copper
A11: 10 | B11: Exhaust Raw | C11: 3102010007 | D11: Exhaust Fan Capacitor Box | E11: Pcs | F11: 1 | G11: Ex-08 Copper
A12: 11 | B12: Exhaust Raw | C12: 3102010009 | D12: Exhaust Fan Clam | E12: Pcs | F12: 1 | G12: Ex-08 Copper
A13: 12 | B13: Exhaust Raw | C13: 3102010002 | D13: Exhaust Fan Cover (8``) | E13: Pcs | F13: 1 | G13: Ex-08 Copper
... A23: 22 | B23: Exhaust Raw | C23: 3202010001 | D23: HDPE Poly 18x22``-(Std.W.- 0.006206 kg) | E23: KG | F23: 0.015 | G23: Ex-08 Copper
A24: 23 | B24: Exhaust Raw | C24: 3102010019 | D24: MEP Cable Tie -3.5x150mm | E24: Pcs | F24: 1 | G24: Ex-08 Copper | K24: Ex-08 Copper
A25: 24 | B25: Exhaust Raw | C25: 3202010007 | D25: PP Band Fita | E25: KG | F25: 0.006 | G25: Ex-08 Copper | K25: Ex-10 Copper
A26: 25 | B26: Packing Materials - FAN | C26: 3201010046 | D26: Carton Tape - (W=60mm,L=200m, MEP Print) | E26: Mtr | F26: 1.099 | G26: Ex-08 Copper | K26: Ex-10 Aluminium
A27: 26 | B27: Packing Materials - FAN | C27: 3201010014 | D27: Fan QC Sticker | E27: Pcs | F27: 1 | G27: Ex-08 Copper | K27: Ex-08 Aluminium
A28: 27 | B28: Packing Materials - FAN | C28: 3201010062 | D28: MEP Hologram Sticker | E28: Pcs | F28: 1 | G28: Ex-08 Copper
A29: 1 | B29: Ceiling Raw | C29: 3101010023 | D29: FAN Ampere Tube-04 no | E29: Mtr | F29: 0.129 | G29: Ex-10 Copper
A30: 2 | B30: Ceiling Raw | C30: 3101010094 | D30: Soldering Wire | E30: KG | F30: 0.001 | G30: Ex-10 Copper
A31: 3 | B31: Exhaust Raw | C31: 3202010009 | D31: 10 Inch Exhasust Fan Body Carton | E31: Pcs | F31: 1 | G31: Ex-10 Copper
A32: 4 | B32: Exhaust Raw | C32: 3102010013 | D32: 5/32 Inch, 9mm Screw | E32: KG | F32: 0.009 | G32: Ex-10 Copper
A33: 5 | B33: Exhaust Raw | C33: 3202010016 | D33: Air Fresher Sticker | E33: Pcs | F33: 1 | G33: Ex-10 Copper
A34: 6 | B34: Exhaust Raw | C34: 3102010012 | D34: Cable 2x23/0.0076 | E34: Mtr | F34: 0.62 | G34: Ex-10 Copper
A35: 7 | B35: Exhaust Raw | C35: 3202010010 | D35: Exhaust Fan Base (10``) | E35: Pcs | F35: 1 | G35: Ex-10 Copper
A36: 8 | B36: Exhaust Raw | C36: 3202010017 | D36: Exhaust Fan Blade (10``) | E36: Pcs | F36: 1 | G36: Ex-10 Copper
A37: 9 | B37: Exhaust Raw | C37: 3102010025 | D37: Exhaust Fan Capacitor 1.2 (10``) | E37: Pcs | F37: 1 | G37: Ex-10 Copper
A38: 10 | B38: Exhaust Raw | C38: 3102010007 | D38: Exhaust Fan Capacitor Box | E38: Pcs | F38: 1 | G38: Ex-10 Copper
A39: 11 | B39: Exhaust Raw | C39: 3102010009 | D39: Exhaust Fan Clam | E39: Pcs | F39: 1 | G39: Ex-10 Copper
... A108: 26 | B108: Packing Materials - FAN | C108: 3201010014 | D108: Fan QC Sticker | E108: Pcs | F108: 1 | G108: Ex-08 Aluminium
A109: 27 | B109: Packing Materials - FAN | C109: 3201010062 | D109: MEP Hologram Sticker | E109: Pcs | F109: 1 | G109: Ex-08 Aluminium | J109: Capacitor 2.5
A110: 1 | B110: Ceiling Raw | C110: 3101010138 | D110: MEP Capacitor 2.5 µF (450VAC) | E110: Pcs | F110: 1 | G110: Capacitor 2.5 | J110: Capacitor 3.5
A111: 2 | B111: Packing Materials - FAN | C111: 3201010074 | D111: Capacitor Inner box 2.5 µF -Fan | E111: Pcs | F111: 0.0834 | G111: Capacitor 2.5
A112: 3 | B112: Packing Materials - FAN | C112: 3201010073 | D112: Capacitor Master Carton-Fan | E112: Pcs | F112: 0.0209 | G112: Capacitor 2.5
A113: 4 | B113: Packing Materials - FAN | C113: 3201010076 | D113: Capacitor Warranty Card 2.5 µF -Fan | E113: Pcs | F113: 1 | G113: Capacitor 2.5
A114: 5 | B114: Packing Materials - FAN | C114: 3201010046 | D114: Carton Tape - (W=60mm,L=200m, MEP Print) | E114: Mtr | F114: 0.0286 | G114: Capacitor 2.5
A115: 6 | B115: Packing Materials - FAN | C115: 3201010078 | D115: Zipper poly (3 x 4) inch -Fan | E115: KG | F115: 0.00086 | G115: Capacitor 2.5
A116: 1 | B116: Ceiling Raw | C116: 3101010139 | D116: MEP Capacitor 3.5 µF (450VAC) | E116: Pcs | F116: 1 | G116: Capacitor 3.5
A117: 2 | B117: Packing Materials - FAN | C117: 3201010075 | D117: Capacitor Inner box 3.5 µF -Fan | E117: Pcs | F117: 0.0834 | G117: Capacitor 3.5
A118: 3 | B118: Packing Materials - FAN | C118: 3201010073 | D118: Capacitor Master Carton-Fan | E118: Pcs | F118: 0.0209 | G118: Capacitor 3.5
A119: 4 | B119: Packing Materials - FAN | C119: 3201010077 | D119: Capacitor Warranty Card 3.5 µF -Fan | E119: Pcs | F119: 1 | G119: Capacitor 3.5
A120: 5 | B120: Packing Materials - FAN | C120: 3201010046 | D120: Carton Tape - (W=60mm,L=200m, MEP Print) | E120: Mtr | F120: 0.0286 | G120: Capacitor 3.5
A121: 6 | B121: Packing Materials - FAN | C121: 3201010078 | D121: Zipper poly (3 x 4) inch -Fan | E121: KG | F121: 0.00086 | G121: Capacitor 3.5
A122: 1 | B122: Ceiling Raw | C122: 3101010135 | D122: Ball Bearing 6202 -(CnU) | E122: Pcs | F122: 1 | G122: CF 3601
... A149: 28 | B149: Packing Materials - FAN | C149: 3201010003 | D149: Tissue Paper | E149: Pcs | F149: 0.52 | G149: CF 3601
A150: 29 | B150: FAN SFG | C150: SFG1010027 | D150: Complete Armature 5.5 Circle 16mm | E150: Pcs | F150: 1 | G150: CF 3601
A151: 30 | B151: FAN SFG | C151: SFG1010070 | D151: Complete Canopy Big - 4801, 5601, 5603 | E151: Set | F151: 1 | G151: CF 3601
A152: 31 | B152: FAN SFG | C152: SFG1010065 | D152: Complete Down Pipe 10 Inch -(5602,3601,2401)- Ivory | E152: Pcs | F152: 1 | G152: CF 3601
A153: 32 | B153: FAN SFG | C153: SFG1010039 | D153: Complete Rotor 5.5 Circle 15.5mm | E153: Pcs | F153: 1 | G153: CF 3601
A154: 33 | B154: FAN SFG | C154: SFG1010081 | D154: MEP Fan Regulator - 3601, 4801, 5601, 5603 | E154: Pcs | F154: 1 | G154: CF 3601
A155: 34 | B155: FAN SFG | C155: SFG1010015 | D155: Painting Bottom Cover-3601 (184mm) - Ivory | E155: Pcs | F155: 1 | G155: CF 3601
A156: 35 | B156: FAN SFG | C156: SFG1010006 | D156: Painting Top Cover-3601 (184mm) - Ivory | E156: Pcs | F156: 1 | G156: CF 3601
A157: 36 | B157: FAN SFG | C157: SFG1010072 | D157: 3601 Hero Ceiling Fan Blade - Ivory | E157: Set | F157: 1 | G157: CF 3601
A158: 1 | B158: Ceiling Raw | C158: 3101010135 | D158: Ball Bearing 6202 -(CnU) | E158: Pcs | F158: 1 | G158: CF 2401
A159: 2 | B159: Ceiling Raw | C159: 3101010136 | D159: Ball Bearing 6203 (CnU) | E159: Pcs | F159: 1 | G159: CF 2401
A160: 3 | B160: Ceiling Raw | C160: 3101010077 | D160: Blade/Body Screw 12.7x6mm,H=10mm (220/kg) | E160: KG | F160: 0.048 | G160: CF 2401
A161: 4 | B161: Ceiling Raw | C161: 3101010035 | D161: Capacitor 2.2 uF | E161: Pcs | F161: 1 | G161: CF 2401
A162: 5 | B162: Ceiling Raw | C162: 3101010080 | D162: Capacitor Cover | E162: Pcs | F162: 1 | G162: CF 2401
A163: 6 | B163: Ceiling Raw | C163: 3101010023 | D163: FAN Ampere Tube-04 no | E163: Mtr | F163: 0.16 | G163: CF 2401
A164: 7 | B164: Ceiling Raw | C164: 3101010112 | D164: Flaxible Cable 14x0.0076 - Black | E164: Mtr | F164: 0.61 | G164: CF 2401
A165: 8 | B165: Ceiling Raw | C165: 3101010090 | D165: Flaxible Cable 14x0.0076 - Red | E165: Mtr | F165: 0.61 | G165: CF 2401
A166: 9 | B166: Ceiling Raw | C166: 3101010038 | D166: Golden Powder | E166: KG | F166: 0.0001 | G166: CF 2401
A167: 10 | B167: Ceiling Raw | C167: 3101010108 | D167: NC / ABC Thinner | E167: Ltr | F167: 0.001 | G167: CF 2401
A168: 11 | B168: Ceiling Raw | C168: 3101010054 | D168: Paint Clear | E168: Ltr. | F168: 0.0005 | G168: CF 2401
A169: 12 | B169: Ceiling Raw | C169: 3101010084 | D169: Plastic XL Cap | E169: Pcs | F169: 1 | G169: CF 2401
... A185: 28 | B185: Packing Materials - FAN | C185: 3201010003 | D185: Tissue Paper | E185: Pcs | F185: 0.52 | G185: CF 2401
A186: 29 | B186: FAN SFG | C186: SFG1010071 | D186: 2401 Super Ceiling Fan Blade - Ivory | E186: Set | F186: 1 | G186: CF 2401
A187: 30 | B187: FAN SFG | C187: SFG1010027 | D187: Complete Armature 5.5 Circle 16mm | E187: Pcs | F187: 1 | G187: CF 2401
A188: 31 | B188: FAN SFG | C188: SFG1010070 | D188: Complete Canopy Big - 4801, 5601, 5603 | E188: Set | F188: 1 | G188: CF 2401
A189: 32 | B189: FAN SFG | C189: SFG1010065 | D189: Complete Down Pipe 10 Inch -(5602,3601,2401)- Ivory | E189: Pcs | F189: 1 | G189: CF 2401
A190: 33 | B190: FAN SFG | C190: SFG1010039 | D190: Complete Rotor 5.5 Circle 15.5mm | E190: Pcs | F190: 1 | G190: CF 2401
A191: 34 | B191: FAN SFG | C191: SFG1010014 | D191: Painting Bottom Cover-2401 (184mm) - Ivory | E191: Pcs | F191: 1 | G191: CF 2401
A192: 35 | B192: FAN SFG | C192: SFG1010005 | D192: Painting Top Cover-2401 (184mm)- Ivory | E192: Pcs | F192: 1 | G192: CF 2401
A193: 36 | B193: FAN SFG | C193: SFG1010071 | D193: 2401 Super Ceiling Fan Blade - Ivory | E193: Set | F193: 1 | G193: CF 2401
A194: 1 | B194: Ceiling Raw | C194: 3101010135 | D194: Ball Bearing 6202 -(CnU) | E194: Pcs | F194: 1 | G194: CF 4801
A195: 2 | B195: Ceiling Raw | C195: 3101010136 | D195: Ball Bearing 6203 (CnU) | E195: Pcs | F195: 1 | G195: CF 4801
A196: 3 | B196: Ceiling Raw | C196: 3101010077 | D196: Blade/Body Screw 12.7x6mm,H=10mm (220/kg) | E196: KG | F196: 0.024 | G196: CF 4801
A197: 4 | B197: Ceiling Raw | C197: 3101010075 | D197: Body Screw 18x6mm,H=10mm (200/kg) | E197: KG | F197: 0.016 | G197: CF 4801
A198: 5 | B198: Ceiling Raw | C198: 3101010034 | D198: Capacitor 2.5 uF (BM) | E198: Pcs | F198: 1 | G198: CF 4801
A199: 6 | B199: Ceiling Raw | C199: 3101010080 | D199: Capacitor Cover | E199: Pcs | F199: 1 | G199: CF 4801
A200: 7 | B200: Ceiling Raw | C200: 3101010023 | D200: FAN Ampere Tube-04 no | E200: Mtr | F200: 0.16 | G200: CF 4801
A201: 8 | B201: Ceiling Raw | C201: 3101010112 | D201: Flaxible Cable 14x0.0076 - Black | E201: Mtr | F201: 0.61 | G201: CF 4801
A202: 9 | B202: Ceiling Raw | C202: 3101010090 | D202: Flaxible Cable 14x0.0076 - Red | E202: Mtr | F202: 0.61 | G202: CF 4801
A203: 10 | B203: Ceiling Raw | C203: 3101010038 | D203: Golden Powder | E203: KG | F203: 0.0001 | G203: CF 4801
A204: 11 | B204: Ceiling Raw | C204: 3101010108 | D204: NC / ABC Thinner | E204: Ltr | F204: 0.001 | G204: CF 4801
A205: 12 | B205: Ceiling Raw | C205: 3101010054 | D205: Paint Clear | E205: Ltr. | F205: 0.0005 | G205: CF 4801
... A222: 29 | B222: Packing Materials - FAN | C222: 3201010003 | D222: Tissue Paper | E222: Pcs | F222: 0.52 | G222: CF 4801
A223: 30 | B223: FAN SFG | C223: SFG1010028 | D223: Complete Armature 6 Circle 16mm | E223: Pcs | F223: 1 | G223: CF 4801
A224: 31 | B224: FAN SFG | C224: SFG1010070 | D224: Complete Canopy Big - 4801, 5601, 5603 | E224: Set | F224: 1 | G224: CF 4801
A225: 32 | B225: FAN SFG | C225: SFG1010064 | D225: Complete Down Pipe 10 Inch- 4801, 5601, 5603 - Ivory | E225: Pcs | F225: 1 | G225: CF 4801
A226: 33 | B226: FAN SFG | C226: SFG1010040 | D226: Complete Rotor 6 Circle 15.5mm | E226: Pcs | F226: 1 | G226: CF 4801
A227: 34 | B227: FAN SFG | C227: SFG1010082 | D227: Completed Clamp with Accessories - 4801, 5601, 5603 | E227: Set | F227: 1 | G227: CF 4801
A228: 35 | B228: FAN SFG | C228: SFG1010081 | D228: MEP Fan Regulator - 3601, 4801, 5601, 5603 | E228: Pcs | F228: 1 | G228: CF 4801
A229: 36 | B229: FAN SFG | C229: SFG1010016 | D229: Painting Bottom Cover-4801 (220mm) - Ivory | E229: Pcs | F229: 1 | G229: CF 4801
A230: 37 | B230: FAN SFG | C230: SFG1010007 | D230: Painting Top Cover-4801 (220mm) - Ivory | E230: Pcs | F230: 1 | G230: CF 4801
A231: 38 | B231: FAN SFG | C231: SFG1010073 | D231: 4801 Popular Ceiling Fan Blade - Ivory | E231: Set | F231: 1 | G231: CF 4801
A232: 1 | B232: Ceiling Raw | C232: 3101010135 | D232: Ball Bearing 6202 -(CnU) | E232: Pcs | F232: 1 | G232: CF 5607
A233: 2 | B233: Ceiling Raw | C233: 3101010136 | D233: Ball Bearing 6203 (CnU) | E233: Pcs | F233: 1 | G233: CF 5607
A234: 3 | B234: Ceiling Raw | C234: 3101010077 | D234: Blade/Body Screw 12.7x6mm,H=10mm (220/kg) | E234: KG | F234: 0.032 | G234: CF 5607
...

Sheet SFG Accessories
B1: MEP FAN LTD.
B2: =TODAY() -> 46264
B3: Daily Fan Accessories SFG Report
A4: Date | B4: Date | C4: Day | D4: Item Name | E4: Opening | F4: Daily Production | G4: Consumption (Assemble Floor) | H4: Closing | I4: Remarks
A5: =IF(AND(E5<>"",#REF!<> ""),#REF!+ 1, "") -> #REF! | B5: 46249 | C5: =B5 -> 46249 | D5: Complete Down Pipe 10 Inch- 4801, 5601, 5603 - Ivory | E5: {='[2]SFG Accessories'!$E$5:$I$854} -> 7409 | F5: 960 | G5: 1700 | H5: 6669 | I5: 0
A6: =IF(AND(E5<>"",#REF!<> ""),#REF!+ 1, "") -> #REF! | D6: Complete Down Pipe 10 Inch -(5602,3601,2401)- Ivory | E6: 7100 | F6: 0 | G6: 0 | H6: 7100 | I6: 0
A7: =IF(AND(E5<>"",#REF!<> ""),#REF!+ 1, "") -> #REF! | D7: Complete Canopy Big - 4801, 5601, 5603 | E7: 3417 | F7: 2530 | G7: 1700 | H7: 4247 | I7: 0
A8: =IF(AND(E5<>"",#REF!<> ""),#REF!+ 1, "") -> #REF! | D8: Complete Canopy Small-5602 | E8: 1280 | F8: 0 | G8: 0 | H8: 1280 | I8: 0
A9: =IF(AND(E5<>"",#REF!<> ""),#REF!+ 1, "") -> #REF! | D9: Completed Clamp with Accessories - 4801, 5601, 5603 | E9: 6260 | F9: 580 | G9: 1700 | H9: 5140 | I9: 0
A10: =IF(AND(E10<>"", A5<>""), A5+1, "") -> #REF! | B10: 46250 | C10: =B10 -> 46250 | D10: Complete Down Pipe 10 Inch- 4801, 5601, 5603 - Ivory | E10: 6669 | F10: 2265 | G10: 965 | H10: 7969 | I10: 0
A11: =IF(AND(E10<>"", A6<>""), A6+1, "") -> #REF! | D11: Complete Down Pipe 10 Inch -(5602,3601,2401)- Ivory | E11: 7100 | F11: 0 | G11: 0 | H11: 7100 | I11: 0
A12: =IF(AND(E10<>"", A7<>""), A7+1, "") -> #REF! | D12: Complete Canopy Big - 4801, 5601, 5603 | E12: 4247 | F12: 2810 | G12: 965 | H12: 6092 | I12: 0
A13: =IF(AND(E10<>"", A8<>""), A8+1, "") -> #REF! | D13: Complete Canopy Small-5602 | E13: 1280 | F13: 0 | G13: 0 | H13: 1280 | I13: 0
